Workbook

Sheet Cover
B2: MICRON TECHNOLOGY, INC. (NASDAQ: MU)
B3: Discounted Cash Flow Valuation
B5: Prepared By: | C5: Siddhanth Balakrishnan
B6: Date: | C6: 46277
B8: MODEL PARAMETERS
B9: Valuation Date | C9: 46268
B10: Currency & Units | C10: US$ in millions except per share
B11: Fiscal year end | C11: Thursday nearest 31 August
B12: Historical period | C12: FY2022A – FY2025A, as reported
B13: Bridge year | C13: FY2026E - 9M reported + FQ4 estimate
B14: Forecast Period | C14: FY2027E - FY2032E (6 years)
B15: Valuation Method | C15: DCF of unlevered free cash flow, discounted at WACC; cross-checked with trading comparables
B16: Terminal Value | C16: Perpetuity growth on normalised FY2033E cash flow (g computed, capped at the 10-year Treasury); exit EV/EBITDA as cross-check
B17: Discounting | C17: Mid-year Convention
B18: Market price reference | C18: ="$"&TEXT('Raw Data'!D177,"#,##0.00")&" as of "&'Raw Data'!E177 -> $927.60 as of 15-Sep-2026
B19: Net debt basis | C19: FY2026E closing balance sheet (estimated; last reported is FQ3-26, 28-May-26)
B22: Formatting Key
B23: 1234.5 | C23: Hardcoded input — typed by hand on this tab
B24: 1234.5 | C24: Formula or link — calculated, do not type over
B25: 1234.5 | C25: Scenario switch or assumption needing attention
B27: Tab Index
B28: Tab | C28: Purpose
B29: Cover | C29: Parameters, formatting key, tab index, disclaimer
B30: Executive Summary | C30: Valuation range, key financials, charts
B31: Assumptions | C31: Scenario switch and every forecast driver
B32: Raw Data | C32: As-reported financials and footnote data
B33: Historical Drivers | C33: Drivers computed off actuals
B34: Schedules | C34: Revenue, cost, PP&E, working capital, debt, shares, tax
B35: Model | C35: Income statement, cash flow, balance sheet
B36: WACC | C36: Cost of capital build
B37: DCF | C37: Free cash flow, terminal value, equity bridge
B38: Comps | C38: Peer multiples and P/B floor
B39: Scenarios | C39: Cases, probability weighting, sensitivities
... B41: Sources | C41: Every external number, with citation
B44: Status and Disclaimer
B45: Personal project for educational purposes. Not investment advice.

Sheet Executive Summary
B2: =Cover!B2 -> MICRON TECHNOLOGY, INC. (NASDAQ: MU)
B3: Discounted cash flow valuation | Executive summary
B6: THE CALL
B7: RECOMMENDATION | D7: TARGET PRICE ($) | F7: CURRENT PRICE ($) | H7: UPSIDE / (DOWNSIDE) | J7: IMPLIED FY27E EV/EBITDA | L7: MODEL CHECKS
B8: =Scenarios!I46 -> SELL | D8: =Scenarios!I42 -> 284.13116 | F8: =Scenarios!I38 -> 927.6 | H8: =Scenarios!I43 -> -0.69369215 | J8: =(Scenarios!I42*Scenarios!G18-Scenarios!G16)/Scenarios!G29 -> 2.2759042 | L8: =Checks!H28 -> ALL CHECKS PASS
B9: Buy > +15% · Sell < -15% to target | D9: Probability-weighted DCF (25/50/25) | F9: Close, 15-Sep-2026 | H9: Target vs. current price | J9: EV at target / Base FY2027E EBITDA | L9: See Checks tab
B10: Thesis | C10: Micron is earning record margins on an AI-driven memory shortage: FY2026E revenue of ~$129bn is 3.5x FY2025 and gross margin is ~80%. Memory is a commodity, and every past price spike has been followed by a collapse as new supply arrives. Our base case lets prices peak in FY2027E, fall 45% in FY2028E and keep easing, while cost per bit falls 8% a year. On that path the DCF is worth $247 a share; even the Bull case ($515) sits well below the $927.60 price. To justify today's price the market needs ~11% growth forever or a ~38x exit multiple. Rating: SELL, target = probability-weighted value.
B12: VALUATION SUMMARY
B13: Case | C13: Probability | D13: Enterprise value | E13: Net cash | F13: Equity value | G13: Diluted shares | H13: Implied price | I13: Upside % | J13: EV/EBITDA FY27E | K13: P/B | L13: Terminal value % | M13: Exit-multiple price
B14: Bear case | C14: =Scenarios!F41 -> 0.25 | D14: =Scenarios!F15 -> 100530.04 | E14: =Scenarios!F16 -> 45796.481 | F14: =Scenarios!F17 -> 146326.52 | G14: =Scenarios!F18 -> 1150 | H14: =Scenarios!F10 -> 127.24045 | I14: =Scenarios!F12 -> -0.86282832 | J14: =Scenarios!F20 -> 1.2782422 | K14: =Scenarios!F21 -> 1.0746806 | L14: =Scenarios!F19 -> 0.20174256 | M14: =Scenarios!F11 -> 198.20869
B15: Base case | C15: =Scenarios!G41 -> 0.5 | D15: =Scenarios!G15 -> 238365.89 | E15: =Scenarios!G16 -> 45796.481 | F15: =Scenarios!G17 -> 284162.37 | G15: =Scenarios!G18 -> 1150 | H15: =Scenarios!G10 -> 247.09772 | I15: =Scenarios!G12 -> -0.73361609 | J15: =Scenarios!G20 -> 1.9309113 | K15: =Scenarios!G21 -> 2.0870022 | L15: =Scenarios!G19 -> 0.32835097 | M15: =Scenarios!G11 -> 333.11753
B16: Bull case | C16: =Scenarios!H41 -> 0.25 | D16: =Scenarios!H15 -> 546555.59 | E16: =Scenarios!H16 -> 45796.481 | F16: =Scenarios!H17 -> 592352.08 | G16: =Scenarios!H18 -> 1150 | H16: =Scenarios!H10 -> 515.08876 | I16: =Scenarios!H12 -> -0.44470811 | J16: =Scenarios!H20 -> 3.46259 | K16: =Scenarios!H21 -> 4.3504708 | L16: =Scenarios!H19 -> 0.48357963 | M16: =Scenarios!H11 -> 582.57188
B17: Probability-weighted | C17: =SUM(C14:C16) -> 1 | D17: =Scenarios!I15 -> 280954.35 | E17: =Scenarios!I16 -> 45796.481 | F17: =Scenarios!I17 -> 326750.84 | G17: =Scenarios!I18 -> 1150 | H17: =Scenarios!I10 -> 284.13116 | I17: =Scenarios!I12 -> -0.69369215 | M17: =Scenarios!I11 -> 361.75391
B19: BASE CASE | Q19: ="LIVE CASE: "&UPPER(INDEX(Assumptions!$C$27:$C$29,Assumptions!$D$7)) -> LIVE CASE: BASE
H20: Projected | V20: Projected
B21: Fiscal year | C21: ($ in millions) | D21: =R$21 -> FY2022A | E21: =S$21 -> FY2023A | F21: =T$21 -> FY2024A | G21: =U$21 -> FY2025A | H21: =V$21 -> FY2026E | I21: =W$21 -> FY2027E | J21: =X$21 -> FY2028E | K21: =Y$21 -> FY2029E | ... N21: =AB$21 -> FY2032E | Q21: Fiscal year | R21: FY2022A | S21: FY2023A | T21: FY2024A | U21: FY2025A | V21: FY2026E | W21: FY2027E | X21: FY2028E | Y21: FY2029E | Z21: FY2030E | AA21: FY2031E | AB21: FY2032E
B22: Revenue | D22: 30758 | E22: 15540 | F22: 25111 | G22: 37378 | H22: 128959 | I22: 145667.62 | J22: 92134.769 | K22: 69981.931 | L22: 72846.275 | M22: 71045.642 | N22: 69290.759 | Q22: Revenue | R22: =Model!F10 -> 30758 | S22: =Model!G10 -> 15540 | T22: =Model!H10 -> 25111 | U22: =Model!I10 -> 37378 | V22: =Model!J10 -> 128959 | W22: =Model!K10 -> 145667.62 | X22: =Model!L10 -> 92134.769 | Y22: =Model!M10 -> 69981.931 | ... AB22: =Model!P10 -> 69290.759
B23: % growth | E23: -0.49476559 | F23: 0.61589447 | G23: 0.48851101 | H23: 2.4501311 | I23: 0.12956536 | J23: -0.3675 | K23: -0.2404395 | L23: 0.040929753 | M23: -0.024718253 | N23: -0.024700781 | Q23: % growth | S23: =Model!G11 -> -0.49476559 | T23: =Model!H11 -> 0.61589447 | U23: =Model!I11 -> 0.48851101 | V23: =Model!J11 -> 2.4501311 | W23: =Model!K11 -> 0.12956536 | X23: =Model!L11 -> -0.3675 | Y23: =Model!M11 -> -0.2404395 | Z23: =Model!N11 -> 0.040929753 | ... AB23: =Model!P11 -> -0.024700781
B24: Gross profit | D24: 13898 | E24: -1416 | F24: 5613 | G24: 14873 | H24: 103457 | I24: 119859.6 | J24: 64829.88 | K24: 40627.257 | L24: 41611.095 | M24: 37805.657 | N24: 33918.911 | Q24: Gross profit | R24: =Schedules!F261 -> 13898 | S24: =Schedules!G261 -> -1416 | T24: =Schedules!H261 -> 5613 | U24: =Schedules!I261 -> 14873 | V24: =Schedules!J261 -> 103457 | W24: =Schedules!K261 -> 119859.6 | X24: =Schedules!L261 -> 64829.88 | Y24: =Schedules!M261 -> 40627.257 | ... AB24: =Schedules!P261 -> 33918.911
B25: % margin | D25: 0.45184993 | E25: -0.091119691 | F25: 0.22352754 | G25: 0.39790786 | H25: 0.80224723 | I25: 0.82282937 | J25: 0.70364185 | K25: 0.58053924 | L25: 0.57121789 | M25: 0.53213196 | N25: 0.48951564 | Q25: % margin | R25: =Schedules!F262 -> 0.45184993 | S25: =Schedules!G262 -> -0.091119691 | T25: =Schedules!H262 -> 0.22352754 | U25: =Schedules!I262 -> 0.39790786 | V25: =Schedules!J262 -> 0.80224723 | W25: =Schedules!K262 -> 0.82282937 | X25: =Schedules!L262 -> 0.70364185 | Y25: =Schedules!M262 -> 0.58053924 | ... AB25: =Schedules!P262 -> 0.48951564
B26: EBITDA | D26: 16818 | E26: 2011 | F26: 9084 | G26: 18122 | H26: 105878.33 | I26: 123447.35 | J26: 70878.559 | K26: 48617.832 | L26: 51159.389 | M26: 48751.452 | N26: 46116.364 | Q26: EBITDA | R26: =Model!F13 -> 16818 | S26: =Model!G13 -> 2011 | T26: =Model!H13 -> 9084 | U26: =Model!I13 -> 18122 | V26: =Model!J13 -> 105878.33 | W26: =Model!K13 -> 123447.35 | X26: =Model!L13 -> 70878.559 | Y26: =Model!M13 -> 48617.832 | ... AB26: =Model!P13 -> 46116.364
B27: % margin | D27: 0.54678458 | E27: 0.12940798 | F27: 0.36175381 | G27: 0.48483065 | H27: 0.82102322 | I27: 0.84745914 | J27: 0.7692922 | K27: 0.69471978 | L27: 0.70229245 | M27: 0.68619905 | N27: 0.66554854 | Q27: % margin | R27: =Model!F14 -> 0.54678458 | S27: =Model!G14 -> 0.12940798 | T27: =Model!H14 -> 0.36175381 | U27: =Model!I14 -> 0.48483065 | V27: =Model!J14 -> 0.82102322 | W27: =Model!K14 -> 0.84745914 | X27: =Model!L14 -> 0.7692922 | Y27: =Model!M14 -> 0.69471978 | ... AB27: =Model!P14 -> 0.66554854
B28: EBIT | D28: 9702 | E28: -5745 | F28: 1304 | G28: 9770 | H28: 96729 | I28: 112554.22 | J28: 56826.881 | K28: 31859.501 | L28: 32004.948 | M28: 27280.351 | N28: 22385.847 | Q28: EBIT | R28: =Model!F15 -> 9702 | S28: =Model!G15 -> -5745 | T28: =Model!H15 -> 1304 | U28: =Model!I15 -> 9770 | V28: =Model!J15 -> 96729 | W28: =Model!K15 -> 112554.22 | X28: =Model!L15 -> 56826.881 | Y28: =Model!M15 -> 31859.501 | ... AB28: =Model!P15 -> 22385.847
B29: Net income | D29: 8687 | E29: -5833 | F29: 778 | G29: 8539 | H29: 82874.655 | I29: 96992.878 | J29: 51852.433 | K29: 31942.905 | L29: 32864.86 | M29: 29651.694 | N29: 26305.502 | Q29: Net income | R29: =Schedules!F281 -> 8687 | S29: =Schedules!G281 -> -5833 | T29: =Schedules!H281 -> 778 | U29: =Schedules!I281 -> 8539 | V29: =Schedules!J281 -> 82874.655 | W29: =Schedules!K281 -> 96992.878 | X29: =Schedules!L281 -> 51852.433 | Y29: =Schedules!M281 -> 31942.905 | ... AB29: =Schedules!P281 -> 26305.502
B30: EPS ($) | D30: 7.7424242 | E30: -5.336688 | F30: 0.69588551 | G30: 7.5902222 | H30: 72.064917 | I30: 84.341633 | J30: 45.089072 | K30: 27.776439 | L30: 28.578139 | M30: 25.784082 | N30: 22.87435 | Q30: EPS ($) | R30: =Schedules!F286 -> 7.7424242 | S30: =Schedules!G286 -> -5.336688 | T30: =Schedules!H286 -> 0.69588551 | U30: =Schedules!I286 -> 7.5902222 | V30: =Schedules!J286 -> 72.064917 | W30: =Schedules!K286 -> 84.341633 | X30: =Schedules!L286 -> 45.089072 | Y30: =Schedules!M286 -> 27.776439 | ... AB30: =Schedules!P286 -> 22.87435
B31: Capex | D31: 12067 | E31: 7676 | F31: 8386 | G31: 15857 | H31: 30985.333 | I31: 36416.905 | J31: 32247.169 | K31: 26593.134 | L31: 25496.196 | M31: 24865.975 | N31: 24251.766 | Q31: Capex | R31: =-Schedules!F307 -> 12067 | S31: =-Schedules!G307 -> 7676 | T31: =-Schedules!H307 -> 8386 | U31: =-Schedules!I307 -> 15857 | V31: =-Schedules!J307 -> 30985.333 | W31: =-Schedules!K307 -> 36416.905 | X31: =-Schedules!L307 -> 32247.169 | Y31: =-Schedules!M307 -> 26593.134 | ... AB31: =-Schedules!P307 -> 24251.766
B32: % of sales | D32: 0.3923207 | E32: 0.49395109 | F32: 0.33395723 | G32: 0.42423351 | H32: 0.24027275 | I32: 0.25 | J32: 0.35 | K32: 0.38 | L32: 0.35 | M32: 0.35 | N32: 0.35 | Q32: % of sales | R32: =R31/R22 -> 0.3923207 | S32: =S31/S22 -> 0.49395109 | T32: =T31/T22 -> 0.33395723 | U32: =U31/U22 -> 0.42423351 | V32: =V31/V22 -> 0.24027275 | W32: =W31/W22 -> 0.25 | X32: =X31/X22 -> 0.35 | Y32: =Y31/Y22 -> 0.38 | ... AB32: =AB31/AB22 -> 0.35
B33: Unlevered FCF | D33: 2310.8458 | E33: -7228.7216 | F33: -1615.2774 | G33: 2738.4943 | H33: 42180.471 | I33: 74252.158 | J33: 41335.314 | K33: 22807 | L33: 22240.669 | M33: 21875.47 | N33: 20519.229 | Q33: Unlevered FCF | R33: =Model!F25 -> 2310.8458 | S33: =Model!G25 -> -7228.7216 | T33: =Model!H25 -> -1615.2774 | U33: =Model!I25 -> 2738.4943 | V33: =Model!J25 -> 42180.471 | W33: =Model!K25 -> 74252.158 | X33: =Model!L25 -> 41335.314 | Y33: =Model!M25 -> 22807 | ... AB33: =Model!P25 -> 20519.229
B34: Net debt / EBITDA | D34: -0.24212154 | E34: 1.4380905 | F34: 0.46730515 | G34: 0.14573447 | H34: -0.43253874 | I34: -0.97758616 | J34: -2.3251929 | K34: -3.9417791 | L34: -4.2733834 | M34: -5.0450256 | N34: -5.9119542 | Q34: Net debt / EBITDA | R34: =Model!F49 -> -0.24212154 | S34: =Model!G49 -> 1.4380905 | T34: =Model!H49 -> 0.46730515 | U34: =Model!I49 -> 0.14573447 | V34: =Model!J49 -> -0.43253874 | W34: =Model!K49 -> -0.97758616 | X34: =Model!L49 -> -2.3251929 | Y34: =Model!M49 -> -3.9417791 | ... AB34: =Model!P49 -> -5.9119542
B36: BULL CASE
H37: Projected
B38: Fiscal year | C38: ($ in millions) | D38: =R$21 -> FY2022A | E38: =S$21 -> FY2023A | F38: =T$21 -> FY2024A | G38: =U$21 -> FY2025A | H38: =V$21 -> FY2026E | I38: =W$21 -> FY2027E | J38: =X$21 -> FY2028E | K38: =Y$21 -> FY2029E | ... N38: =AB$21 -> FY2032E
B39: Revenue | D39: 30758 | E39: 15540 | F39: 25111 | G39: 37378 | H39: 128959 | I39: 180920.79 | J39: 160114.9 | K39: 114176.91 | L39: 107466.58 | M39: 110418.35 | N39: 112695.57
B40: % growth | E40: -0.49476559 | F40: 0.61589447 | G40: 0.48851101 | H40: 2.4501311 | I40: 0.40293266 | J40: -0.115 | K40: -0.28690639 | L40: -0.058771339 | M40: 0.027466825 | N40: 0.020623527
B41: Gross profit | D41: 13898 | E41: -1416 | F41: 5613 | G41: 14873 | H41: 103457 | I41: 154102.39 | J41: 131000.84 | K41: 82343.305 | L41: 73009.473 | M41: 73117.394 | N41: 72585.186
B42: % margin | D42: 0.45184993 | E42: -0.091119691 | F42: 0.22352754 | G42: 0.39790786 | H42: 0.80224723 | I42: 0.85176716 | J42: 0.81816771 | K42: 0.72119049 | L42: 0.67936907 | M42: 0.66218517 | N42: 0.64408201
B43: EBITDA | D43: 16818 | E43: 2011 | F43: 9084 | G43: 18122 | H43: 105878.33 | I43: 157845.89 | J43: 137939.91 | K43: 92260.582 | L43: 85252.083 | M43: 87447.657 | N43: 88986.663
B44: % margin | D44: 0.54678458 | E44: 0.12940798 | F44: 0.36175381 | G44: 0.48483065 | H44: 0.82102322 | I44: 0.87245854 | J44: 0.86150578 | K44: 0.80804936 | L44: 0.79328922 | M44: 0.79196671 | N44: 0.78961992
B45: EBIT | D45: 9702 | E45: -5745 | F45: 1304 | G45: 9770 | H45: 96729 | I45: 146797.02 | J45: 122997.85 | K45: 73575.549 | L45: 63403.326 | M45: 62592.089 | N45: 61052.123
B46: Net income | D46: 8687 | E46: -5833 | F46: 778 | G46: 8539 | H46: 82874.655 | I46: 126099.25 | J46: 108700.18 | K46: 69214.779 | L46: 62375.018 | M46: 63306.298 | N46: 63661.541
B47: EPS ($) | D47: 7.7424242 | E47: -5.336688 | F47: 0.69588551 | G47: 7.5902222 | H47: 72.064917 | I47: 109.65152 | J47: 94.5219 | K47: 60.186765 | L47: 54.239146 | M47: 55.048955 | N47: 55.357861
B48: Capex | D48: 12067 | E48: 7676 | F48: 8386 | G48: 15857 | H48: 30985.333 | I48: 39802.575 | J48: 44832.173 | K48: 36536.612 | L48: 32239.975 | M48: 33125.505 | N48: 33808.67
B49: % of sales | D49: 0.3923207 | E49: 0.49395109 | F49: 0.33395723 | G49: 0.42423351 | H49: 0.24027275 | I49: 0.22 | J49: 0.28 | K49: 0.32 | L49: 0.3 | M49: 0.3 | N49: 0.3
B50: Unlevered FCF | D50: 2310.8458 | E50: -7228.7216 | F50: -1615.2774 | G50: 2738.4943 | H50: 42180.471 | I50: 94501.994 | J50: 81432.075 | K50: 54886.336 | L50: 46917.93 | M50: 46809.877 | N50: 48065.741
B51: Net debt / EBITDA | D51: -0.24212154 | E51: 1.4380905 | F51: 0.46730515 | G51: 0.14573447 | H51: -0.43253874 | I51: -0.89283453 | J51: -1.6366209 | K51: -3.1051436 | L51: -3.999481 | M51: -4.5383349 | N51: -5.1197389
B53: BEAR CASE
H54: Projected
B55: Fiscal year | C55: ($ in millions) | D55: =R$21 -> FY2022A | E55: =S$21 -> FY2023A | F55: =T$21 -> FY2024A | G55: =U$21 -> FY2025A | H55: =V$21 -> FY2026E | I55: =W$21 -> FY2027E | J55: =X$21 -> FY2028E | K55: =Y$21 -> FY2029E | ... N55: =AB$21 -> FY2032E
B56: Revenue | D56: 30758 | E56: 15540 | F56: 25111 | G56: 37378 | H56: 128959 | I56: 99989.595 | J56: 55213.394 | K56: 44704.463 | L56: 51165.796 | M56: 49779.528 | N56: 48433.435
B57: % growth | E57: -0.49476559 | F57: 0.61589447 | G57: 0.48851101 | H57: 2.4501311 | I57: -0.22464043 | J57: -0.44780861 | K57: -0.190333 | L57: 0.14453442 | M57: -0.027093661 | N57: -0.027041089
B58: Gross profit | D58: 13898 | E58: -1416 | F58: 5613 | G58: 14873 | H58: 103457 | I58: 75354.663 | J58: 30183.511 | K58: 18069.319 | L58: 23119.745 | M58: 20246.249 | N58: 17332.384
B59: % margin | D59: 0.45184993 | E59: -0.091119691 | F59: 0.22352754 | G59: 0.39790786 | H59: 0.80224723 | I59: 0.75362505 | J59: 0.54667008 | K59: 0.40419497 | L59: 0.45185937 | M59: 0.40671838 | N59: 0.35785989
B60: EBITDA | D60: 16818 | E60: 2011 | F60: 9084 | G60: 18122 | H60: 105878.33 | I60: 78647.102 | J60: 35301.095 | K60: 24490.445 | L60: 30569.313 | M60: 28634.052 | N60: 26519.548
B61: % margin | D61: 0.54678458 | E61: 0.12940798 | F61: 0.36175381 | G61: 0.48483065 | H61: 0.82102322 | I61: 0.78655286 | J61: 0.63935745 | K61: 0.54782997 | L61: 0.59745602 | M61: 0.57521744 | N61: 0.54754629
B62: EBIT | D62: 9702 | E62: -5745 | F62: 1304 | G62: 9770 | H62: 96729 | I62: 68049.293 | J62: 22180.512 | K62: 9301.5626 | L62: 13513.598 | M62: 9720.9432 | N62: 5799.3202
B63: Net income | D63: 8687 | E63: -5833 | F63: 778 | G63: 8539 | H63: 82874.655 | I63: 59163.686 | J63: 21671.453 | K63: 11274.576 | L63: 15113.205 | M63: 12223.135 | N63: 9244.4217
B64: EPS ($) | D64: 7.7424242 | E64: -5.336688 | F64: 0.69588551 | G64: 7.5902222 | H64: 72.064917 | I64: 51.446683 | J64: 18.844742 | K64: 9.803979 | L64: 13.141917 | M64: 10.628813 | N64: 8.0386276
B65: Capex | D65: 12067 | E65: 7676 | F65: 8386 | G65: 15857 | H65: 30985.333 | I65: 29996.879 | J65: 24846.027 | K65: 20117.008 | L65: 20466.319 | M65: 19911.811 | N65: 19373.374
B66: % of sales | D66: 0.3923207 | E66: 0.49395109 | F66: 0.33395723 | G66: 0.42423351 | H66: 0.24027275 | I66: 0.3 | J66: 0.45 | K66: 0.45 | L66: 0.4 | M66: 0.4 | N66: 0.4
B67: Unlevered FCF | D67: 2310.8458 | E67: -7228.7216 | F67: -1615.2774 | G67: 2738.4943 | H67: 42180.471 | I67: 49661.701 | J67: 16436.108 | K67: 6152.3332 | L67: 8508.0996 | M67: 8934.1645 | N67: 7888.4964
B68: Net debt / EBITDA | D68: -0.24212154 | E68: 1.4380905 | F68: 0.46730515 | G68: 0.14573447 | H68: -0.43253874 | I68: -1.2217865 | J68: -3.245936 | K68: -5.0334233 | L68: -4.3994162 | M68: -5.1117948 | N68: -5.9376444
B70: KEY ASSUMPTIONS BY CASE | I70: ="SENSITIVITY — "&UPPER(INDEX(Assumptions!$C$27:$C$29,Assumptions!$D$7))&" CASE" -> SENSITIVITY — BASE CASE
B71: Driver | C71: Units | D71: Bear | E71: Base | F71: Bull | I71: Value per share ($) — WACC (rows) vs. long-run growth g (columns)
B72: Revenue growth a year, FY2026E–FY2032E | C72: % | D72: =Scenarios!F27 -> -0.15059346 | E72: =Scenarios!G27 -> -0.098351474 | F72: =Scenarios!H27 -> -0.022216896 | I72: WACC \ g | J72: =Scenarios!F50 -> 0 | K72: =Scenarios!G50 -> 0.005 | L72: =Scenarios!H50 -> 0.0096558191 | M72: =Scenarios!I50 -> 0.02 | N72: =Scenarios!J50 -> 0.03
B73: EBITDA margin, FY2032E | C73: % | D73: =Scenarios!F30 -> 0.54754629 | E73: =Scenarios!G30 -> 0.66554854 | F73: =Scenarios!H30 -> 0.78961992 | I73: =Scenarios!E51 -> 0.105 | J73: =Scenarios!F51 -> 270.28082 | K73: =Scenarios!G51 -> 272.52969 | L73: =Scenarios!H51 -> 274.81206 | M73: =Scenarios!I51 -> 280.68579 | N73: =Scenarios!J51 -> 287.76759
B74: Capex % of sales, FY2027E–FY2032E avg. | C74: % | D74: =Scenarios!F31 -> 0.4 | E74: =Scenarios!G31 -> 0.33833333 | F74: =Scenarios!H31 -> 0.28666667 | I74: =Scenarios!E52 -> 0.115 | J74: =Scenarios!F52 -> 256.15571 | K74: =Scenarios!G52 -> 257.76842 | L74: =Scenarios!H52 -> 259.38738 | M74: =Scenarios!I52 -> 263.47427 | N74: =Scenarios!J52 -> 268.25645
B75: WACC | C75: % | D75: =Scenarios!F36 -> 0.12453408 | E75: =Scenarios!G36 -> 0.12453408 | F75: =Scenarios!H36 -> 0.12453408 | I75: =Scenarios!E53 -> 0.12453408 | J75: =Scenarios!F53 -> 244.73967 | K75: =Scenarios!G53 -> 245.922 | L75: =Scenarios!H53 -> 247.09772 | M75: =Scenarios!I53 -> 250.01735 | N75: =Scenarios!J53 -> 253.34957
B76: Long-run growth g (computed) | C76: % | D76: =Scenarios!F22 -> -0.011055966 | E76: =Scenarios!G22 -> 0.0096558191 | F76: =Scenarios!H22 -> 0.034885871 | I76: =Scenarios!E54 -> 0.135 | J76: =Scenarios!F54 -> 234.00154 | K76: =Scenarios!G54 -> 234.8446 | L76: =Scenarios!H54 -> 235.67469 | M76: =Scenarios!I54 -> 237.70161 | N76: =Scenarios!J54 -> 239.95754
B77: Exit EV/EBITDA multiple | C77: x | D77: =Scenarios!F37 -> 7.77 | E77: =Scenarios!G37 -> 7.77 | F77: =Scenarios!H37 -> 7.77 | I77: =Scenarios!E55 -> 0.145 | J77: =Scenarios!F55 -> 225.13317 | K77: =Scenarios!G55 -> 225.7419 | L77: =Scenarios!H55 -> 226.33564 | M77: =Scenarios!I55 -> 227.76253 | N77: =Scenarios!J55 -> 229.3139
B78: Probability weight | C78: % | D78: =Scenarios!F41 -> 0.25 | E78: =Scenarios!G41 -> 0.5 | F78: =Scenarios!H41 -> 0.25
B80: EXHIBITS
B81: Exhibit 1 — Valuation range vs. current price (football field) | I81: Exhibit 2 — Revenue (bars) and EBITDA margin (labels), FY2022A–FY2032E, Base case
B98: Exhibit 3 — Enterprise value to equity value bridge | I98: Exhibit 4 — Implied share price by case vs. current price
B115: Source: see Sources tab. US$ in millions except per share. Blue = hardcoded input, black = formula or link. Personal project for educational purposes not investment advice.

Sheet Assumptions
C2: =Cover!B2 -> MICRON TECHNOLOGY, INC. (NASDAQ: MU)
C3: Assumptions and Key Drivers
B7: SCENARIO SWITCH: | D7: 2
C10: A. FY2026E INPUTS (Q4 GUIDANCE)
C11: Line item | E11: Units | J11: FY2026E
C12: Q4 revenue | E12: $M | J12: 50000
C13: Q4 gross margin | E13: % | J13: 0.86
C14: Q4 operating expenses | E14: $M | J14: 1860
C15: Q4 tax rate | E15: % | J15: 0.139 | K15: <- Implied based on eps, guidance
C16: Diluted shares | E16: M sh | J16: 1150
C17: Q4 PRODUCT MIX
C18: Q4 DRAM % of revenue | E18: % | J18: =('Raw Data'!L159/'Raw Data'!L162) -> 0.75569278
C19: Q4 NAND % of revenue | E19: % | J19: =('Raw Data'!L160/'Raw Data'!L162) -> 0.23984465
C20: Q4 Other % of revenue | E20: % | J20: =('Raw Data'!L161/'Raw Data'!L162) -> 0.0044625627
C21: FY2026 net capex guidance | E21: $ M | J21: 27000
C23: B. KEY DRIVERS (CHANGE BY CASE)
C24: Line item | E24: Units | K24: FY2027E | L24: FY2028E | M24: FY2029E | N24: FY2030E | O24: FY2031E | P24: FY2032E
C25: 1. DRAM PRICE CHANGE (ASP, Y/Y)
C26: Live | E26: % | K26: =INDEX(K27:K29,$D$7) -> 0.05 | L26: =INDEX(L27:L29,$D$7) -> -0.45 | M26: =INDEX(M27:M29,$D$7) -> -0.35 | N26: =INDEX(N27:N29,$D$7) -> -0.1 | O26: =INDEX(O27:O29,$D$7) -> -0.15 | P26: =INDEX(P27:P29,$D$7) -> -0.15
C27: Bear | E27: % | K27: -0.25 | L27: -0.5 | M27: -0.3 | N27: 0 | O27: -0.15 | P27: -0.15
C28: Base | E28: % | K28: 0.05 | L28: -0.45 | M28: -0.35 | N28: -0.1 | O28: -0.15 | P28: -0.15
C29: Bull | E29: % | K29: 0.25 | L29: -0.25 | M29: -0.4 | N29: -0.2 | O29: -0.12 | P29: -0.12
C30: 2. NAND PRICE CHANGE (ASP, Y/Y)
C31: Live | E31: % | K31: =INDEX(K32:K34,$D$7) -> -0.05 | L31: =INDEX(L32:L34,$D$7) -> -0.45 | M31: =INDEX(M32:M34,$D$7) -> -0.35 | N31: =INDEX(N32:N34,$D$7) -> -0.1 | O31: =INDEX(O32:O34,$D$7) -> -0.18 | P31: =INDEX(P32:P34,$D$7) -> -0.18
C32: Bear | E32: % | K32: -0.3 | L32: -0.5 | M32: -0.3 | N32: 0 | O32: -0.15 | P32: -0.15
C33: Base | E33: % | K33: -0.05 | L33: -0.45 | M33: -0.35 | N33: -0.1 | O33: -0.18 | P33: -0.18
C34: Bull | E34: % | K34: 0.15 | L34: -0.25 | M34: -0.4 | N34: -0.2 | O34: -0.15 | P34: -0.15
C35: 3A. DRAM BIT SHIPMENT GROWTH (Y/Y)
C36: Live | E36: % | K36: =INDEX(K37:K39,$D$7) -> 0.1 | L36: =INDEX(L37:L39,$D$7) -> 0.15 | M36: =INDEX(M37:M39,$D$7) -> 0.16 | N36: =INDEX(N37:N39,$D$7) -> 0.15 | O36: =INDEX(O37:O39,$D$7) -> 0.15 | P36: =INDEX(P37:P39,$D$7) -> 0.15
C37: Bear | E37: % | K37: 0.05 | L37: 0.1 | M37: 0.15 | N37: 0.14 | O37: 0.14 | P37: 0.14
C38: Base | E38: % | K38: 0.1 | L38: 0.15 | M38: 0.16 | N38: 0.15 | O38: 0.15 | P38: 0.15
C39: Bull | E39: % | K39: 0.15 | L39: 0.18 | M39: 0.18 | N39: 0.17 | O39: 0.17 | P39: 0.16
C40: 3B. NAND BIT SHIPMENT GROWTH (Y/Y)
C41: Live | E41: % | K41: =INDEX(K42:K44,$D$7) -> 0.1 | L41: =INDEX(L42:L44,$D$7) -> 0.15 | M41: =INDEX(M42:M44,$D$7) -> 0.2 | N41: =INDEX(N42:N44,$D$7) -> 0.18 | O41: =INDEX(O42:O44,$D$7) -> 0.18 | P41: =INDEX(P42:P44,$D$7) -> 0.18
C42: Bear | E42: % | K42: 0.05 | L42: 0.12 | M42: 0.18 | N42: 0.16 | O42: 0.16 | P42: 0.16
C43: Base | E43: % | K43: 0.1 | L43: 0.15 | M43: 0.2 | N43: 0.18 | O43: 0.18 | P43: 0.18
C44: Bull | E44: % | K44: 0.12 | L44: 0.18 | M44: 0.22 | N44: 0.2 | O44: 0.2 | P44: 0.2
C45: 4. CAPEX % OF REVENUE
C46: Live | E46: % | K46: =INDEX(K47:K49,$D$7) -> 0.25 | L46: =INDEX(L47:L49,$D$7) -> 0.35 | M46: =INDEX(M47:M49,$D$7) -> 0.38 | N46: =INDEX(N47:N49,$D$7) -> 0.35 | O46: =INDEX(O47:O49,$D$7) -> 0.35 | P46: =INDEX(P47:P49,$D$7) -> 0.35
C47: Bear | E47: % | K47: 0.3 | L47: 0.45 | M47: 0.45 | N47: 0.4 | O47: 0.4 | P47: 0.4
C48: Base | E48: % | K48: 0.25 | L48: 0.35 | M48: 0.38 | N48: 0.35 | O48: 0.35 | P48: 0.35
C49: Bull | E49: % | K49: 0.22 | L49: 0.28 | M49: 0.32 | N49: 0.3 | O49: 0.3 | P49: 0.3
C52: C. OPERATING ASSUMPTIONS (SAME IN EVERY CASE)
C53: Line item | E53: Units | J53: FY2026E | K53: FY2027E | L53: FY2028E | M53: FY2029E | N53: FY2030E | O53: FY2031E | P53: FY2032E
C54: REVENUE AND COSTS
C55: Cost per bit decline | E55: % | K55: 0.08 | L55: 0.08 | M55: 0.08 | N55: 0.08 | O55: 0.08 | P55: 0.08
C56: Other revenue % of DRAM + NAND | E56: % | K56: 0.0046 | L56: 0.0046 | M56: 0.0046 | N56: 0.0046 | O56: 0.0046 | P56: 0.0046
C57: R&D growth ($) | E57: % | K57: 0.1 | L57: 0.1 | M57: 0.1 | N57: 0.1 | O57: 0.1 | P57: 0.1
C58: SG&A growth ($) | E58: % | K58: 0.08 | L58: 0.08 | M58: 0.08 | N58: 0.08 | O58: 0.08 | P58: 0.08
C59: Other operating (income) expense | E59: $M | K59: 0 | L59: 0 | M59: 0 | N59: 0 | O59: 0 | P59: 0
C60: CAPEX AND PP&E
C61: Depreciation years, existing assets | E61: years | K61: 7
C62: Depreciation years, new assets | E62: years | K62: 10
C63: Government incentives % of capex | E63: % | K63: 0.08 | L63: 0.08 | M63: 0.08 | N63: 0.08 | O63: 0.08 | P63: 0.08
C64: WORKING CAPITAL
C65: DSO | E65: days | K65: 76 | L65: 76 | M65: 76 | N65: 76 | O65: 76 | P65: 76
C66: DIO | E66: days | K66: 150 | L66: 150 | M66: 150 | N66: 150 | O66: 150 | P66: 150
C67: DPO | E67: days | K67: 128 | L67: 128 | M67: 128 | N67: 128 | O67: 128 | P67: 128
C68: Other current assets days (on COGS) | E68: days | K68: 15 | L68: 15 | M68: 15 | N68: 15 | O68: 15 | P68: 15
C69: Other current liabilities days (on revenue) | E69: days | K69: 16 | L69: 16 | M69: 16 | N69: 16 | O69: 16 | P69: 16
C70: TAX
C71: Effective tax rate | E71: % | K71: 0.15 | L71: 0.15 | M71: 0.15 | N71: 0.15 | O71: 0.15 | P71: 0.15
C72: Statutory tax rate (US federal, memo) | E72: % | K72: 0.21 | L72: 0.21 | M72: 0.21 | N72: 0.21 | O72: 0.21 | P72: 0.21
C73: Deferred tax % of book tax | E73: % | K73: 0 | L73: 0 | M73: 0 | N73: 0 | O73: 0 | P73: 0
C74: SHARES AND CAPITAL RETURNS
C75: Stock-based compensation, FY2026E | E75: $M | J75: 1270
C76: Stock-based compensation growth ($) | E76: % | K76: 0.1 | L76: 0.1 | M76: 0.1 | N76: 0.1 | O76: 0.1 | P76: 0.1
C77: Diluted shares | E77: M sh | K77: 1150 | L77: 1150 | M77: 1150 | N77: 1150 | O77: 1150 | P77: 1150
C78: Buybacks % of stock-based compensation | E78: % | K78: 1 | L78: 1 | M78: 1 | N78: 1 | O78: 1 | P78: 1
C79: Dividends per share, FY2027E | E79: $ | K79: 0.6
C80: Dividends per share growth | E80: % | L80: 0.1 | M80: 0.1 | N80: 0.1 | O80: 0.1 | P80: 0.1
C81: INTEREST AND DEBT
C82: Interest rate on cash and investments | E82: % | K82: 0.035 | L82: 0.035 | M82: 0.035 | N82: 0.035 | O82: 0.035 | P82: 0.035
C83: Interest rate on senior notes | E83: % | K83: 0.04 | L83: 0.04 | M83: 0.04 | N83: 0.04 | O83: 0.04 | P83: 0.04
C84: Senior notes issuance / (repayment) | E84: $M | K84: 0 | L84: 0 | M84: 0 | N84: 0 | O84: -261 | P84: -996
C85: Interest rate on revolver (SOFR + spread) | E85: % | F85: 0.0362 | K85: =$F$85+1% -> 0.0462 | L85: =$F$85+1% -> 0.0462 | M85: =$F$85+1% -> 0.0462 | N85: =$F$85+1% -> 0.0462 | O85: =$F$85+1% -> 0.0462 | P85: =$F$85+1% -> 0.0462
C86: Interest rate on finance leases | E86: % | K86: 0.0472 | L86: 0.0472 | M86: 0.0472 | N86: 0.0472 | O86: 0.0472 | P86: 0.0472
C87: Finance lease additions / (repayments) | E87: $M | K87: 0 | L87: 0 | M87: 0 | N87: 0 | O87: 0 | P87: 0
C88: Finance leases outstanding, FY2025 | E88: $M | J88: 3044
C89: Finance leases outstanding, Q3 FY26 | E89: $M | J89: 2670
C90: Equity-method income and other non-operating | E90: $M | K90: 0 | L90: 0 | M90: 0 | N90: 0 | O90: 0 | P90: 0
C92: D. VALUATION (SAME IN EVERY CASE)
C93: Mid-year discounting adjustment (0.5 = mid-year, 0 = year-end) | E93: years | K93: 0.5

Sheet Raw Data
B2: =Cover!B2 -> MICRON TECHNOLOGY, INC. (NASDAQ: MU)
B3: Raw data | As-reported historical financials and market inputs
B6: SOURCE & SCOPE
B7: Company | D7: Micron Technology, Inc.
B8: Ticker / exchange | D8: MU / NASDAQ
B9: Fiscal year end | D9: Thursday nearest Aug 31
B10: Reporting currency | D10: USD
B11: Units | D11: Millions, except per-share data
B12: Filings used | D12: 10-K FY2021–FY2025; 10-Q FY2026 Q1–Q3; 8-K FY2026
B13: Data pulled on | D13: =Cover!C6 -> 46277
B14: Prepared by | D14: =Cover!C5 -> Siddhanth Balakrishnan | I14: #0000FF
B16: CONSOLIDATED STATEMENTS OF OPERATIONS
B17: Line item | C17: Units | D17: FY2021 | E17: FY2022 | F17: FY2023 | G17: FY2024 | H17: FY2025 | J17: Q1 FY26 | K17: Q2 FY26 | L17: Q3 FY26 | M17: FY26 YTD | O17: Source / filing reference
B18: Revenue | C18: $M | D18: 27705 | E18: 30758 | F18: 15540 | G18: 25111 | H18: 37378 | J18: 13643 | K18: 23860 | L18: 41456 | M18: 78959
B19: Cost of goods sold | C19: $M | D19: 17282 | E19: 16860 | F19: 16956 | G19: 19498 | H19: 22505 | J19: 5997 | K19: 6105 | L19: 6400 | M19: 18502
B20: Gross margin | C20: $M | D20: =D18-D19 -> 10423 | E20: =E18-E19 -> 13898 | F20: =F18-F19 -> -1416 | G20: =G18-G19 -> 5613 | H20: =H18-H19 -> 14873 | J20: =J18-J19 -> 7646 | K20: =K18-K19 -> 17755 | L20: =L18-L19 -> 35056 | M20: =M18-M19 -> 60457
B21: OPERATING EXPENSES
B22: Research and development | C22: $M | D22: 2663 | E22: 3116 | F22: 3114 | G22: 3430 | H22: 3798 | J22: 1171 | K22: 1250 | L22: 1316 | M22: 3737
B23: Selling, general, and administrative | C23: $M | D23: 894 | E23: 1066 | F23: 920 | G23: 1129 | H23: 1205 | J23: 337 | K23: 344 | L23: 407 | M23: 1088
B24: Restructure and asset impairments | C24: $M | D24: 488 | E24: 48 | F24: 171 | G24: 1 | H24: 39
B25: Other operating (income) expense, net | C25: $M | D25: 95 | E25: -34 | F25: 124 | G25: -251 | H25: 61 | J25: 2 | K25: 26 | L25: 15 | M25: 43
B26: Operating income | C26: $M | D26: =D20-SUM(D22:D25) -> 6283 | E26: =E20-SUM(E22:E25) -> 9702 | F26: =F20-SUM(F22:F25) -> -5745 | G26: =G20-SUM(G22:G25) -> 1304 | H26: =H20-SUM(H22:H25) -> 9770 | J26: =J20-SUM(J22:J25) -> 6136 | K26: =K20-SUM(K22:K25) -> 16135 | L26: =L20-SUM(L22:L25) -> 33318 | M26: =M20-SUM(M22:M25) -> 55589
B27: NON-OPERATING INCOME (EXPENSE)
B28: Interest income | C28: $M | D28: 37 | E28: 96 | F28: 468 | G28: 529 | H28: 496 | J28: 139 | K28: 155 | L28: 215 | M28: 509
B29: Interest expense | C29: $M | D29: -183 | E29: -189 | F29: -388 | G29: -562 | H29: -477 | J29: -74 | K29: -32 | L29: 0 | M29: -106
B30: Other non-operating income (expense), net | C30: $M | D30: 81 | E30: -38 | F30: 7 | G30: -31 | H30: -135 | J30: -140 | K30: -98 | L30: -321 | M30: -559
B31: Income before taxes and equity in net income of investees | C31: $M | D31: =D26+D28+D29+D30 -> 6218 | E31: =E26+E28+E29+E30 -> 9571 | F31: =F26+F28+F29+F30 -> -5658 | G31: =G26+G28+G29+G30 -> 1240 | H31: =H26+H28+H29+H30 -> 9654 | J31: =J26+J28+J29+J30 -> 6061 | K31: =K26+K28+K29+K30 -> 16160 | L31: =L26+L28+L29+L30 -> 33212 | M31: =M26+M28+M29+M30 -> 55433
B32: Income tax (provision) benefit | C32: $M | D32: -394 | E32: -888 | F32: -177 | G32: -451 | H32: -1124 | J32: -829 | K32: -2371 | L32: -4978 | M32: -8178
B33: Equity in net income (loss) of equity method investees | C33: $M | D33: 37 | E33: 4 | F33: 2 | G33: -11 | H33: 9 | J33: 8 | K33: -4 | L33: 9 | M33: 13
B34: Net income | C34: $M | D34: =D31+D32+D33 -> 5861 | E34: =E31+E32+E33 -> 8687 | F34: =F31+F32+F33 -> -5833 | G34: =G31+G32+G33 -> 778 | H34: =H31+H32+H33 -> 8539 | J34: =J31+J32+J33 -> 5240 | K34: =K31+K32+K33 -> 13785 | L34: =L31+L32+L33 -> 28243 | M34: =M31+M32+M33 -> 47268
B35: Net income attributable to noncontrolling interests | C35: $M
B36: Net income attributable to Micron | C36: $M | D36: =D34+D35 -> 5861 | E36: =E34+E35 -> 8687 | F36: =F34+F35 -> -5833 | G36: =G34+G35 -> 778 | H36: =H34+H35 -> 8539 | J36: =J34+J35 -> 5240 | K36: =K34+K35 -> 13785 | L36: =L34+L35 -> 28243 | M36: =M34+M35 -> 47268
B37: EARNINGS PER SHARE
B38: Basic | C38: $ | D38: 5.23 | E38: 7.81 | F38: -5.34 | G38: 0.7 | H38: 7.65 | J38: 4.66 | K38: 12.25 | L38: 25.03 | M38: 41.97
B39: Diluted | C39: $ | D39: 5.14 | E39: 7.75 | F39: -5.34 | G39: 0.7 | H39: 7.59 | J39: 4.6 | K39: 12.07 | L39: 24.67 | M39: 41.4
B40: NUMBER OF SHARES USED IN PER SHARE CALCULATIONS
B41: Basic | C41: M sh | D41: 1120 | E41: 1112 | F41: 1093 | G41: 1105 | H41: 1116 | J41: 1125 | K41: 1126 | L41: 1128 | M41: 1126
B42: Diluted | C42: M sh | D42: 1141 | E42: 1122 | F42: 1093 | G42: 1118 | H42: 1125 | J42: 1138 | K42: 1142 | L42: 1145 | M42: 1142
B43: DIVIDENDS
B44: Dividends declared per share | C44: $ | D44: 0.1 | E44: 0.315 | F44: 0.46 | G44: 0.46 | H44: 0.46 | J44: 0.115 | K44: 0.115 | L44: 0.15 | M44: 0.38
B47: CONSOLIDATED BALANCE SHEETS
B48: Line item | C48: Units | D48: FY2021 | E48: FY2022 | F48: FY2023 | G48: FY2024 | H48: FY2025 | J48: Q1 FY26 | K48: Q2 FY26 | L48: Q3 FY26 | M48: Latest | O48: Source / filing reference
B49: ASSETS
B50: Current assets
B51: Cash and equivalents | C51: $M | D51: 7763 | E51: 8262 | F51: 8577 | G51: 7041 | H51: 9642 | L51: 24995 | M51: 24995
B52: Short-term investments | C52: $M | D52: 870 | E52: 1069 | F52: 1017 | G52: 1065 | H52: 665 | L52: 1027 | M52: 1027
B53: Receivables | C53: $M | D53: 5311 | E53: 5130 | F53: 2443 | G53: 6615 | H53: 9265 | L53: 31025 | M53: 31025
B54: Inventories | C54: $M | D54: 4487 | E54: 6663 | F54: 8387 | G54: 8875 | H54: 8355 | L54: 8567 | M54: 8567
B55: Assets held for sale | C55: $M | D55: 974
B56: Other current assets | C56: $M | D56: 502 | E56: 657 | F56: 820 | G56: 776 | H56: 914 | L56: 1123 | M56: 1123
B57: Total current assets | C57: $M | D57: =SUM(D51:D56) -> 19907 | E57: =SUM(E51:E56) -> 21781 | F57: =SUM(F51:F56) -> 21244 | G57: =SUM(G51:G56) -> 24372 | H57: =SUM(H51:H56) -> 28841 | L57: =SUM(L51:L56) -> 66737 | M57: =SUM(M51:M56) -> 66737
B58: Noncurrent assets
B59: Long-term marketable investments | C59: $M | D59: 1765 | E59: 1647 | F59: 844 | G59: 1046 | H59: 1629 | L59: 4106 | M59: 4106
B60: Property, plant, and equipment | C60: $M | D60: 33213 | E60: 38549 | F60: 37928 | G60: 39749 | H60: 46590 | L60: 56426 | M60: 56426
B61: Operating lease right-of-use assets | C61: $M | D61: 551 | E61: 678 | F61: 666 | G61: 645 | H61: 736 | L61: 683 | M61: 683
B62: Intangible assets | C62: $M | D62: 349 | E62: 421 | F62: 404 | G62: 416 | H62: 453 | L62: 473 | M62: 473
B63: Deferred tax assets | C63: $M | D63: 782 | E63: 702 | F63: 756 | G63: 520 | H63: 616 | L63: 700 | M63: 700
B64: Goodwill | C64: $M | D64: 1228 | E64: 1228 | F64: 1150 | G64: 1150 | H64: 1150 | L64: 1150 | M64: 1150
B65: Other noncurrent assets | C65: $M | D65: 1054 | E65: 1277 | F65: 1262 | G65: 1518 | H65: 2783 | L65: 3837 | M65: 3837
B66: Total noncurrent assets | C66: $M | D66: =SUM(D59:D65) -> 38942 | E66: =SUM(E59:E65) -> 44502 | F66: =SUM(F59:F65) -> 43010 | G66: =SUM(G59:G65) -> 45044 | H66: =SUM(H59:H65) -> 53957 | L66: =SUM(L59:L65) -> 67375 | M66: =SUM(M59:M65) -> 67375
B67: Total assets | C67: $M | D67: =D57+D66 -> 58849 | E67: =E57+E66 -> 66283 | F67: =F57+F66 -> 64254 | G67: =G57+G66 -> 69416 | H67: =H57+H66 -> 82798 | L67: =L57+L66 -> 134112 | M67: =M57+M66 -> 134112
B68: LIABILITIES
B69: Current liabilities
B70: Accounts payable and accrued expenses | C70: $M | D70: 5325 | E70: 6090 | F70: 3958 | G70: 7299 | H70: 9649 | L70: 15521 | M70: 15521
B71: Current debt | C71: $M | D71: 155 | E71: 103 | F71: 278 | G71: 431 | H71: 560 | L71: 582 | M71: 582
B72: Other current liabilities | C72: $M | D72: 944 | E72: 1346 | F72: 529 | G72: 1518 | H72: 1245 | L72: 3385 | M72: 3385
B73: Total current liabilities | C73: $M | D73: =SUM(D70:D72) -> 6424 | E73: =SUM(E70:E72) -> 7539 | F73: =SUM(F70:F72) -> 4765 | G73: =SUM(G70:G72) -> 9248 | H73: =SUM(H70:H72) -> 11454 | L73: =SUM(L70:L72) -> 19488 | M73: =SUM(M70:M72) -> 19488
B74: Noncurrent liabilities
B75: Long-term debt | C75: $M | D75: 6621 | E75: 6803 | F75: 13052 | G75: 12966 | H75: 14017 | L75: 5140 | M75: 5140
B76: Noncurrent operating lease liabilities | C76: $M | D76: 504 | E76: 610 | F76: 603 | G76: 610 | H76: 701 | L76: 654 | M76: 654
B77: Noncurrent unearned government incentives | C77: $M | D77: 808 | E77: 589 | F77: 727 | G77: 550 | H77: 1018 | L77: 1020 | M77: 1020
B78: Other noncurrent liabilities | C78: $M | D78: 559 | E78: 835 | F78: 987 | G78: 911 | H78: 1443 | L78: 7086 | M78: 7086
B79: Total noncurrent liabilities | C79: $M | D79: =SUM(D75:D78) -> 8492 | E79: =SUM(E75:E78) -> 8837 | F79: =SUM(F75:F78) -> 15369 | G79: =SUM(G75:G78) -> 15037 | H79: =SUM(H75:H78) -> 17179 | L79: =SUM(L75:L78) -> 13900 | M79: =SUM(M75:M78) -> 13900
B80: Total liabilities | C80: $M | D80: =D79+D73 -> 14916 | E80: =E79+E73 -> 16376 | F80: =F79+F73 -> 20134 | G80: =G79+G73 -> 24285 | H80: =H79+H73 -> 28633 | L80: =L79+L73 -> 33388 | M80: =M79+M73 -> 33388
B81: MICRON SHAREHOLDERS' EQUITY
B82: Common stock, $0.10 par value | C82: $M | D82: 122 | E82: 123 | F82: 124 | G82: 125 | H82: 127 | L82: 128 | M82: 128
B83: Additional capital | C83: $M | D83: 9453 | E83: 10197 | F83: 11036 | G83: 12115 | H83: 13339 | L83: 14442 | M83: 14442
B84: Retained earnings | C84: $M | D84: 39051 | E84: 47274 | F84: 40824 | G84: 40877 | H84: 48583 | L84: 94682 | M84: 94682
B85: Treasury stock | C85: $M | D85: =-4695 -> -4695 | E85: -7127 | F85: -7552 | G85: -7852 | H85: -7852 | L85: -8502 | M85: -8502
B86: Accumulated other comprehensive income (loss) | C86: $M | D86: 2 | E86: -560 | F86: -312 | G86: -134 | H86: -32 | L86: -26 | M86: -26
B87: Total Micron shareholders' equity | C87: $M | D87: =SUM(D82:D86) -> 43933 | E87: =SUM(E82:E86) -> 49907 | F87: =SUM(F82:F86) -> 44120 | G87: =SUM(G82:G86) -> 45131 | H87: =SUM(H82:H86) -> 54165 | L87: =SUM(L82:L86) -> 100724 | M87: =SUM(M82:M86) -> 100724
B88: Noncontrolling interests in subsidiaries | C88: $M
B89: Total equity | C89: $M | D89: =D87+D88 -> 43933 | E89: =E87+E88 -> 49907 | F89: =F87+F88 -> 44120 | G89: =G87+G88 -> 45131 | H89: =H87+H88 -> 54165 | L89: =L87+L88 -> 100724 | M89: =M87+M88 -> 100724
B90: Total liabilities and equity | C90: $M | D90: =D89+D80 -> 58849 | E90: =E89+E80 -> 66283 | F90: =F89+F80 -> 64254 | G90: =G89+G80 -> 69416 | H90: =H89+H80 -> 82798 | L90: =L89+L80 -> 134112 | M90: =M89+M80 -> 134112
B93: CONSOLIDATED STATEMENTS OF CASH FLOWS
B94: Line item | C94: Units | D94: FY2021 | E94: FY2022 | F94: FY2023 | G94: FY2024 | H94: FY2025 | J94: Q1 FY26 | K94: Q2 FY26 | L94: Q3 FY26 | M94: FY26 YTD | O94: Source / filing reference
B95: CASH FLOWS FROM OPERATING ACTIVITIES
B96: Net income | C96: $M | D96: 5861 | E96: 8687 | F96: -5833 | G96: 778 | H96: 8539 | M96: 47268
B97: Adjustments to reconcile net income to net cash provided by operating activities
B98: Depreciation expense and amortization of intangible assets | C98: $M | D98: 6214 | E98: 7116 | F98: 7756 | G98: 7780 | H98: 8352 | M98: 6862
B99: Amortization of debt discount and other costs | C99: $M | D99: 30
B100: Restructure and asset impairments | C100: $M | D100: 454
B101: Stock-based compensation | C101: $M | D101: 378 | E101: 514 | F101: 596 | G101: 833 | H101: 972 | M101: 954
B102: Provision to write down inventories to net realizable value | C102: $M | D102: 0 | F102: 1831
B103: Goodwill Impairement | C103: $M | D103: 0 | F103: 101
B104: (Gains) losses on debt prepayments, repurchases, and conversions | C104: $M | D104: 1
B105: Change in operating assets and liabilities
B106: Receivables | C106: $M | D106: -1446 | E106: 190 | F106: 2763 | G106: -3581 | H106: -1776 | M106: -19953
B107: Inventories | C107: $M | D107: 866 | E107: -2179 | F107: -3555 | G107: -488 | H107: 520 | M107: -212
B108: Deferred income taxes, net | C108: $M | D108: -50
...

Sheet Historical Drivers
B2: =Cover!B2 -> MICRON TECHNOLOGY, INC. (NASDAQ: MU)
B3: Historical drivers | Ratios computed from Raw Data
B6: PERIOD
B7: Line item | C7: Units | D7: FY2022 | E7: FY2023 | F7: FY2024 | G7: FY2025 | H7: 9M FY26 | J7: Trough | K7: Mid-cycle | L7: Peak | O7: From Raw Data
B8: Days in period | C8: days | D8: 365 | E8: 365 | F8: 365 | G8: 365 | H8: 273 | O8: Typed: 365 for a full year, 273 for the 9 months
B11: A. REVENUE
B12: Line item | C12: Units | D12: FY2022 | E12: FY2023 | F12: FY2024 | G12: FY2025 | H12: 9M FY26 | J12: Trough | K12: Mid-cycle | L12: Peak | O12: From Raw Data
B13: Revenue | C13: $M | D13: ='Raw Data'!E18 -> 30758 | E13: ='Raw Data'!F18 -> 15540 | F13: ='Raw Data'!G18 -> 25111 | G13: ='Raw Data'!H18 -> 37378 | H13: ='Raw Data'!M18 -> 78959 | O13: Row 18
B14: Revenue growth | C14: % | D14: =D13/'Raw Data'!D18 - 1 -> 0.11019672 | E14: =E13/D13 - 1 -> -0.49476559 | F14: =F13/E13 - 1 -> 0.61589447 | G14: =G13/F13 - 1 -> 0.48851101 | O14: Row 18 vs prior year (9M: blank)
B15: PRODUCT MIX
B16: DRAM revenue | C16: $M | D16: ='Raw Data'!E159 -> 22386 | E16: ='Raw Data'!F159 -> 10978 | F16: ='Raw Data'!G159 -> 17603 | G16: ='Raw Data'!H159 -> 28578 | H16: ='Raw Data'!M159 -> 60908 | O16: Row 159
B17: NAND revenue | C17: $M | D17: ='Raw Data'!E160 -> 7811 | E17: ='Raw Data'!F160 -> 4206 | F17: ='Raw Data'!G160 -> 7227 | G17: ='Raw Data'!H160 -> 8503 | H17: ='Raw Data'!M160 -> 17683 | O17: Row 160
B18: DRAM % of revenue | C18: % | D18: =D16/'Raw Data'!E162 -> 0.72781065 | E18: =E16/'Raw Data'!F162 -> 0.70643501 | F18: =F16/'Raw Data'!G162 -> 0.70100753 | G18: =G16/'Raw Data'!H162 -> 0.76456739 | H18: =H16/'Raw Data'!M162 -> 0.77138768 | O18: Row 159 / row 18
B19: NAND % of revenue | C19: % | D19: =D17/'Raw Data'!E162 -> 0.25395019 | E19: =E17/'Raw Data'!F162 -> 0.27065637 | F19: =F17/'Raw Data'!G162 -> 0.28780216 | G19: =G17/'Raw Data'!H162 -> 0.22748676 | H19: =H17/'Raw Data'!M162 -> 0.22395167 | O19: Row 160 / row 18
B20: DRAM revenue growth | C20: % | D20: =D16/'Raw Data'!D159 - 1 -> 0.11712161 | E20: =E16/'Raw Data'!E159 - 1 -> -0.50960422 | F20: =F16/'Raw Data'!F159 - 1 -> 0.60347969 | G20: =G16/'Raw Data'!G159 - 1 -> 0.62347327 | O20: Row 159 vs prior year (9M: blank)
B21: NAND revenue growth | C21: % | D21: =D17/'Raw Data'!D160 - 1 -> 0.1147424 | E21: =E17/'Raw Data'!E160 - 1 -> -0.46152861 | F21: =F17/'Raw Data'!F160 - 1 -> 0.71825963 | G21: =G17/'Raw Data'!G160 - 1 -> 0.17656012 | O21: Row 160 vs prior year (9M: blank)
B22: VOLUME AND PRICING
B23: DRAM bit shipment growth (y/y) | C23: % | D23: ='Raw Data'!E164 -> 0.11 | E23: ='Raw Data'!F164 -> -0.08 | F23: ='Raw Data'!G164 -> 0.45 | G23: ='Raw Data'!H164 -> 0.15 | H23: ='Raw Data'!M164 -> 0.3 | O23: Row 164
B24: DRAM ASP change (y/y) | C24: % | D24: ='Raw Data'!E165 -> 0 | E24: ='Raw Data'!F165 -> -0.48 | F24: ='Raw Data'!G165 -> 0.12 | G24: ='Raw Data'!H165 -> 0.42 | H24: ='Raw Data'!M165 -> 1.4 | O24: Row 165
B25: NAND bit shipment growth (y/y) | C25: % | D25: ='Raw Data'!E166 -> 0.08 | E25: ='Raw Data'!F166 -> 0.08 | F25: ='Raw Data'!G166 -> 0.32 | G25: ='Raw Data'!H166 -> 0.18 | H25: ='Raw Data'!M166 -> 0.22 | O25: Row 166
B26: NAND ASP change (y/y) | C26: % | D26: ='Raw Data'!E167 -> 0.02 | E26: ='Raw Data'!F167 -> -0.52 | F26: ='Raw Data'!G167 -> 0.32 | G26: ='Raw Data'!H167 -> 0 | H26: ='Raw Data'!M167 -> 1.3 | O26: Row 167
B27: Check: DRAM bits x ASP (implied revenue growth) | C27: % | D27: =(1+D23)*(1+D24)-1 -> 0.11 | E27: =(1+E23)*(1+E24)-1 -> -0.5216 | F27: =(1+F23)*(1+F24)-1 -> 0.624 | G27: =(1+G23)*(1+G24)-1 -> 0.633 | H27: =(1+H23)*(1+H24)-1 -> 2.12 | O27: (1 + bits) x (1 + ASP) - 1; compare with DRAM revenue growth
B30: B. MARGINS AND COSTS
B31: Line item | C31: Units | D31: FY2022 | E31: FY2023 | F31: FY2024 | G31: FY2025 | H31: 9M FY26 | J31: Trough | K31: Mid-cycle | L31: Peak | O31: From Raw Data
B32: Gross margin % | C32: % | D32: ='Raw Data'!E20/'Raw Data'!E18 -> 0.45184993 | E32: ='Raw Data'!F20/'Raw Data'!F18 -> -0.091119691 | F32: ='Raw Data'!G20/'Raw Data'!G18 -> 0.22352754 | G32: ='Raw Data'!H20/'Raw Data'!H18 -> 0.39790786 | H32: ='Raw Data'!M20/'Raw Data'!M18 -> 0.76567586 | J32: =MIN(D32:G32) -> -0.091119691 | K32: =AVERAGE(D32:G32) -> 0.24554141 | L32: =MAX(D32:G32) -> 0.45184993 | O32: Row 20 / row 18
B33: R&D % of revenue | C33: % | D33: ='Raw Data'!E22/'Raw Data'!E18 -> 0.10130698 | E33: ='Raw Data'!F22/'Raw Data'!F18 -> 0.2003861 | F33: ='Raw Data'!G22/'Raw Data'!G18 -> 0.13659352 | G33: ='Raw Data'!H22/'Raw Data'!H18 -> 0.10161057 | H33: ='Raw Data'!M22/'Raw Data'!M18 -> 0.04732836 | J33: =MIN(D33:G33) -> 0.10130698 | K33: =AVERAGE(D33:G33) -> 0.13497429 | L33: =MAX(D33:G33) -> 0.2003861 | O33: Row 22 / row 18
B34: R&D growth ($) | C34: % | D34: ='Raw Data'!E22/'Raw Data'!D22 - 1 -> 0.1701089 | E34: ='Raw Data'!F22/'Raw Data'!E22 - 1 -> -0.00064184852 | F34: ='Raw Data'!G22/'Raw Data'!F22 - 1 -> 0.1014772 | G34: ='Raw Data'!H22/'Raw Data'!G22 - 1 -> 0.10728863 | O34: Row 22 vs prior year (9M: blank)
B35: SG&A % of revenue | C35: % | D35: ='Raw Data'!E23/'Raw Data'!E18 -> 0.03465765 | E35: ='Raw Data'!F23/'Raw Data'!F18 -> 0.059202059 | F35: ='Raw Data'!G23/'Raw Data'!G18 -> 0.044960376 | G35: ='Raw Data'!H23/'Raw Data'!H18 -> 0.032238215 | H35: ='Raw Data'!M23/'Raw Data'!M18 -> 0.013779303 | J35: =MIN(D35:G35) -> 0.032238215 | K35: =AVERAGE(D35:G35) -> 0.042764575 | L35: =MAX(D35:G35) -> 0.059202059 | O35: Row 23 / row 18
B36: SG&A growth ($) | C36: % | D36: ='Raw Data'!E23/'Raw Data'!D23-1 -> 0.19239374 | E36: ='Raw Data'!F23/'Raw Data'!E23-1 -> -0.1369606 | F36: ='Raw Data'!G23/'Raw Data'!F23-1 -> 0.22717391 | G36: ='Raw Data'!H23/'Raw Data'!G23-1 -> 0.067316209 | O36: Row 23 vs prior year (9M: blank)
B37: Operating margin % | C37: % | D37: ='Raw Data'!E26/'Raw Data'!E18 -> 0.31543013 | E37: ='Raw Data'!F26/'Raw Data'!F18 -> -0.36969112 | F37: ='Raw Data'!G26/'Raw Data'!G18 -> 0.051929433 | G37: ='Raw Data'!H26/'Raw Data'!H18 -> 0.2613837 | H37: ='Raw Data'!M26/'Raw Data'!M18 -> 0.70402361 | J37: =MIN(D37:G37) -> -0.36969112 | K37: =AVERAGE(D37:G37) -> 0.064763037 | L37: =MAX(D37:G37) -> 0.31543013 | O37: Row 26 / row 18
B38: EBITDA | C38: $M | D38: ='Raw Data'!E26+'Raw Data'!E98 -> 16818 | E38: ='Raw Data'!F26+'Raw Data'!F98 -> 2011 | F38: ='Raw Data'!G26+'Raw Data'!G98 -> 9084 | G38: ='Raw Data'!H26+'Raw Data'!H98 -> 18122 | H38: ='Raw Data'!M26+'Raw Data'!M98 -> 62451 | O38: Row 26 + row 98
B39: EBITDA margin % | C39: % | D39: =D38/D13 -> 0.54678458 | E39: =E38/E13 -> 0.12940798 | F39: =F38/F13 -> 0.36175381 | G39: =G38/G13 -> 0.48483065 | H39: =H38/H13 -> 0.79092947 | J39: =MIN(D39:G39) -> 0.12940798 | K39: =AVERAGE(D39:G39) -> 0.38069425 | L39: =MAX(D39:G39) -> 0.54678458 | O39: EBITDA / revenue
B42: C. CAPEX AND PP&E
B43: Line item | C43: Units | D43: FY2022 | E43: FY2023 | F43: FY2024 | G43: FY2025 | H43: 9M FY26 | J43: Trough | K43: Mid-cycle | L43: Peak | O43: From Raw Data
B44: Capex | C44: $M | D44: =-'Raw Data'!E115 -> 12067 | E44: =-'Raw Data'!F115 -> 7676 | F44: =-'Raw Data'!G115 -> 8386 | G44: =-'Raw Data'!H115 -> 15857 | H44: =-'Raw Data'!M115 -> 19602 | O44: Row 115, shown positive
B45: Capex % of revenue | C45: % | D45: =D44/D13 -> 0.3923207 | E45: =E44/E13 -> 0.49395109 | F45: =F44/F13 -> 0.33395723 | G45: =G44/G13 -> 0.42423351 | H45: =H44/H13 -> 0.24825542 | J45: =MIN(D45:G45) -> 0.33395723 | K45: =AVERAGE(D45:G45) -> 0.41111563 | L45: =MAX(D45:G45) -> 0.49395109 | O45: Capex / row 18
B46: Government incentives received | C46: $M | D46: ='Raw Data'!E119 -> 115 | E46: ='Raw Data'!F119 -> 710 | F46: ='Raw Data'!G119 -> 315 | G46: ='Raw Data'!H119 -> 2005 | H46: ='Raw Data'!M119 -> 2989 | O46: Row 119
B47: Net capex after incentives | C47: $M | D47: =D44-D46 -> 11952 | E47: =E44-E46 -> 6966 | F47: =F44-F46 -> 8071 | G47: =G44-G46 -> 13852 | H47: =H44-H46 -> 16613 | O47: Capex - row 119
B48: D&A | C48: $M | D48: ='Raw Data'!E98 -> 7116 | E48: ='Raw Data'!F98 -> 7756 | F48: ='Raw Data'!G98 -> 7780 | G48: ='Raw Data'!H98 -> 8352 | H48: ='Raw Data'!M98 -> 6862 | O48: Row 98
B49: D&A % of opening PP&E | C49: % | D49: =D48/'Raw Data'!D60 -> 0.21425345 | E49: =E48/'Raw Data'!E60 -> 0.20119847 | F49: =F48/'Raw Data'!F60 -> 0.2051255 | G49: =G48/'Raw Data'!G60 -> 0.21011849 | H49: =H48*$D$8/H$8/'Raw Data'!H60 -> 0.19691927 | J49: =MIN(D49:G49) -> 0.20119847 | K49: =AVERAGE(D49:G49) -> 0.20767398 | L49: =MAX(D49:G49) -> 0.21425345 | O49: Row 98 / prior-year row 60 (9M: annualise)
B50: Capex / D&A | C50: x | D50: =D44/D48 -> 1.695756 | E50: =E44/E48 -> 0.9896854 | F50: =F44/F48 -> 1.077892 | G50: =G44/G48 -> 1.8985872 | H50: =H44/H48 -> 2.8566016 | O50: Capex / row 98
B53: D. WORKING CAPITAL
B54: Line item | C54: Units | D54: FY2022 | E54: FY2023 | F54: FY2024 | G54: FY2025 | H54: 9M FY26 | J54: Trough | K54: Mid-cycle | L54: Peak | O54: From Raw Data
B55: DSO | C55: days | D55: ='Raw Data'!E53/'Historical Drivers'!D13 * 'Historical Drivers'!D8 -> 60.876845 | E55: ='Raw Data'!F53/'Historical Drivers'!E13 * 'Historical Drivers'!E8 -> 57.380631 | F55: ='Raw Data'!G53/'Historical Drivers'!F13 * 'Historical Drivers'!F8 -> 96.152085 | G55: ='Raw Data'!H53/'Historical Drivers'!G13 * 'Historical Drivers'!G8 -> 90.473674 | H55: ='Raw Data'!M53/'Historical Drivers'!H13 * 'Historical Drivers'!H8 -> 107.26865 | J55: =MIN(D55:G55) -> 57.380631 | K55: =AVERAGE(D55:G55) -> 76.220809 | L55: =MAX(D55:G55) -> 96.152085 | O55: Row 53 / row 18 x days | P55: dso = ar/rev * 365
B56: DIO | C56: days | D56: ='Raw Data'!E54/'Raw Data'!E19 * 'Historical Drivers'!D8 -> 144.24644 | E56: ='Raw Data'!F54/'Raw Data'!F19 * 'Historical Drivers'!E8 -> 180.54111 | F56: ='Raw Data'!G54/'Raw Data'!G19 * 'Historical Drivers'!F8 -> 166.13883 | G56: ='Raw Data'!H54/'Raw Data'!H19 * 'Historical Drivers'!G8 -> 135.50655 | H56: ='Raw Data'!M54/'Raw Data'!M19 * 'Historical Drivers'!H8 -> 126.40747 | J56: =MIN(D56:G56) -> 135.50655 | K56: =AVERAGE(D56:G56) -> 156.60823 | L56: =MAX(D56:G56) -> 180.54111 | O56: Row 54 / row 19 x days | P56: dho = inv/cogs * 365
B57: DPO | C57: days | D57: ='Raw Data'!E70/'Raw Data'!E19 * 'Historical Drivers'!D8 -> 131.84164 | E57: ='Raw Data'!F70/'Raw Data'!F19 * 'Historical Drivers'!E8 -> 85.201109 | F57: ='Raw Data'!G70/'Raw Data'!G19 * 'Historical Drivers'!F8 -> 136.63632 | G57: ='Raw Data'!H70/'Raw Data'!H19 * 'Historical Drivers'!G8 -> 156.49345 | H57: ='Raw Data'!M70/'Raw Data'!M19 * 'Historical Drivers'!H8 -> 229.01486 | J57: =MIN(D57:G57) -> 85.201109 | K57: =AVERAGE(D57:G57) -> 127.54313 | L57: =MAX(D57:G57) -> 156.49345 | O57: Row 70 / row 19 x days | P57: dpo = ap/cogs*365
B58: Net working capital | C58: $M | D58: ='Raw Data'!E53+'Raw Data'!E54-'Raw Data'!E70 -> 5703 | E58: ='Raw Data'!F53+'Raw Data'!F54-'Raw Data'!F70 -> 6872 | F58: ='Raw Data'!G53+'Raw Data'!G54-'Raw Data'!G70 -> 8191 | G58: ='Raw Data'!H53+'Raw Data'!H54-'Raw Data'!H70 -> 7971 | H58: ='Raw Data'!M53+'Raw Data'!M54-'Raw Data'!M70 -> 24071 | O58: Row 53 + row 54 - row 70 | P58: ccc
B59: NWC % of revenue | C59: % | D59: =D58/D13 -> 0.18541518 | E59: =E58/E13 -> 0.44221364 | F59: =F58/F13 -> 0.32619171 | G59: =G58/G13 -> 0.21325379 | H59: =H58/(H13*$D$8/H$8) -> 0.2280144 | O59: NWC / annualised revenue
B62: E. TAX
B63: Line item | C63: Units | D63: FY2022 | E63: FY2023 | F63: FY2024 | G63: FY2025 | H63: 9M FY26 | J63: Trough | K63: Mid-cycle | L63: Peak | O63: From Raw Data
B64: Effective tax rate | C64: % | D64: =-'Raw Data'!E32/'Raw Data'!E31 -> 0.092780274 | E64: =-'Raw Data'!F32/'Raw Data'!F31 -> -0.031283139 | F64: =-'Raw Data'!G32/'Raw Data'!G31 -> 0.36370968 | G64: =-'Raw Data'!H32/'Raw Data'!H31 -> 0.11642842 | H64: =-'Raw Data'!M32/'Raw Data'!M31 -> 0.14752945 | J64: =MIN(D64:G64) -> -0.031283139 | K64: =AVERAGE(D64:G64) -> 0.13540881 | L64: =MAX(D64:G64) -> 0.36370968 | O64: -Row 32 / row 31
B65: Cash tax rate | C65: % | D65: =-'Raw Data'!E139/'Raw Data'!E31 -> 0.051509769 | E65: =-'Raw Data'!F139/'Raw Data'!F31 -> -0.094026158 | F65: =-'Raw Data'!G139/'Raw Data'!G31 -> 0.27258065 | G65: =-'Raw Data'!H139/'Raw Data'!H31 -> 0.060389476 | O65: -Row 139 / row 31 (9M: blank)
B68: F. CASH FLOW
B69: Line item | C69: Units | D69: FY2022 | E69: FY2023 | F69: FY2024 | G69: FY2025 | H69: 9M FY26 | J69: Trough | K69: Mid-cycle | L69: Peak | O69: From Raw Data
B70: Operating cash flow | C70: $M | D70: ='Raw Data'!E113 -> 15181 | E70: ='Raw Data'!F113 -> 1559 | F70: ='Raw Data'!G113 -> 8507 | G70: ='Raw Data'!H113 -> 17525 | H70: ='Raw Data'!M113 -> 45702 | O70: Row 113
B71: Free cash flow | C71: $M | D71: ='Raw Data'!E113+'Raw Data'!E115 -> 3114 | E71: ='Raw Data'!F113+'Raw Data'!F115 -> -6117 | F71: ='Raw Data'!G113+'Raw Data'!G115 -> 121 | G71: ='Raw Data'!H113+'Raw Data'!H115 -> 1668 | H71: ='Raw Data'!M113+'Raw Data'!M115 -> 26100 | O71: Row 113 + row 115
B72: FCF margin % | C72: % | D72: =D71/D13 -> 0.10124195 | E72: =E71/E13 -> -0.39362934 | F72: =F71/F13 -> 0.0048186054 | G72: =G71/G13 -> 0.044625181 | H72: =H71/H13 -> 0.3305513 | O72: FCF / revenue
B73: FCF including incentives | C73: $M | D73: =D71+'Raw Data'!E119 -> 3229 | E73: =E71+'Raw Data'!F119 -> -5407 | F73: =F71+'Raw Data'!G119 -> 436 | G73: =G71+'Raw Data'!H119 -> 3673 | H73: =H71+'Raw Data'!M119 -> 29089 | O73: FCF + row 119
B76: G. SHARES AND CAPITAL RETURNS
B77: Line item | C77: Units | D77: FY2022 | E77: FY2023 | F77: FY2024 | G77: FY2025 | H77: 9M FY26 | J77: Trough | K77: Mid-cycle | L77: Peak | O77: From Raw Data
B78: SBC % of revenue | C78: % | D78: ='Raw Data'!E101/D13 -> 0.0167111 | E78: ='Raw Data'!F101/E13 -> 0.038352638 | F78: ='Raw Data'!G101/F13 -> 0.033172713 | G78: ='Raw Data'!H101/G13 -> 0.026004602 | H78: ='Raw Data'!M101/H13 -> 0.01208222 | J78: =MIN(D78:G78) -> 0.0167111 | K78: =AVERAGE(D78:G78) -> 0.028560263 | L78: =MAX(D78:G78) -> 0.038352638 | O78: Row 101 / row 18
B79: Diluted shares | C79: M sh | D79: ='Raw Data'!E42 -> 1122 | E79: ='Raw Data'!F42 -> 1093 | F79: ='Raw Data'!G42 -> 1118 | G79: ='Raw Data'!H42 -> 1125 | H79: ='Raw Data'!M42 -> 1142 | O79: Row 42
B80: Diluted share change | C80: % | D80: ='Raw Data'!E42/'Raw Data'!D42 - 1 -> -0.01665206 | E80: ='Raw Data'!F42/'Raw Data'!E42 - 1 -> -0.025846702 | F80: ='Raw Data'!G42/'Raw Data'!F42 - 1 -> 0.022872827 | G80: ='Raw Data'!H42/'Raw Data'!G42 - 1 -> 0.0062611807 | O80: Row 42 vs prior year (9M: blank)
B81: Dividends per share | C81: $ | D81: ='Raw Data'!E44 -> 0.315 | E81: ='Raw Data'!F44 -> 0.46 | F81: ='Raw Data'!G44 -> 0.46 | G81: ='Raw Data'!H44 -> 0.46 | H81: ='Raw Data'!M44 -> 0.38 | O81: Row 44
B82: Dividends paid | C82: $M | D82: =-'Raw Data'!E127 -> 461 | E82: =-'Raw Data'!F127 -> 504 | F82: =-'Raw Data'!G127 -> 513 | G82: =-'Raw Data'!H127 -> 522 | H82: =-'Raw Data'!M127 -> 437 | O82: Row 127, shown positive
B83: Buybacks | C83: $M | D83: =-('Raw Data'!E126+'Raw Data'!E125) -> 2432 | E83: =-('Raw Data'!F126+'Raw Data'!F125) -> 425 | F83: =-('Raw Data'!G126+'Raw Data'!G125) -> 300 | G83: =-('Raw Data'!H126+'Raw Data'!H125) -> 0 | H83: =-('Raw Data'!M126+'Raw Data'!M125) -> 1412 | O83: Rows 125 + 126, shown positive
B84: Dividend Payout Ratio | C84: % | D84: =D82/'Raw Data'!E34 -> 0.053067802 | E84: =E82/'Raw Data'!F34 -> -0.086404937 | F84: =F82/'Raw Data'!G34 -> 0.65938303 | G84: =G82/'Raw Data'!H34 -> 0.06113128 | H84: =H82/'Raw Data'!M34 -> 0.0092451553 | O84: Dividends/NI
B85: Total Payout ratio | C85: % | D85: =(D82+D83)/'Raw Data'!E34 -> 0.33302636 | E85: =(E82+E83)/'Raw Data'!F34 -> -0.15926624 | F85: =(F82+F83)/'Raw Data'!G34 -> 1.0449871 | G85: =(G82+G83)/'Raw Data'!H34 -> 0.06113128 | H85: =(H82+H83)/'Raw Data'!M34 -> 0.039117373 | O85: (Dividends + buybacks) / row 34
B88: H. BALANCE SHEET
B89: Line item | C89: Units | D89: FY2022 | E89: FY2023 | F89: FY2024 | G89: FY2025 | H89: 9M FY26 | J89: Trough | K89: Mid-cycle | L89: Peak | O89: From Raw Data
B90: Cash and investments | C90: $M | D90: ='Raw Data'!E51+'Raw Data'!E52+'Raw Data'!E59 -> 10978 | E90: ='Raw Data'!F51+'Raw Data'!F52+'Raw Data'!F59 -> 10438 | F90: ='Raw Data'!G51+'Raw Data'!G52+'Raw Data'!G59 -> 9152 | G90: ='Raw Data'!H51+'Raw Data'!H52+'Raw Data'!H59 -> 11936 | H90: ='Raw Data'!M51+'Raw Data'!M52+'Raw Data'!M59 -> 30128 | O90: Rows 51 + 52 + 59
B91: Total debt | C91: $M | D91: ='Raw Data'!E71+'Raw Data'!E75 -> 6906 | E91: ='Raw Data'!F71+'Raw Data'!F75 -> 13330 | F91: ='Raw Data'!G71+'Raw Data'!G75 -> 13397 | G91: ='Raw Data'!H71+'Raw Data'!H75 -> 14577 | H91: ='Raw Data'!M71+'Raw Data'!M75 -> 5722 | O91: Rows 71 + 75
B92: Net cash / (net debt) | C92: $M | D92: =D90-D91 -> 4072 | E92: =E90-E91 -> -2892 | F92: =F90-F91 -> -4245 | G92: =G90-G91 -> -2641 | H92: =H90-H91 -> 24406 | O92: Cash and investments - total debt
B93: Debt / EBITDA | C93: x | D93: =D91/D38 -> 0.41063147 | E93: =E91/E38 -> 6.628543 | F93: =F91/F38 -> 1.4747908 | G93: =G91/G38 -> 0.80438141 | H93: =H91/(H38*$D$8/H$8) -> 0.068529607 | O93: Total debt / annualised EBITDA

Sheet Schedules
B3: Revenue Schedule
F6: Actual | J6: Projected
E7: Units | F7: ='Raw Data'!E144 -> FY2022 | G7: ='Raw Data'!F144 -> FY2023 | H7: ='Raw Data'!G144 -> FY2024 | I7: ='Raw Data'!H144 -> FY2025 | J7: FY2026E | K7: =Assumptions!K24 -> FY2027E | L7: =Assumptions!L24 -> FY2028E | M7: =Assumptions!M24 -> FY2029E | N7: =Assumptions!N24 -> FY2030E | O7: =Assumptions!O24 -> FY2031E | P7: =Assumptions!P24 -> FY2032E
C9: DRAM
D10: Bit growth | E10: (%) | F10: ='Historical Drivers'!D23 -> 0.11 | G10: ='Historical Drivers'!E23 -> -0.08 | H10: ='Historical Drivers'!F23 -> 0.45 | I10: ='Historical Drivers'!G23 -> 0.15 | K10: =Assumptions!K36 -> 0.1 | L10: =Assumptions!L36 -> 0.15 | M10: =Assumptions!M36 -> 0.16 | N10: =Assumptions!N36 -> 0.15 | O10: =Assumptions!O36 -> 0.15 | P10: =Assumptions!P36 -> 0.15
D11: Price change | E11: (%) | F11: ='Historical Drivers'!D24 -> 0 | G11: ='Historical Drivers'!E24 -> -0.48 | H11: ='Historical Drivers'!F24 -> 0.12 | I11: ='Historical Drivers'!G24 -> 0.42 | K11: =Assumptions!K26 -> 0.05 | L11: =Assumptions!L26 -> -0.45 | M11: =Assumptions!M26 -> -0.35 | N11: =Assumptions!N26 -> -0.1 | O11: =Assumptions!O26 -> -0.15 | P11: =Assumptions!P26 -> -0.15
D12: Bit volume index | E12: (index) | J12: 100 | K12: =J12*(1+K10) -> 110 | L12: =K12*(1+L10) -> 126.5 | M12: =L12*(1+M10) -> 146.74 | N12: =M12*(1+N10) -> 168.751 | O12: =N12*(1+O10) -> 194.06365 | P12: =O12*(1+P10) -> 223.1732
D13: Revenue per bit index | E13: (index) | J13: 100 | K13: =J13*(1+K11) -> 105 | L13: =K13*(1+L11) -> 57.75 | M13: =L13*(1+M11) -> 37.5375 | N13: =M13*(1+N11) -> 33.78375 | O13: =N13*(1+O11) -> 28.716188 | P13: =O13*(1+P11) -> 24.408759
D14: DRAM revenue | E14: ($M) | F14: ='Historical Drivers'!D16 -> 22386 | G14: ='Historical Drivers'!E16 -> 10978 | H14: ='Historical Drivers'!F16 -> 17603 | I14: ='Historical Drivers'!G16 -> 28578 | J14: ='Raw Data'!M159+(Assumptions!J12*Assumptions!J18) -> 98692.639 | K14: =$J14*(K12/$J12)*(K13/$J13) -> 113990 | L14: =$J14*(L12/$J12)*(L13/$J13) -> 72098.674 | M14: =$J14*(M12/$J12)*(M13/$J13) -> 54362.4 | N14: =$J14*(N12/$J12)*(N13/$J13) -> 56265.084 | O14: =$J14*(O12/$J12)*(O13/$J13) -> 54999.12 | P14: =$J14*(P12/$J12)*(P13/$J13) -> 53761.64 | Q14: <- Index Based calc method. We use the base price from 2026 to forecast
D15: Growth | E15: (%) | F15: ='Historical Drivers'!D20 -> 0.11712161 | G15: ='Historical Drivers'!E20 -> -0.50960422 | H15: ='Historical Drivers'!F20 -> 0.60347969 | I15: ='Historical Drivers'!G20 -> 0.62347327 | J15: =J14/I14 - 1 -> 2.4534481 | K15: =K14/J14 - 1 -> 0.155 | L15: =L14/K14 - 1 -> -0.3675 | M15: =M14/L14 - 1 -> -0.246 | N15: =N14/M14 - 1 -> 0.035 | O15: =O14/N14 - 1 -> -0.0225 | P15: =P14/O14 - 1 -> -0.0225
C17: NAND
D18: Bit growth | E18: (%) | F18: ='Historical Drivers'!D25 -> 0.08 | G18: ='Historical Drivers'!E25 -> 0.08 | H18: ='Historical Drivers'!F25 -> 0.32 | I18: ='Historical Drivers'!G25 -> 0.18 | K18: =Assumptions!K41 -> 0.1 | L18: =Assumptions!L41 -> 0.15 | M18: =Assumptions!M41 -> 0.2 | N18: =Assumptions!N41 -> 0.18 | O18: =Assumptions!O41 -> 0.18 | P18: =Assumptions!P41 -> 0.18
D19: Price change | E19: (%) | F19: ='Historical Drivers'!D26 -> 0.02 | G19: ='Historical Drivers'!E26 -> -0.52 | H19: ='Historical Drivers'!F26 -> 0.32 | I19: ='Historical Drivers'!G26 -> 0 | K19: =Assumptions!K31 -> -0.05 | L19: =Assumptions!L31 -> -0.45 | M19: =Assumptions!M31 -> -0.35 | N19: =Assumptions!N31 -> -0.1 | O19: =Assumptions!O31 -> -0.18 | P19: =Assumptions!P31 -> -0.18
D20: Bit volume index | E20: (index) | J20: 100 | K20: =J20*(1+K18) -> 110 | L20: =K20*(1+L18) -> 126.5 | M20: =L20*(1+M18) -> 151.8 | N20: =M20*(1+N18) -> 179.124 | O20: =N20*(1+O18) -> 211.36632 | P20: =O20*(1+P18) -> 249.41226
D21: Revenue per bit index | E21: (index) | J21: 100 | K21: =J21*(1+K19) -> 95 | L21: =K21*(1+L19) -> 52.25 | M21: =L21*(1+M19) -> 33.9625 | N21: =M21*(1+N19) -> 30.56625 | O21: =N21*(1+O19) -> 25.064325 | P21: =O21*(1+P19) -> 20.552747
D22: NAND revenue | E22: ($M) | F22: ='Historical Drivers'!D17 -> 7811 | G22: ='Historical Drivers'!E17 -> 4206 | H22: ='Historical Drivers'!F17 -> 7227 | I22: ='Historical Drivers'!G17 -> 8503 | J22: ='Raw Data'!M160+(Assumptions!J12*Assumptions!J19) -> 29675.233 | K22: =$J22*(K20/$J20)*(K21/$J21) -> 31010.618 | L22: =$J22*(L20/$J20)*(L21/$J21) -> 19614.216 | M22: =$J22*(M20/$J20)*(M21/$J21) -> 15299.088 | N22: =$J22*(N20/$J20)*(N21/$J21) -> 16247.632 | O22: =$J22*(O20/$J20)*(O21/$J21) -> 15721.209 | P22: =$J22*(P20/$J20)*(P21/$J21) -> 15211.842 | Q22: <- Index Based calc method. We use the base price from 2026 to forecast
D23: Growth | E23: (%) | F23: ='Historical Drivers'!D21 -> 0.1147424 | G23: ='Historical Drivers'!E21 -> -0.46152861 | H23: ='Historical Drivers'!F21 -> 0.71825963 | I23: ='Historical Drivers'!G21 -> 0.17656012 | J23: =J22/I22 - 1 -> 2.4899721 | K23: =K22/J22 - 1 -> 0.045 | L23: =L22/K22 - 1 -> -0.3675 | M23: =M22/L22 - 1 -> -0.22 | N23: =N22/M22 - 1 -> 0.062 | O23: =O22/N22 - 1 -> -0.0324 | P23: =P22/O22 - 1 -> -0.0324
C25: Other
D26: Other revenue % of DRAM + NAND | E26: (%) | F26: =F27/(F14+F22) -> 0.018578004 | G26: =G27/(G14+G22) -> 0.023445732 | H26: =H27/(H14+H22) -> 0.011316955 | I26: =I27/(I14+I22) -> 0.0080094927 | J26: =J27/(J14+J22) -> 0.0046049539 | K26: =Assumptions!K56 -> 0.0046 | L26: =Assumptions!L56 -> 0.0046 | M26: =Assumptions!M56 -> 0.0046 | N26: =Assumptions!N56 -> 0.0046 | O26: =Assumptions!O56 -> 0.0046 | P26: =Assumptions!P56 -> 0.0046
D27: Other revenue | E27: ($M) | F27: ='Raw Data'!E161 -> 561 | G27: ='Raw Data'!F161 -> 356 | H27: ='Raw Data'!G161 -> 281 | I27: ='Raw Data'!H161 -> 297 | J27: ='Raw Data'!M161 + (Assumptions!J12*Assumptions!J20) -> 591.12814 | K27: =K26*(K14+K22) -> 667.00284 | L27: =L26*(L14+L22) -> 421.87929 | M27: =M26*(M14+M22) -> 320.44285 | N27: =N26*(N14+N22) -> 333.55849 | O27: =O26*(O14+O22) -> 325.31351 | P27: =P26*(P14+P22) -> 317.27801
C29: Total Revenue
D30: Total revenue | E30: ($M) | F30: =F14+F22+F27 -> 30758 | G30: =G14+G22+G27 -> 15540 | H30: =H14+H22+H27 -> 25111 | I30: =I14+I22+I27 -> 37378 | J30: =J14+J22+J27 -> 128959 | K30: =K14+K22+K27 -> 145667.62 | L30: =L14+L22+L27 -> 92134.769 | M30: =M14+M22+M27 -> 69981.931 | ... P30: =P14+P22+P27 -> 69290.759
D31: Growth | E31: (%) | F31: ='Historical Drivers'!D14 -> 0.11019672 | G31: ='Historical Drivers'!E14 -> -0.49476559 | H31: ='Historical Drivers'!F14 -> 0.61589447 | I31: ='Historical Drivers'!G14 -> 0.48851101 | J31: =J30/I30 - 1 -> 2.4501311 | K31: =K30/J30 - 1 -> 0.12956536 | L31: =L30/K30 - 1 -> -0.3675 | M31: =M30/L30 - 1 -> -0.2404395 | N31: =N30/M30 - 1 -> 0.040929753 | O31: =O30/N30 - 1 -> -0.024718253 | P31: =P30/O30 - 1 -> -0.024700781
D32: DRAM % of revenue | E32: (%) | F32: =F14/F30 -> 0.72781065 | G32: =G14/G30 -> 0.70643501 | H32: =H14/H30 -> 0.70100753 | I32: =I14/I30 -> 0.76456739 | J32: =J14/J30 -> 0.76530245 | K32: =K14/K30 -> 0.78253492 | L32: =L14/L30 -> 0.78253492 | M32: =M14/M30 -> 0.77680623 | ... P32: =P14/P30 -> 0.7758847
D33: NAND % of revenue | E33: (%) | F33: =F22/F30 -> 0.25395019 | G33: =G22/G30 -> 0.27065637 | H33: =H22/H30 -> 0.28780216 | I33: =I22/I30 -> 0.22748676 | J33: =J22/J30 -> 0.2301137 | K33: =K22/K30 -> 0.21288615 | L33: =L22/L30 -> 0.21288615 | M33: =M22/M30 -> 0.21861484 | ... P33: =P22/P30 -> 0.21953637
D34: Other % of revenue | E34: (%) | F34: =F27/F30 -> 0.018239157 | G34: =G27/G30 -> 0.022908623 | H34: =H27/H30 -> 0.011190315 | I34: =I27/I30 -> 0.0079458505 | J34: =J27/J30 -> 0.0045838455 | K34: =K27/K30 -> 0.0045789369 | L34: =L27/L30 -> 0.0045789369 | M34: =M27/M30 -> 0.0045789369 | ... P34: =P27/P30 -> 0.0045789369
B40: Cost Schedule
F43: Actual | J43: Projected
E44: Units | F44: =F7 -> FY2022 | G44: =G7 -> FY2023 | H44: =H7 -> FY2024 | I44: =I7 -> FY2025 | J44: =J7 -> FY2026E | K44: =K7 -> FY2027E | L44: =L7 -> FY2028E | M44: =M7 -> FY2029E | ... P44: =P7 -> FY2032E
C46: Cost per bit
D47: Blended bit growth | K47: =(K10*J14 + K18* J22)/(J14+J22) -> 0.1 | L47: =(L10*K14 + L18* K22)/(K14+K22) -> 0.15 | M47: =(M10*L14 + M18* L22)/(L14+L22) -> 0.16855462 | N47: =(N10*M14 + N18* M22)/(M14+M22) -> 0.15658861 | O47: =(O10*N14 + O18* N22)/(N14+N22) -> 0.15672198 | P47: =(P10*O14 + P18* O22)/(O14+O22) -> 0.15666903
D48: Cost per bit decline | K48: =-Assumptions!K55 -> -0.08 | L48: =-Assumptions!L55 -> -0.08 | M48: =-Assumptions!M55 -> -0.08 | N48: =-Assumptions!N55 -> -0.08 | O48: =-Assumptions!O55 -> -0.08 | P48: =-Assumptions!P55 -> -0.08
D49: Bit volume index | J49: 100 | K49: =J49*(1+K47) -> 110 | L49: =K49*(1+L47) -> 126.5 | M49: =L49*(1+M47) -> 147.82216 | N49: =M49*(1+N47) -> 170.96943 | O49: =N49*(1+O47) -> 197.76409 | P49: =O49*(1+P47) -> 228.7476
D50: Cost per bit index | J50: 100 | K50: =J50*(1+K48) -> 92 | L50: =K50*(1+L48) -> 84.64 | M50: =L50*(1+M48) -> 77.8688 | N50: =M50*(1+N48) -> 71.639296 | O50: =N50*(1+O48) -> 65.908152 | P50: =O50*(1+P48) -> 60.6355
D52: COGS | F52: ='Raw Data'!E19 -> 16860 | G52: ='Raw Data'!F19 -> 16956 | H52: ='Raw Data'!G19 -> 19498 | I52: ='Raw Data'!H19 -> 22505 | J52: ='Raw Data'!M19 + Assumptions!J12*(1-Assumptions!J13) -> 25502 | K52: =$J52*(K49/$J49)*(K50/$J50) -> 25808.024 | L52: =$J52*(L49/$J49)*(L50/$J50) -> 27304.889 | M52: =$J52*(M49/$J49)*(M50/$J50) -> 29354.674 | N52: =$J52*(N49/$J49)*(N50/$J50) -> 31235.179 | O52: =$J52*(O49/$J49)*(O50/$J50) -> 33239.985 | P52: =$J52*(P49/$J49)*(P50/$J50) -> 35371.848
J53: q3 acc cogs *(revenue*1-gpm)
C55: Revenue | F55: =F30 -> 30758 | G55: =G30 -> 15540 | H55: =H30 -> 25111 | I55: =I30 -> 37378 | J55: =J30 -> 128959 | K55: =K30 -> 145667.62 | L55: =L30 -> 92134.769 | M55: =M30 -> 69981.931 | ... P55: =P30 -> 69290.759
C56: COGS | F56: =F52 -> 16860 | G56: =G52 -> 16956 | H56: =H52 -> 19498 | I56: =I52 -> 22505 | J56: =J52 -> 25502 | K56: =K52 -> 25808.024 | L56: =L52 -> 27304.889 | M56: =M52 -> 29354.674 | ... P56: =P52 -> 35371.848
C57: Gross Profit | F57: =F55-F56 -> 13898 | G57: =G55-G56 -> -1416 | H57: =H55-H56 -> 5613 | I57: =I55-I56 -> 14873 | J57: =J55-J56 -> 103457 | K57: =K55-K56 -> 119859.6 | L57: =L55-L56 -> 64829.88 | M57: =M55-M56 -> 40627.257 | ... P57: =P55-P56 -> 33918.911
C58: Gross Margin (%) | F58: =F57/F55 -> 0.45184993 | G58: =G57/G55 -> -0.091119691 | H58: =H57/H55 -> 0.22352754 | I58: =I57/I55 -> 0.39790786 | J58: =J57/J55 -> 0.80224723 | K58: =K57/K55 -> 0.82282937 | L58: =L57/L55 -> 0.70364185 | M58: =M57/M55 -> 0.58053924 | ... P58: =P57/P55 -> 0.48951564
C61: R&D growth (%) | F61: =F62/'Raw Data'!D22 - 1 -> 0.1701089 | G61: =G62/F62 - 1 -> -0.00064184852 | H61: =H62/G62 - 1 -> 0.1014772 | I61: =I62/H62 - 1 -> 0.10728863 | J61: =J62/I62 - 1 -> 0.35475973 | K61: =Assumptions!K57 -> 0.1 | L61: =Assumptions!L57 -> 0.1 | M61: =Assumptions!M57 -> 0.1 | N61: =Assumptions!N57 -> 0.1 | O61: =Assumptions!O57 -> 0.1 | P61: =Assumptions!P57 -> 0.1
C62: R&D ($M) | F62: ='Raw Data'!E22 -> 3116 | G62: ='Raw Data'!F22 -> 3114 | H62: ='Raw Data'!G22 -> 3430 | I62: ='Raw Data'!H22 -> 3798 | J62: ='Raw Data'!M22+Assumptions!J14 * 'Raw Data'!L22/SUM('Raw Data'!L22:L25) -> 5145.3774 | K62: =J62*(1+K61) -> 5659.9152 | L62: =K62*(1+L61) -> 6225.9067 | M62: =L62*(1+M61) -> 6848.4974 | N62: =M62*(1+N61) -> 7533.3471 | O62: =N62*(1+O61) -> 8286.6818 | P62: =O62*(1+P61) -> 9115.35
C63: SG&A growth (%) | F63: =F64/'Raw Data'!D23 - 1 -> 0.19239374 | G63: =G64/F64 - 1 -> -0.1369606 | H63: =H64/G64 - 1 -> 0.22717391 | I63: =I64/H64 - 1 -> 0.067316209 | J63: =J64/I64 - 1 -> 0.26437313 | K63: =Assumptions!K58 -> 0.08 | L63: =Assumptions!L58 -> 0.08 | M63: =Assumptions!M58 -> 0.08 | N63: =Assumptions!N58 -> 0.08 | O63: =Assumptions!O58 -> 0.08 | P63: =Assumptions!P58 -> 0.08
C64: SG&A ($M) | F64: ='Raw Data'!E23 -> 1066 | G64: ='Raw Data'!F23 -> 920 | H64: ='Raw Data'!G23 -> 1129 | I64: ='Raw Data'!H23 -> 1205 | J64: ='Raw Data'!M23+ Assumptions!J14 * 'Raw Data'!L23/SUM('Raw Data'!L22:L25) -> 1523.5696 | K64: =J64*(1+K63) -> 1645.4552 | L64: =K64*(1+L63) -> 1777.0916 | M64: =L64*(1+M63) -> 1919.2589 | N64: =M64*(1+N63) -> 2072.7996 | O64: =N64*(1+O63) -> 2238.6236 | P64: =O64*(1+P63) -> 2417.7135
C65: Other operating ($M) | F65: ='Raw Data'!E24+'Raw Data'!E25 -> 14 | G65: ='Raw Data'!F24+'Raw Data'!F25 -> 295 | H65: ='Raw Data'!G24+'Raw Data'!G25 -> -250 | I65: ='Raw Data'!H24+'Raw Data'!H25 -> 100 | J65: ='Raw Data'!M24+'Raw Data'!M25+Assumptions!$J$14*('Raw Data'!L24+'Raw Data'!L25)/SUM('Raw Data'!L22:L25) -> 59.052934 | K65: =Assumptions!K59 -> 0 | L65: =Assumptions!L59 -> 0 | M65: =Assumptions!M59 -> 0 | N65: =Assumptions!N59 -> 0 | O65: =Assumptions!O59 -> 0 | P65: =Assumptions!P59 -> 0
C66: Total operating expenses | F66: =F62+F64+F65 -> 4196 | G66: =G62+G64+G65 -> 4329 | H66: =H62+H64+H65 -> 4309 | I66: =I62+I64+I65 -> 5103 | J66: 6728 | K66: 7305.3704 | L66: 8002.9983 | M66: 8767.7563 | N66: 9606.1468 | O66: 10525.305 | P66: 11533.064
C68: How FY2026E R&D is built: R&D = R&D already spent in Q1-Q3 (9-month YTD) + Q4 opex guidance x R&D's share of Q3 opex (Q3 R&D / Q3 total operating expenses). Micron guides only one Q4 opex total, so we split it using last quarter's mix. SG&A and other operating are built the same way.
C69: Operating Income ($M) | F69: =F57-F66 -> 9702 | G69: =G57-G66 -> -5745 | H69: =H57-H66 -> 1304 | I69: =I57-I66 -> 9770 | J69: =J57-J66 -> 96729 | K69: =K57-K66 -> 112554.22 | L69: =L57-L66 -> 56826.881 | M69: =M57-M66 -> 31859.501 | ... P69: =P57-P66 -> 22385.847
C70: Operating Margin (%) | F70: =F69/F55 -> 0.31543013 | G70: =G69/G55 -> -0.36969112 | H70: =H69/H55 -> 0.051929433 | I70: =I69/I55 -> 0.2613837 | J70: =J69/J55 -> 0.75007561 | K70: =K69/K55 -> 0.77267841 | L70: =L69/L55 -> 0.61677998 | M70: =M69/M55 -> 0.45525324 | ... P70: =P69/P55 -> 0.32307118
B75: Fixed Asset (PP&E) Schedule
F78: Actual | J78: Projected
E79: Units | F79: =F44 -> FY2022 | G79: =G44 -> FY2023 | H79: =H44 -> FY2024 | I79: =I44 -> FY2025 | J79: =J44 -> FY2026E | K79: =K44 -> FY2027E | L79: =L44 -> FY2028E | M79: =M44 -> FY2029E | ... P79: =P44 -> FY2032E
C81: Capex
D82: Capex % | F82: =F84/F83 -> 0.3923207 | G82: =G84/G83 -> 0.49395109 | H82: =H84/H83 -> 0.33395723 | I82: =I84/I83 -> 0.42423351 | J82: =J84/J83 -> 0.24027275 | K82: =Assumptions!K46 -> 0.25 | L82: =Assumptions!L46 -> 0.35 | M82: =Assumptions!M46 -> 0.38 | N82: =Assumptions!N46 -> 0.35 | O82: =Assumptions!O46 -> 0.35 | P82: =Assumptions!P46 -> 0.35
D83: Revenue | F83: =F55 -> 30758 | G83: =G55 -> 15540 | H83: =H55 -> 25111 | I83: =I55 -> 37378 | J83: =J55 -> 128959 | K83: =K55 -> 145667.62 | L83: =L55 -> 92134.769 | M83: =M55 -> 69981.931 | ... P83: =P55 -> 69290.759
D84: Capex | F84: ='Historical Drivers'!D44 -> 12067 | G84: ='Historical Drivers'!E44 -> 7676 | H84: ='Historical Drivers'!F44 -> 8386 | I84: ='Historical Drivers'!G44 -> 15857 | J84: =Assumptions!J21+J86 -> 30985.333 | K84: =K83*K82 -> 36416.905 | L84: =L83*L82 -> 32247.169 | M84: =M83*M82 -> 26593.134 | N84: =N83*N82 -> 25496.196 | O84: =O83*O82 -> 24865.975 | P84: =P83*P82 -> 24251.766
D85: Incentives % | F85: =F86/F84 -> 0.0095301235 | G85: =G86/G84 -> 0.092496092 | H85: =H86/H84 -> 0.037562604 | I85: =I86/I84 -> 0.12644258 | J85: =J86/J84 -> 0.12861999 | K85: =Assumptions!K63 -> 0.08 | L85: =Assumptions!L63 -> 0.08 | M85: =Assumptions!M63 -> 0.08 | N85: =Assumptions!N63 -> 0.08 | O85: =Assumptions!O63 -> 0.08 | P85: =Assumptions!P63 -> 0.08
D86: Incentives | F86: ='Historical Drivers'!D46 -> 115 | G86: ='Historical Drivers'!E46 -> 710 | H86: ='Historical Drivers'!F46 -> 315 | I86: ='Historical Drivers'!G46 -> 2005 | J86: ='Raw Data'!M119*4/3 -> 3985.3333 | K86: =K85*K84 -> 2913.3524 | L86: =L85*L84 -> 2579.7735 | M86: =M85*M84 -> 2127.4507 | N86: =N85*N84 -> 2039.6957 | O86: =O85*O84 -> 1989.278 | P86: =P85*P84 -> 1940.1413
D87: Net capex | F87: =F84-F86 -> 11952 | G87: =G84-G86 -> 6966 | H87: =H84-H86 -> 8071 | I87: =I84-I86 -> 13852 | J87: =J84-J86 -> 27000 | K87: =K84-K86 -> 33503.552 | L87: =L84-L86 -> 29667.396 | M87: =M84-M86 -> 24465.683 | ... P87: =P84-P86 -> 22311.624
C89: Fixed Assets (PP&E)
D90: Years remaining:
D91: Existing assets: | E91: =Assumptions!K61 -> 7
D92: New assets: | E92: =Assumptions!K62 -> 10
D94: PP&E - beginning | F94: ='Raw Data'!D60 -> 33213 | G94: =F109 -> 38549 | H94: =G109 -> 37928 | I94: =H109 -> 39749 | J94: =I109 -> 46590 | K94: =J109 -> 64525.667 | L94: =K109 -> 87136.089 | M94: =L109 -> 102751.81 | N94: =M109 -> 110459.16 | ... P94: =O109 -> 116166.82
D95: Plus: net capex | F95: =F87 -> 11952 | G95: =G87 -> 6966 | H95: =H87 -> 8071 | I95: =I87 -> 13852 | J95: =J87 -> 27000 | K95: =K87 -> 33503.552 | L95: =L87 -> 29667.396 | M95: =M87 -> 24465.683 | ... P95: =P87 -> 22311.624
D97: Depreciation - existing assets | K97: =J109/$E$91 -> 9217.9524 | L97: =K97 -> 9217.9524 | M97: =L97 -> 9217.9524 | N97: =M97 -> 9217.9524 | O97: =N97 -> 9217.9524 | P97: =O97 -> 9217.9524
D99: Depreciation - new assets (by capex year)
D100: =K79 -> FY2027E | E100: =HLOOKUP($D100,$K$79:$P$87,ROWS($K$79:$K$87), FALSE) -> 33503.552 | K100: =IF($D100=K$79,$E100/$E$92/2,MIN($E100/$E$92,$E100-SUM($J100:J100))) -> 1675.1776 | L100: =IF($D100=L$79,$E100/$E$92/2,MIN($E100/$E$92,$E100-SUM($J100:K100))) -> 3350.3552 | M100: =IF($D100=M$79,$E100/$E$92/2,MIN($E100/$E$92,$E100-SUM($J100:L100))) -> 3350.3552 | N100: =IF($D100=N$79,$E100/$E$92/2,MIN($E100/$E$92,$E100-SUM($J100:M100))) -> 3350.3552 | O100: =IF($D100=O$79,$E100/$E$92/2,MIN($E100/$E$92,$E100-SUM($J100:N100))) -> 3350.3552 | P100: =IF($D100=P$79,$E100/$E$92/2,MIN($E100/$E$92,$E100-SUM($J100:O100))) -> 3350.3552
D101: =L79 -> FY2028E | E101: =HLOOKUP($D101,$K$79:$P$87,ROWS($K$79:$K$87), FALSE) -> 29667.396 | L101: =IF($D101=L$79,$E101/$E$92/2,MIN($E101/$E$92,$E101-SUM($J101:K101))) -> 1483.3698 | M101: =IF($D101=M$79,$E101/$E$92/2,MIN($E101/$E$92,$E101-SUM($J101:L101))) -> 2966.7396 | N101: =IF($D101=N$79,$E101/$E$92/2,MIN($E101/$E$92,$E101-SUM($J101:M101))) -> 2966.7396 | O101: =IF($D101=O$79,$E101/$E$92/2,MIN($E101/$E$92,$E101-SUM($J101:N101))) -> 2966.7396 | P101: =IF($D101=P$79,$E101/$E$92/2,MIN($E101/$E$92,$E101-SUM($J101:O101))) -> 2966.7396
D102: =M79 -> FY2029E | E102: =HLOOKUP($D102,$K$79:$P$87,ROWS($K$79:$K$87), FALSE) -> 24465.683 | M102: =IF($D102=M$79,$E102/$E$92/2,MIN($E102/$E$92,$E102-SUM($J102:L102))) -> 1223.2842 | N102: =IF($D102=N$79,$E102/$E$92/2,MIN($E102/$E$92,$E102-SUM($J102:M102))) -> 2446.5683 | O102: =IF($D102=O$79,$E102/$E$92/2,MIN($E102/$E$92,$E102-SUM($J102:N102))) -> 2446.5683 | P102: =IF($D102=P$79,$E102/$E$92/2,MIN($E102/$E$92,$E102-SUM($J102:O102))) -> 2446.5683
D103: =N79 -> FY2030E | E103: =HLOOKUP($D103,$K$79:$P$87,ROWS($K$79:$K$87), FALSE) -> 23456.5 | N103: =IF($D103=N$79,$E103/$E$92/2,MIN($E103/$E$92,$E103-SUM($J103:M103))) -> 1172.825 | O103: =IF($D103=O$79,$E103/$E$92/2,MIN($E103/$E$92,$E103-SUM($J103:N103))) -> 2345.65 | P103: =IF($D103=P$79,$E103/$E$92/2,MIN($E103/$E$92,$E103-SUM($J103:O103))) -> 2345.65
D104: =O79 -> FY2031E | E104: =HLOOKUP($D104,$K$79:$P$87,ROWS($K$79:$K$87), FALSE) -> 22876.697 | O104: =IF($D104=O$79,$E104/$E$92/2,MIN($E104/$E$92,$E104-SUM($J104:N104))) -> 1143.8348 | P104: =IF($D104=P$79,$E104/$E$92/2,MIN($E104/$E$92,$E104-SUM($J104:O104))) -> 2287.6697
D105: =P79 -> FY2032E | E105: =HLOOKUP($D105,$K$79:$P$87,ROWS($K$79:$K$87), FALSE) -> 22311.624 | P105: =IF($D105=P$79,$E105/$E$92/2,MIN($E105/$E$92,$E105-SUM($J105:O105))) -> 1115.5812
D106: Total depreciation | F106: ='Raw Data'!E98 -> 7116 | G106: ='Raw Data'!F98 -> 7756 | H106: ='Raw Data'!G98 -> 7780 | I106: ='Raw Data'!H98 -> 8352 | J106: ='Raw Data'!M98 * 4/3 -> 9149.3333 | K106: =K97+SUM(K100:K105) -> 10893.13 | L106: =L97+SUM(L100:L105) -> 14051.677 | M106: =M97+SUM(M100:M105) -> 16758.331 | N106: =N97+SUM(N100:N105) -> 19154.441 | O106: =O97+SUM(O100:O105) -> 21471.1 | P106: =P97+SUM(P100:P105) -> 23730.516
D108: Other (reconciling) | F108: =F109-(F94+F95-F106) -> 500 | G108: =G109-(G94+G95-G106) -> 169 | H108: =H109-(H94+H95-H106) -> 1530 | I108: =I109-(I94+I95-I106) -> 1341 | J108: =J109-(J94+J95-J106) -> 85 | K108: 0 | L108: 0 | M108: 0 | N108: 0 | O108: 0 | P108: 0
D109: PP&E - ending | F109: ='Raw Data'!E60 -> 38549 | G109: ='Raw Data'!F60 -> 37928 | H109: ='Raw Data'!G60 -> 39749 | I109: ='Raw Data'!H60 -> 46590 | J109: ='Raw Data'!M60 + (Schedules!J87 - (-'Raw Data'!M115-'Raw Data'!M119)) - (Schedules!J106 - 'Raw Data'!M98) -> 64525.667 | K109: =K94+K95-K106+K108 -> 87136.089 | L109: =L94+L95-L106+L108 -> 102751.81 | M109: =M94+M95-M106+M108 -> 110459.16 | N109: =N94+N95-N106+N108 -> 114761.22 | O109: =O94+O95-O106+O108 -> 116166.82 | P109: =P94+P95-P106+P108 -> 114747.92
B114: Working Capital Schedule
F117: Actual | J117: Projected
E118: Units | F118: =F79 -> FY2022 | G118: =G79 -> FY2023 | H118: =H79 -> FY2024 | I118: =I79 -> FY2025 | J118: =J79 -> FY2026E | K118: =K79 -> FY2027E | L118: =L79 -> FY2028E | M118: =M79 -> FY2029E | ... P118: =P79 -> FY2032E
C120: Income statement items
D121: Days in period | E121: (days) | F121: ='Historical Drivers'!D8 -> 365 | G121: ='Historical Drivers'!E8 -> 365 | H121: ='Historical Drivers'!F8 -> 365 | I121: ='Historical Drivers'!G8 -> 365 | J121: =I121 -> 365 | K121: =J121 -> 365 | L121: =K121 -> 365 | M121: =L121 -> 365 | N121: =M121 -> 365 | O121: =N121 -> 365 | P121: =O121 -> 365
D122: Revenue | E122: ($M) | F122: =F30 -> 30758 | G122: =G30 -> 15540 | H122: =H30 -> 25111 | I122: =I30 -> 37378 | J122: =J30 -> 128959 | K122: =K30 -> 145667.62 | L122: =L30 -> 92134.769 | M122: =M30 -> 69981.931 | ... P122: =P30 -> 69290.759
D123: COGS | E123: ($M) | F123: =F52 -> 16860 | G123: =G52 -> 16956 | H123: =H52 -> 19498 | I123: =I52 -> 22505 | J123: =J52 -> 25502 | K123: =K52 -> 25808.024 | L123: =L52 -> 27304.889 | M123: =M52 -> 29354.674 | ... P123: =P52 -> 35371.848
C125: Days
D126: Receivables (DSO, on revenue) | E126: (days) | F126: =F133*F121/F122 -> 60.876845 | G126: =G133*G121/G122 -> 57.380631 | H126: =H133*H121/H122 -> 96.152085 | I126: =I133*I121/I122 -> 90.473674 | J126: ='Raw Data'!M53/'Raw Data'!M18 * 'Historical Drivers'!$H$8 -> 107.26865 | K126: =Assumptions!K65 -> 76 | L126: =Assumptions!L65 -> 76 | M126: =Assumptions!M65 -> 76 | N126: =Assumptions!N65 -> 76 | O126: =Assumptions!O65 -> 76 | P126: =Assumptions!P65 -> 76
D127: Inventories (DIO, on COGS) | E127: (days) | F127: =F134*F121/F123 -> 144.24644 | G127: =G134*G121/G123 -> 180.54111 | H127: =H134*H121/H123 -> 166.13883 | I127: =I134*I121/I123 -> 135.50655 | J127: ='Raw Data'!M54/'Raw Data'!M19 * 'Historical Drivers'!$H$8 -> 126.40747 | K127: =Assumptions!K66 -> 150 | L127: =Assumptions!L66 -> 150 | M127: =Assumptions!M66 -> 150 | N127: =Assumptions!N66 -> 150 | O127: =Assumptions!O66 -> 150 | P127: =Assumptions!P66 -> 150
D128: Other current assets (on COGS) | E128: (days) | F128: =F135*F121/F123 -> 14.22331 | G128: =G135*G121/G123 -> 17.651569 | H128: =H135*H121/H123 -> 14.526618 | I128: =I135*I121/I123 -> 14.823817 | J128: ='Raw Data'!M56/'Raw Data'!M19 * 'Historical Drivers'!H8 -> 16.570046 | K128: =Assumptions!K68 -> 15 | L128: =Assumptions!L68 -> 15 | M128: =Assumptions!M68 -> 15 | N128: =Assumptions!N68 -> 15 | O128: =Assumptions!O68 -> 15 | P128: =Assumptions!P68 -> 15
D129: Payables and accrued expenses (DPO, on COGS) | E129: (days) | F129: =F136*F121/F123 -> 131.84164 | G129: =G136*G121/G123 -> 85.201109 | H129: =H136*H121/H123 -> 136.63632 | I129: =I136*I121/I123 -> 156.49345 | J129: ='Raw Data'!M70/'Raw Data'!M19*'Historical Drivers'!$H$8 -> 229.01486 | K129: =Assumptions!K67 -> 128 | L129: =Assumptions!L67 -> 128 | M129: =Assumptions!M67 -> 128 | N129: =Assumptions!N67 -> 128 | O129: =Assumptions!O67 -> 128 | P129: =Assumptions!P67 -> 128
D130: Other current liabilities (on revenue) | E130: (days) | F130: =F137*F121/F122 -> 15.972755 | G130: =G137*G121/G122 -> 12.425032 | H130: =H137*H121/H122 -> 22.064832 | I130: =I137*I121/I122 -> 12.157553 | J130: ='Raw Data'!M72/'Raw Data'!M18*'Historical Drivers'!$H$8 -> 11.703606 | K130: =Assumptions!K69 -> 16 | L130: =Assumptions!L69 -> 16 | M130: =Assumptions!M69 -> 16 | N130: =Assumptions!N69 -> 16 | O130: =Assumptions!O69 -> 16 | P130: =Assumptions!P69 -> 16
C132: Balances
D133: Receivables | E133: ($M) | F133: ='Raw Data'!E53 -> 5130 | G133: ='Raw Data'!F53 -> 2443 | H133: ='Raw Data'!G53 -> 6615 | I133: ='Raw Data'!H53 -> 9265 | J133: =J126*J122/J121 -> 37899.335 | K133: =K126*K122/K121 -> 30330.792 | L133: =L126*L122/L121 -> 19184.226 | M133: =M126*M122/M121 -> 14571.58 | N133: =N126*N122/N121 -> 15167.991 | O133: =O126*O122/O121 -> 14793.065 | P133: =P126*P122/P121 -> 14427.665
D134: Inventories | E134: ($M) | F134: ='Raw Data'!E54 -> 6663 | G134: ='Raw Data'!F54 -> 8387 | H134: ='Raw Data'!G54 -> 8875 | I134: ='Raw Data'!H54 -> 8355 | J134: =J127*J123/J121 -> 8831.8994 | K134: =K127*K123/K121 -> 10606.037 | L134: =L127*L123/L121 -> 11221.187 | M134: =M127*M123/M121 -> 12063.565 | N134: =N127*N123/N121 -> 12836.375 | O134: =O127*O123/O121 -> 13660.268 | P134: =P127*P123/P121 -> 14536.376
D135: Other current assets | E135: ($M) | F135: ='Raw Data'!E56 -> 657 | G135: ='Raw Data'!F56 -> 820 | H135: ='Raw Data'!G56 -> 776 | I135: ='Raw Data'!H56 -> 914 | J135: =J128*J123/J121 -> 1157.7242 | K135: =K128*K123/K121 -> 1060.6037 | L135: =L128*L123/L121 -> 1122.1187 | M135: =M128*M123/M121 -> 1206.3565 | N135: =N128*N123/N121 -> 1283.6375 | O135: =O128*O123/O121 -> 1366.0268 | P135: =P128*P123/P121 -> 1453.6376
D136: Payables and accrued expenses | E136: ($M) | F136: ='Raw Data'!E70 -> 6090 | G136: ='Raw Data'!F70 -> 3958 | H136: ='Raw Data'!G70 -> 7299 | I136: ='Raw Data'!H70 -> 9649 | J136: =J129*J123/J121 -> 16000.923 | K136: =K129*K123/K121 -> 9050.4851 | L136: =L129*L123/L121 -> 9575.4133 | M136: =M129*M123/M121 -> 10294.242 | N136: =N129*N123/N121 -> 10953.707 | O136: =O129*O123/O121 -> 11656.762 | P136: =P129*P123/P121 -> 12404.374
D137: Other current liabilities | E137: ($M) | F137: ='Raw Data'!E72 -> 1346 | G137: ='Raw Data'!F72 -> 529 | H137: ='Raw Data'!G72 -> 1518 | I137: ='Raw Data'!H72 -> 1245 | J137: =J130*J122/J121 -> 4135.0282 | K137: =K130*K122/K121 -> 6385.4299 | L137: =L130*L122/L121 -> 4038.7844 | M137: =M130*M122/M121 -> 3067.7011 | N137: =N130*N122/N121 -> 3193.2614 | O137: =O130*O122/O121 -> 3114.3295 | P137: =P130*P122/P121 -> 3037.4031
D138: Net working capital | E138: ($M) | F138: =F133+F134+F135-F136-F137 -> 5014 | G138: =G133+G134+G135-G136-G137 -> 7163 | H138: =H133+H134+H135-H136-H137 -> 7449 | I138: =I133+I134+I135-I136-I137 -> 7640 | J138: =J133+J134+J135-J136-J137 -> 27753.007 | K138: =K133+K134+K135-K136-K137 -> 26561.518 | L138: =L133+L134+L135-L136-L137 -> 17913.334 | M138: =M133+M134+M135-M136-M137 -> 14479.558 | ... P138: =P133+P134+P135-P136-P137 -> 14975.901
D140: (Increase) / decrease in NWC | E140: ($M) | G140: =F138-G138 -> -2149 | H140: =G138-H138 -> -286 | I140: =H138-I138 -> -191 | J140: =I138-J138 -> -20113.007 | K140: =J138-K138 -> 1191.4891 | L140: =K138-L138 -> 8648.1835 | M140: =L138-M138 -> 3433.776 | N140: =M138-N138 -> -661.47748 | ... P140: =O138-P138 -> 72.36719
B145: Income Tax Schedule
F148: Actual | J148: Projected
E149: Units | F149: =F118 -> FY2022 | G149: =G118 -> FY2023 | H149: =H118 -> FY2024 | I149: =I118 -> FY2025 | J149: =J118 -> FY2026E | K149: =K118 -> FY2027E | L149: =L118 -> FY2028E | M149: =M118 -> FY2029E | ... P149: =P118 -> FY2032E
...

Sheet Model
B3: Free Cash Flow
F6: Actual | J6: Projected
E7: Units | F7: ='Raw Data'!E144 -> FY2022 | G7: ='Raw Data'!F144 -> FY2023 | H7: ='Raw Data'!G144 -> FY2024 | I7: ='Raw Data'!H144 -> FY2025 | J7: FY2026E | K7: =Assumptions!K24 -> FY2027E | L7: =Assumptions!L24 -> FY2028E | M7: =Assumptions!M24 -> FY2029E | N7: =Assumptions!N24 -> FY2030E | O7: =Assumptions!O24 -> FY2031E | P7: =Assumptions!P24 -> FY2032E
C9: Operating Performance
D10: Revenue | E10: ($M) | F10: =Schedules!F259 -> 30758 | G10: =Schedules!G259 -> 15540 | H10: =Schedules!H259 -> 25111 | I10: =Schedules!I259 -> 37378 | J10: =Schedules!J259 -> 128959 | K10: =Schedules!K259 -> 145667.62 | L10: =Schedules!L259 -> 92134.769 | M10: =Schedules!M259 -> 69981.931 | ... P10: =Schedules!P259 -> 69290.759
D11: Revenue Growth | E11: (%) | G11: =G10/F10 - 1 -> -0.49476559 | H11: =H10/G10 - 1 -> 0.61589447 | I11: =I10/H10 - 1 -> 0.48851101 | J11: =J10/I10 - 1 -> 2.4501311 | K11: =K10/J10 - 1 -> 0.12956536 | L11: =L10/K10 - 1 -> -0.3675 | M11: =M10/L10 - 1 -> -0.2404395 | N11: =N10/M10 - 1 -> 0.040929753 | ... P11: =P10/O10 - 1 -> -0.024700781
D13: EBITDA | E13: ($M) | F13: =F15+F22 -> 16818 | G13: =G15+G22 -> 2011 | H13: =H15+H22 -> 9084 | I13: =I15+I22 -> 18122 | J13: =J15+J22 -> 105878.33 | K13: =K15+K22 -> 123447.35 | L13: =L15+L22 -> 70878.559 | M13: =M15+M22 -> 48617.832 | ... P13: =P15+P22 -> 46116.364
D14: EBITDA Margin | E14: (%) | F14: =F13/F10 -> 0.54678458 | G14: =G13/G10 -> 0.12940798 | H14: =H13/H10 -> 0.36175381 | I14: =I13/I10 -> 0.48483065 | J14: =J13/J10 -> 0.82102322 | K14: =K13/K10 -> 0.84745914 | L14: =L13/L10 -> 0.7692922 | M14: =M13/M10 -> 0.69471978 | ... P14: =P13/P10 -> 0.66554854
D15: EBIT | E15: ($M) | F15: =Schedules!F271 -> 9702 | G15: =Schedules!G271 -> -5745 | H15: =Schedules!H271 -> 1304 | I15: =Schedules!I271 -> 9770 | J15: =Schedules!J271 -> 96729 | K15: =Schedules!K271 -> 112554.22 | L15: =Schedules!L271 -> 56826.881 | M15: =Schedules!M271 -> 31859.501 | ... P15: =Schedules!P271 -> 22385.847
D16: EBIT Margin | E16: (%) | F16: =F15/F10 -> 0.31543013 | G16: =G15/G10 -> -0.36969112 | H16: =H15/H10 -> 0.051929433 | I16: =I15/I10 -> 0.2613837 | J16: =J15/J10 -> 0.75007561 | K16: =K15/K10 -> 0.77267841 | L16: =L15/L10 -> 0.61677998 | M16: =M15/M10 -> 0.45525324 | ... P16: =P15/P10 -> 0.32307118
D19: Effective Tax Rate | E19: (%) | F19: =Schedules!F160 -> 0.092780274 | G19: =Schedules!G160 -> -0.031283139 | H19: =Schedules!H160 -> 0.36370968 | I19: =Schedules!I160 -> 0.11642842 | J19: =Schedules!J160 -> 0.14388504 | K19: =Schedules!K160 -> 0.15 | L19: =Schedules!L160 -> 0.15 | M19: =Schedules!M160 -> 0.15 | ... P19: =Schedules!P160 -> 0.15
D20: Less: taxes on EBIT | E20: ($M) | F20: =-F19*F15 -> -900.15422 | G20: =-G19*G15 -> -179.72163 | H20: =-H19*H15 -> -474.27742 | I20: =-I19*I15 -> -1137.5057 | J20: =-J19*J15 -> -13917.856 | K20: =-K19*K15 -> -16883.134 | L20: =-L19*L15 -> -8524.0322 | M20: =-M19*M15 -> -4778.9251 | ... P20: =-P19*P15 -> -3357.8771
D21: NOPAT | E21: ($M) | F21: =F15+F20 -> 8801.8458 | G21: =G15+G20 -> -5924.7216 | H21: =H15+H20 -> 829.72258 | I21: =I15+I20 -> 8632.4943 | J21: =J15+J20 -> 82811.144 | K21: =K15+K20 -> 95671.091 | L21: =L15+L20 -> 48302.849 | M21: =M15+M20 -> 27080.576 | ... P21: =P15+P20 -> 19027.97
D22: Plus: depreciation and amortisation | E22: ($M) | F22: =Schedules!F300 -> 7116 | G22: =Schedules!G300 -> 7756 | H22: =Schedules!H300 -> 7780 | I22: =Schedules!I300 -> 8352 | J22: =Schedules!J300 -> 9149.3333 | K22: =Schedules!K300 -> 10893.13 | L22: =Schedules!L300 -> 14051.677 | M22: =Schedules!M300 -> 16758.331 | ... P22: =Schedules!P300 -> 23730.516
D23: Less: Net Capex | E23: ($M) | F23: =Schedules!F307+Schedules!F308 -> -11952 | G23: =Schedules!G307+Schedules!G308 -> -6966 | H23: =Schedules!H307+Schedules!H308 -> -8071 | I23: =Schedules!I307+Schedules!I308 -> -13852 | J23: =Schedules!J307+Schedules!J308 -> -27000 | K23: =Schedules!K307+Schedules!K308 -> -33503.552 | L23: =Schedules!L307+Schedules!L308 -> -29667.396 | M23: =Schedules!M307+Schedules!M308 -> -24465.683 | ... P23: =Schedules!P307+Schedules!P308 -> -22311.624
D24: Less: Increase in Working Capital | E24: ($M) | F24: =Schedules!F302 -> -1655 | G24: =Schedules!G302 -> -2094 | H24: =Schedules!H302 -> -2154 | I24: =Schedules!I302 -> -394 | J24: =Schedules!J302 -> -22780.007 | K24: =Schedules!K302 -> 1191.4891 | L24: =Schedules!L302 -> 8648.1835 | M24: =Schedules!M302 -> 3433.776 | ... P24: =Schedules!P302 -> 72.36719
D25: Unlevered FCF | E25: ($M) | F25: =SUM(F21:F24) -> 2310.8458 | G25: =SUM(G21:G24) -> -7228.7216 | H25: =SUM(H21:H24) -> -1615.2774 | I25: =SUM(I21:I24) -> 2738.4943 | J25: =SUM(J21:J24) -> 42180.471 | K25: =SUM(K21:K24) -> 74252.158 | L25: =SUM(L21:L24) -> 41335.314 | M25: =SUM(M21:M24) -> 22807 | ... P25: =SUM(P21:P24) -> 20519.229
D26: Cash Connversions | E26: (%) | F26: =F25/F13 -> 0.13740313 | G26: =G25/G13 -> -3.5945906 | H26: =H25/H13 -> -0.17781566 | I26: =I25/I13 -> 0.15111435 | J26: =J25/J13 -> 0.39838623 | K26: =K25/K13 -> 0.60148845 | L26: =L25/L13 -> 0.58318503 | M26: =M25/M13 -> 0.46910771 | ... P26: =P25/P13 -> 0.44494465
D28: Cash from Operations | E28: ($M) | F28: =Schedules!F304 -> 15181 | G28: =Schedules!G304 -> 1559 | H28: =Schedules!H304 -> 8507 | I28: =Schedules!I304 -> 17525 | J28: =Schedules!J304 -> 77967.981 | K28: =Schedules!K304 -> 110474.5 | L28: =Schedules!L304 -> 76088.994 | M28: =Schedules!M304 -> 53825.382 | ... P28: =Schedules!P304 -> 52358.268
D29: Less: SBC and after tax Net Interest income | E29: ($M) | F29: =-Schedules!F301-(Schedules!F275+Schedules!F276)*(1-F19) -> -429.62857 | G29: =-Schedules!G301-(Schedules!G275+Schedules!G276)*(1-G19) -> -678.50265 | H29: =-Schedules!H301-(Schedules!H275+Schedules!H276)*(1-H19) -> -812.00242 | I29: =-Schedules!I301-(Schedules!I275+Schedules!I276)*(1-I19) -> -988.78786 | J29: =-Schedules!J301-(Schedules!J275+Schedules!J276)*(1-J19) -> -1799.079 | K29: =-Schedules!K301-(Schedules!K275+Schedules!K276)*(1-K19) -> -2718.7864 | L29: =-Schedules!L301-(Schedules!L275+Schedules!L276)*(1-L19) -> -5086.2838 | M29: =-Schedules!M301-(Schedules!M275+Schedules!M276)*(1-M19) -> -6552.6992 | ... P29: =-Schedules!P301-(Schedules!P275+Schedules!P276)*(1-P19) -> -9527.4144
D30: Less: Capex | E30: ($M) | F30: =F23 -> -11952 | G30: =G23 -> -6966 | H30: =H23 -> -8071 | I30: =I23 -> -13852 | J30: =J23 -> -27000 | K30: =K23 -> -33503.552 | L30: =L23 -> -29667.396 | M30: =M23 -> -24465.683 | ... P30: =P23 -> -22311.624
D31: FCFF (CFO Route) | E31: ($M) | F31: =SUM(F28:F30) -> 2799.3714 | G31: =SUM(G28:G30) -> -6085.5027 | H31: =SUM(H28:H30) -> -376.00242 | I31: =SUM(I28:I30) -> 2684.2121 | J31: =SUM(J28:J30) -> 49168.902 | K31: =SUM(K28:K30) -> 74252.158 | L31: =SUM(L28:L30) -> 41335.314 | M31: =SUM(M28:M30) -> 22807 | ... P31: =SUM(P28:P30) -> 20519.229
D32: Check | E32: ($M) | F32: =F31-F25 -> 488.52565 | G32: =G31-G25 -> 1143.219 | H32: =H31-H25 -> 1239.275 | I32: =I31-I25 -> -54.282163 | J32: =J31-J25 -> 6988.4317 | K32: =K31-K25 -> 0 | L32: =L31-L25 -> 0 | M32: =M31-M25 -> 0 | ... P32: =P31-P25 -> 0
B38: Returns, Leverage and Market Data
F41: Actual | J41: Projected
E42: Units | F42: ='Raw Data'!E144 -> FY2022 | G42: ='Raw Data'!F144 -> FY2023 | H42: ='Raw Data'!G144 -> FY2024 | I42: ='Raw Data'!H144 -> FY2025 | J42: FY2026E | K42: =Assumptions!K24 -> FY2027E | L42: =Assumptions!L24 -> FY2028E | M42: =Assumptions!M24 -> FY2029E | N42: =Assumptions!N24 -> FY2030E | O42: =Assumptions!O24 -> FY2031E | P42: =Assumptions!P24 -> FY2032E
D45: NOPAT | E45: ($M) | F45: =F21 -> 8801.8458 | G45: =G21 -> -5924.7216 | H45: =H21 -> 829.72258 | I45: =I21 -> 8632.4943 | J45: =J21 -> 82811.144 | K45: =K21 -> 95671.091 | L45: =L21 -> 48302.849 | M45: =M21 -> 27080.576 | ... P45: =P21 -> 19027.97
D46: Invested Capital | E46: ($M) | F46: =Schedules!F351+Schedules!F357-Schedules!F334-Schedules!F335-Schedules!F342 -> 45835 | G46: =Schedules!G351+Schedules!G357-Schedules!G334-Schedules!G335-Schedules!G342 -> 47012 | H46: =Schedules!H351+Schedules!H357-Schedules!H334-Schedules!H335-Schedules!H342 -> 49376 | I46: =Schedules!I351+Schedules!I357-Schedules!I334-Schedules!I335-Schedules!I342 -> 56806 | J46: =Schedules!J351+Schedules!J357-Schedules!J334-Schedules!J335-Schedules!J342 -> 90361.674 | K46: =Schedules!K351+Schedules!K357-Schedules!K334-Schedules!K335-Schedules!K342 -> 111780.61 | L46: =Schedules!L351+Schedules!L357-Schedules!L334-Schedules!L335-Schedules!L342 -> 118748.14 | M46: =Schedules!M351+Schedules!M357-Schedules!M334-Schedules!M335-Schedules!M342 -> 123021.72 | ... P46: =Schedules!P351+Schedules!P357-Schedules!P334-Schedules!P335-Schedules!P342 -> 127806.82
D47: ROIC | E47: (%) | F47: =F45/F46 -> 0.19203329 | G47: =G45/G46 -> -0.12602573 | H47: =H45/H46 -> 0.016804168 | I47: =I45/I46 -> 0.15196448 | J47: =J45/J46 -> 0.91644102 | K47: =K45/K46 -> 0.85588273 | L47: =L45/L46 -> 0.4067672 | M47: =M45/M46 -> 0.22012842 | ... P47: =P45/P46 -> 0.1488807
D48: Net Debt/(net cash) | E48: ($M) | F48: =Schedules!F351-Schedules!F334-Schedules!F335-Schedules!F342 -> -4072 | G48: =Schedules!G351-Schedules!G334-Schedules!G335-Schedules!G342 -> 2892 | H48: =Schedules!H351-Schedules!H334-Schedules!H335-Schedules!H342 -> 4245 | I48: =Schedules!I351-Schedules!I334-Schedules!I335-Schedules!I342 -> 2641 | J48: =Schedules!J351-Schedules!J334-Schedules!J335-Schedules!J342 -> -45796.481 | K48: =Schedules!K351-Schedules!K334-Schedules!K335-Schedules!K342 -> -120680.43 | L48: =Schedules!L351-Schedules!L334-Schedules!L335-Schedules!L342 -> -164806.32 | M48: =Schedules!M351-Schedules!M334-Schedules!M335-Schedules!M342 -> -191640.75 | ... P48: =Schedules!P351-Schedules!P334-Schedules!P335-Schedules!P342 -> -272637.83
D49: Net Debt/EBITDA | E49: (x) | F49: =F48/F13 -> -0.24212154 | G49: =G48/G13 -> 1.4380905 | H49: =H48/H13 -> 0.46730515 | I49: =I48/I13 -> 0.14573447 | J49: =J48/J13 -> -0.43253874 | K49: =K48/K13 -> -0.97758616 | L49: =L48/L13 -> -2.3251929 | M49: =M48/M13 -> -3.9417791 | ... P49: =P48/P13 -> -5.9119542
D50: Interest Coverage | E50: (x) | F50: =F13/-Schedules!F276 -> 88.984127 | G50: =G13/-Schedules!G276 -> 5.1829897 | H50: =H13/-Schedules!H276 -> 16.163701 | I50: =I13/-Schedules!I276 -> 37.991614 | J50: =J13/-Schedules!J276 -> 998.8522 | K50: =K13/-Schedules!K276 -> 497.56294 | L50: =L13/-Schedules!L276 -> 285.68084 | M50: =M13/-Schedules!M276 -> 195.95747 | ... P50: =P13/-Schedules!P276 -> 194.04017
D51: D&A as % of operating expenses | E51: (%) | F51: =F22/-(Schedules!F260+Schedules!F268) -> 0.33795593 | G51: =G22/-(Schedules!G260+Schedules!G268) -> 0.36438807 | H51: =H22/-(Schedules!H260+Schedules!H268) -> 0.32679464 | I51: =I22/-(Schedules!I260+Schedules!I268) -> 0.30252101 | J51: =J22/-(Schedules!J260+Schedules!J268) -> 0.28387631 | K51: =K22/-(Schedules!K260+Schedules!K268) -> 0.32896446 | L51: =L22/-(Schedules!L260+Schedules!L268) -> 0.39797559 | M51: =M22/-(Schedules!M260+Schedules!M268) -> 0.43959242 | ... P51: =P22/-(Schedules!P260+Schedules!P268) -> 0.50592817
B53: Market Data (as of 15-Sep-2026)
D54: Share price | E54: ($) | J54: ='Raw Data'!D177 -> 927.6
D55: Shares outstanding | E55: (M sh) | J55: ='Raw Data'!D178 -> 1129.3932
D56: Market capitalisation | E56: ($M) | J56: =J54*J55 -> 1047625.1
D57: Net debt / (net cash), FY2026E | E57: ($M) | J57: =J48 -> -45796.481
D58: Enterprise value | E58: ($M) | J58: =J56+J57 -> 1001828.6
B60: Trading Multiples (today's price)
I61: Trailing | J61: Current | K61: Forward
E62: Basis | I62: =I42 -> FY2025 | J62: =J42 -> FY2026E | K62: =K42 -> FY2027E
D63: P / E | E63: (x) | I63: =$J$54/(Schedules!I281/Schedules!I285) -> 122.20986 | J63: =$J$54/(Schedules!J281/Schedules!J285) -> 12.871728 | K63: =$J$54/(Schedules!K281/Schedules!K285) -> 10.998127
D64: P / B (price to book) | E64: (x) | I64: =$J$56/Schedules!I357 -> 19.341366 | J64: =$J$56/Schedules!J357 -> 7.694178 | K64: =$J$56/Schedules!K357 -> 4.5066697
D65: P / S (price to sales) | E65: (x) | I65: =$J$56/Schedules!I259 -> 28.027853 | J65: =$J$56/Schedules!J259 -> 8.1237067 | K65: =$J$56/Schedules!K259 -> 7.1918872
D66: EV / EBITDA | E66: (x) | I66: =$J$58/I13 -> 55.282453 | J66: =$J$58/J13 -> 9.4620738 | K66: =$J$58/K13 -> 8.1154319
D67: EV / Sales | E67: (x) | I67: =$J$58/I10 -> 26.802627 | J67: =$J$58/J10 -> 7.7685823 | K67: =$J$58/K10 -> 6.8774969
D68: EV / unlevered FCF | E68: (x) | I68: =$J$58/I25 -> 365.83191 | J68: =$J$58/J25 -> 23.751006 | K68: =$J$58/K25 -> 13.492249

Sheet WACC
B3: Weighted Average Cost of Capital
E7: Units | F7: Value
C9: A. Cost of Equity (CAPM)
D10: Risk-free rate (10-year Treasury) | E10: (%) | F10: ='Raw Data'!D187 -> 0.0497
D11: Equity risk premium (implied) | E11: (%) | F11: ='Raw Data'!D188 -> 0.0414
D12: Regression beta (5-year monthly) | E12: (x) | F12: ='Raw Data'!D186 -> 2.22
D13: Market beta | E13: (x) | F13: 1
D14: Weight on regression beta (Blume) | E14: (%) | F14: 0.67
D15: Adjusted beta | E15: (x) | F15: =(F14*F12)+(1-F14)*F13 -> 1.8174
D16: Cost of equity | E16: (%) | F16: =F10+F11*F15 -> 0.12494036
C18: B. Cost of Debt
D19: Pre-tax cost of debt (BBB yield) | E19: (%) | F19: ='Raw Data'!D189 -> 0.059
D20: Tax rate | E20: (%) | F20: =Assumptions!K71 -> 0.15
D21: After-tax cost of debt | E21: (%) | F21: =F19*(1-F20) -> 0.05015
C23: C. Capital Structure (market values)
D24: Market value of equity | E24: ($M) | F24: =Model!J56 -> 1047625.1
D25: Total debt incl. finance leases, FY2026E | E25: ($M) | F25: =Schedules!J214 -> 5722
D26: Total capital | E26: ($M) | F26: =F24+F25 -> 1053347.1
D27: Equity weight (E/V) | E27: (%) | F27: =F24/F26 -> 0.99456779
D28: Debt weight (D/V) | E28: (%) | F28: =F25/F26 -> 0.0054322076
D29: Debt / equity (D/E) | E29: (%) | F29: =F25/F24 -> 0.0054618776
C31: D. WACC
D32: Equity: weight × cost of equity | E32: (%) | F32: =F27*F16 -> 0.12426166
D33: Debt: weight × after-tax cost of debt | E33: (%) | F33: =F28*F21 -> 0.00027242521
D34: WACC | E34: (%) | F34: =F32+F33 -> 0.12453408
C36: E. Industry Beta (bottom-up)
D37: Industry levered beta (US semiconductors) | E37: (x) | F37: ='Raw Data'!D191 -> 1.52
D38: Industry debt / equity | E38: (%) | F38: ='Raw Data'!D192 -> 0.0259
D39: Industry tax rate | E39: (%) | F39: ='Raw Data'!D193 -> 0.0511
D40: Unlevered beta | E40: (x) | F40: =F37/(1+(1-F39)*F38) -> 1.4835398 | G40: Industry Levered beta/(1+(after tax debt to equity ratio)
D41: Relevered beta at Micron's D/E | E41: (x) | F41: =F40*(1+F29*(1-F20)) -> 1.4904272 | G41: Levered beta = unlevered beta * (1+after tax debt to equity ratio)
C43: F. WACC by Beta Method
F44: Adjusted (base) | G44: Regression | H44: Industry
D45: Beta | E45: (x) | F45: =F15 -> 1.8174 | G45: =F12 -> 2.22 | H45: =F41 -> 1.4904272
D46: Cost of equity | E46: (%) | F46: =$F$10+F45*$F$11 -> 0.12494036 | G46: =$F$10+G45*$F$11 -> 0.141608 | H46: =$F$10+H45*$F$11 -> 0.11140369
D47: WACC | E47: (%) | F47: =F46*$F$27+$F$28*$F$21 -> 0.12453408 | G47: =G46*$F$27+$F$28*$F$21 -> 0.14111118 | H47: =H46*$F$27+$F$28*$F$21 -> 0.11107095

Sheet DCF
B3: Discounted Cash Flow
F6: Actual | J6: Projected
E7: Units | F7: =Model!F7 -> FY2022 | G7: =Model!G7 -> FY2023 | H7: =Model!H7 -> FY2024 | I7: =Model!I7 -> FY2025 | J7: =Model!J7 -> FY2026E | K7: =Model!K7 -> FY2027E | L7: =Model!L7 -> FY2028E | M7: =Model!M7 -> FY2029E | ... P7: =Model!P7 -> FY2032E
C9: Unlevered Free Cash Flow
D10: EBITDA | E10: ($M) | F10: =Model!F13 -> 16818 | G10: =Model!G13 -> 2011 | H10: =Model!H13 -> 9084 | I10: =Model!I13 -> 18122 | J10: =Model!J13 -> 105878.33 | K10: =Model!K13 -> 123447.35 | L10: =Model!L13 -> 70878.559 | M10: =Model!M13 -> 48617.832 | ... P10: =Model!P13 -> 46116.364
D11: NOPAT | E11: ($M) | F11: =Model!F21 -> 8801.8458 | G11: =Model!G21 -> -5924.7216 | H11: =Model!H21 -> 829.72258 | I11: =Model!I21 -> 8632.4943 | J11: =Model!J21 -> 82811.144 | K11: =Model!K21 -> 95671.091 | L11: =Model!L21 -> 48302.849 | M11: =Model!M21 -> 27080.576 | ... P11: =Model!P21 -> 19027.97
D12: Plus: depreciation and amortisation | E12: ($M) | F12: =Model!F22 -> 7116 | G12: =Model!G22 -> 7756 | H12: =Model!H22 -> 7780 | I12: =Model!I22 -> 8352 | J12: =Model!J22 -> 9149.3333 | K12: =Model!K22 -> 10893.13 | L12: =Model!L22 -> 14051.677 | M12: =Model!M22 -> 16758.331 | ... P12: =Model!P22 -> 23730.516
D13: Less: net capex | E13: ($M) | F13: =Model!F23 -> -11952 | G13: =Model!G23 -> -6966 | H13: =Model!H23 -> -8071 | I13: =Model!I23 -> -13852 | J13: =Model!J23 -> -27000 | K13: =Model!K23 -> -33503.552 | L13: =Model!L23 -> -29667.396 | M13: =Model!M23 -> -24465.683 | ... P13: =Model!P23 -> -22311.624
D14: Less: increase in working capital | E14: ($M) | F14: =Model!F24 -> -1655 | G14: =Model!G24 -> -2094 | H14: =Model!H24 -> -2154 | I14: =Model!I24 -> -394 | J14: =Model!J24 -> -22780.007 | K14: =Model!K24 -> 1191.4891 | L14: =Model!L24 -> 8648.1835 | M14: =Model!M24 -> 3433.776 | ... P14: =Model!P24 -> 72.36719
D15: Unlevered free cash flow | E15: ($M) | F15: =SUM(F11:F14) -> 2310.8458 | G15: =SUM(G11:G14) -> -7228.7216 | H15: =SUM(H11:H14) -> -1615.2774 | I15: =SUM(I11:I14) -> 2738.4943 | J15: =SUM(J11:J14) -> 42180.471 | K15: =SUM(K11:K14) -> 74252.158 | L15: =SUM(L11:L14) -> 41335.314 | M15: =SUM(M11:M14) -> 22807 | ... P15: =SUM(P11:P14) -> 20519.229
C17: Reinvestment and Returns
D18: Reinvestment (NOPAT less free cash flow) | E18: ($M) | F18: =F11-F15 -> 6491 | G18: =G11-G15 -> 1304 | H18: =H11-H15 -> 2445 | I18: =I11-I15 -> 5894 | J18: =J11-J15 -> 40630.674 | K18: =K11-K15 -> 21418.933 | L18: =L11-L15 -> 6967.5347 | M18: =M11-M15 -> 4273.5759 | ... P18: =P11-P15 -> -1491.2592
D19: Reinvestment rate | E19: (%) | F19: =F18/F11 -> 0.73745896 | G19: =G18/G11 -> -0.22009473 | H19: =H18/H11 -> 2.9467681 | I19: =I18/I11 -> 0.68276906 | J19: =J18/J11 -> 0.49064258 | K19: =K18/K11 -> 0.22388093 | L19: =L18/L11 -> 0.14424687 | M19: =M18/M11 -> 0.15780964 | ... P19: =P18/P11 -> -0.078371955
D20: ROIC | E20: (%) | F20: =Model!F47 -> 0.19203329 | G20: =Model!G47 -> -0.12602573 | H20: =Model!H47 -> 0.016804168 | I20: =Model!I47 -> 0.15196448 | J20: =Model!J47 -> 0.91644102 | K20: =Model!K47 -> 0.85588273 | L20: =Model!L47 -> 0.4067672 | M20: =Model!M47 -> 0.22012842 | ... P20: =Model!P47 -> 0.1488807
C22: Discounting (valuation date: FY2026 year end)
D23: Year | E23: (years) | J23: 0 | K23: =J23+1 -> 1 | L23: =K23+1 -> 2 | M23: =L23+1 -> 3 | N23: =M23+1 -> 4 | O23: =N23+1 -> 5 | P23: =O23+1 -> 6
D24: Discount period (mid-year) | E24: (years) | K24: =K23-$F$37 -> 0.5 | L24: =L23-$F$37 -> 1.5 | M24: =M23-$F$37 -> 2.5 | N24: =N23-$F$37 -> 3.5 | O24: =O23-$F$37 -> 4.5 | P24: =P23-$F$37 -> 5.5
D25: Discount factor | E25: (x) | K25: =1/(1+$F$36)^K24 -> 0.94300433 | L25: =1/(1+$F$36)^L24 -> 0.83857337 | M25: =1/(1+$F$36)^M24 -> 0.74570738 | N25: =1/(1+$F$36)^N24 -> 0.66312564 | O25: =1/(1+$F$36)^O24 -> 0.58968923 | P25: =1/(1+$F$36)^P24 -> 0.52438538
D26: PV of unlevered free cash flow | E26: ($M) | K26: =K15*K25 -> 70020.107 | L26: =L15*L25 -> 34662.694 | M26: =M15*M25 -> 17007.348 | N26: =N15*N25 -> 14748.358 | O26: =O15*O25 -> 12899.729 | P26: =P15*P25 -> 10759.984
B31: Terminal Value and Valuation
E34: Units | F34: Value
C35: A. Valuation Inputs
D36: WACC | E36: (%) | F36: =WACC!F34 -> 0.12453408
D37: Mid-year adjustment | E37: (years) | F37: =Assumptions!K93 -> 0.5
D38: Exit multiple: median FY2021-FY2025 EV / EBITDA | E38: (x) | F38: =MEDIAN('Raw Data'!D172:H172) -> 7.77
C40: B. Long-Run Growth (computed)
D41: Reinvestment rate, FY2030E-FY2032E average | E41: (%) | F41: =AVERAGE(N19:P19) -> 0.053566274
D42: Return on new capital, FY2030E-FY2032E average ROIC | E42: (%) | F42: =AVERAGE(N20:P20) -> 0.1802593
D43: Fundamental growth (reinvestment rate × return) | E43: (%) | F43: =F41*F42 -> 0.0096558191
D44: Ceiling: 10-year Treasury yield | E44: (%) | F44: ='Raw Data'!D187 -> 0.0497
D45: Long-run growth used | E45: (%) | F45: =MIN(F43,F44) -> 0.0096558191
C47: C. Terminal Value (end of FY2032E)
F48: Perpetuity growth | G48: Exit multiple
D49: FY2032E base: NOPAT (F) / EBITDA (G) | E49: ($M) | F49: =P11 -> 19027.97 | G49: =P10 -> 46116.364
D50: Terminal free cash flow, FY2033E | E50: ($M) | F50: =F49*(1+F45)*(1-F45/F42) -> 18182.601
D51: Exit multiple | E51: (x) | G51: =F38 -> 7.77
D52: Terminal value | E52: ($M) | F52: =F50/(F36-F45) -> 158277.13 | G52: =G49*G51 -> 358324.14
D53: Discount factor, end of FY2032E | E53: (x) | F53: =1/(1+$F$36)^$P$23 -> 0.49449768 | G53: =1/(1+$F$36)^$P$23 -> 0.49449768
D54: PV of terminal value | E54: ($M) | F54: =F52*F53 -> 78267.672 | G54: =G52*G53 -> 177190.46
C56: D. Enterprise Value to Value per Share
D57: PV of free cash flow, FY2027E-FY2032E | E57: ($M) | F57: =SUM($K$26:$P$26) -> 160098.22 | G57: =SUM($K$26:$P$26) -> 160098.22
D58: PV of terminal value | E58: ($M) | F58: =F54 -> 78267.672 | G58: =G54 -> 177190.46
D59: Enterprise value | E59: ($M) | F59: =F57+F58 -> 238365.89 | G59: =G57+G58 -> 337288.68
D60: Plus: cash and investments, FY2026E | E60: ($M) | F60: =Schedules!$J$334+Schedules!$J$335+Schedules!$J$342 -> 51518.481 | G60: =Schedules!$J$334+Schedules!$J$335+Schedules!$J$342 -> 51518.481
D61: Less: total debt, FY2026E | E61: ($M) | F61: =-Schedules!$J$351 -> -5722 | G61: =-Schedules!$J$351 -> -5722
D62: Equity value | E62: ($M) | F62: =SUM(F59:F61) -> 284162.37 | G62: =SUM(G59:G61) -> 383085.16
D63: Diluted shares, FY2026E | E63: (M sh) | F63: =Schedules!$J$285 -> 1150 | G63: =Schedules!$J$285 -> 1150
D64: Value per share | E64: ($) | F64: =F62/F63 -> 247.09772 | G64: =G62/G63 -> 333.11753
D65: Share price (15-Sep-2026) | E65: ($) | F65: =Model!$J$54 -> 927.6 | G65: =Model!$J$54 -> 927.6
D66: Upside / (downside) | E66: (%) | F66: =F64/F65-1 -> -0.73361609 | G66: =G64/G65-1 -> -0.64088235
C68: E. Cross-Checks
D69: Terminal value as % of enterprise value | E69: (%) | F69: =F58/F59 -> 0.32835097 | G69: =G58/G59 -> 0.5253377
D70: Implied EV / EBITDA | E70: (x) | F70: =F52/$P$10 -> 3.432125 | G70: =G52/$P$10 -> 7.77
D71: Implied perpetual growth | E71: (%) | F71: =F45 -> 0.0096558191 | G71: =(G52*$F$36-$P$15)/(G52+$P$15) -> 0.063626135
C73: F. What the Market Implies (today's price)
D74: Market value of equity at today's price | E74: ($M) | F74: =F65*F63 -> 1066740
D75: Market enterprise value | E75: ($M) | F75: =F74-F60-F61 -> 1020943.5
D76: Less: PV of free cash flow, FY2027E-FY2032E | E76: ($M) | F76: =-F57 -> -160098.22
D77: Terminal value the price requires | E77: ($M) | F77: =(F75+F76)/F53 -> 1740848
D78: Market-implied perpetual growth | E78: (%) | F78: =(F77*F36-P15)/(F77+P15) -> 0.11143371
D79: Market-implied exit multiple | E79: (x) | F79: =F77/P10 -> 37.74903

Sheet Comps
B3: Comparable Companies
B5: US$ millions at the 15-Sep-2026 close and FX rates (Micron's price date). LTM = last twelve months reported by 15-Sep-2026, i.e. to June 2026. Peer data: Raw Data rows 201-216.
D7: Company | E7: Ccy | F7: FX per US$ | G7: Market cap ($M) | H7: Net debt / (cash) ($M) | I7: Enterprise value ($M) | J7: LTM revenue ($M) | K7: LTM EBITDA ($M) | L7: EBITDA margin | M7: EV / Sales | N7: EV / EBITDA | O7: P / E | P7: P / B
C9: Memory and storage peers (used in the median)
D10: ='Raw Data'!B201&" ("&'Raw Data'!C201&")" -> Samsung Electronics (005930.KS) | E10: KRW | F10: ='Raw Data'!$D$214 -> 1361.84 | G10: ='Raw Data'!F201/F10 -> 1165605.6 | H10: ='Raw Data'!G201/F10 -> -123061.45 | I10: ='Raw Data'!H201/F10 -> 1042544.1 | J10: ='Raw Data'!J201/F10 -> 356334.08 | K10: ='Raw Data'!K201/F10 -> 166774.36 | L10: =K10/J10 -> 0.46802811 | M10: =I10/J10 -> 2.9257492 | N10: =I10/K10 -> 6.2512253 | O10: =IF('Raw Data'!L201<=0,"n.m.",'Raw Data'!D201/'Raw Data'!L201) -> 12.197606 | P10: ='Raw Data'!F201/'Raw Data'!M201 -> 2.7401017
D11: ='Raw Data'!B202&" ("&'Raw Data'!C202&")" -> SK hynix (000660.KS) | E11: KRW | F11: ='Raw Data'!$D$214 -> 1361.84 | G11: ='Raw Data'!F202/F11 -> 904504.42 | H11: ='Raw Data'!G202/F11 -> -49102.685 | I11: ='Raw Data'!H202/F11 -> 855401.74 | J11: ='Raw Data'!J202/F11 -> 138907.65 | K11: ='Raw Data'!K202/F11 -> 105445.57 | L11: =K11/J11 -> 0.75910557 | M11: =I11/J11 -> 6.1580605 | N11: =I11/K11 -> 8.1122584 | O11: =IF('Raw Data'!L202<=0,"n.m.",'Raw Data'!D202/'Raw Data'!L202) -> 7.4256893 | P11: ='Raw Data'!F202/'Raw Data'!M202 -> 4.6891404
D12: ='Raw Data'!B203&" ("&'Raw Data'!C203&")" -> Western Digital (WDC) | E12: USD | F12: ='Raw Data'!$D$216 -> 1 | G12: ='Raw Data'!F203/F12 -> 154204.87 | H12: ='Raw Data'!G203/F12 -> -388 | I12: ='Raw Data'!H203/F12 -> 153816.87 | J12: ='Raw Data'!J203/F12 -> 12920 | K12: ='Raw Data'!K203/F12 -> 5000 | L12: =K12/J12 -> 0.3869969 | M12: =I12/J12 -> 11.90533 | N12: =I12/K12 -> 30.763373 | O12: =IF('Raw Data'!L203<=0,"n.m.",'Raw Data'!D203/'Raw Data'!L203) -> 16.967051 | P12: ='Raw Data'!F203/'Raw Data'!M203 -> 17.404613
D13: ='Raw Data'!B204&" ("&'Raw Data'!C204&")" -> SanDisk (SNDK) | E13: USD | F13: ='Raw Data'!$D$216 -> 1 | G13: ='Raw Data'!F204/F13 -> 224154.38 | H13: ='Raw Data'!G204/F13 -> -6340 | I13: ='Raw Data'!H204/F13 -> 217814.38 | J13: ='Raw Data'!J204/F13 -> 20250 | K13: ='Raw Data'!K204/F13 -> 12620 | L13: =K13/J13 -> 0.62320988 | M13: =I13/J13 -> 10.756266 | N13: =I13/K13 -> 17.259459 | O13: =IF('Raw Data'!L204<=0,"n.m.",'Raw Data'!D204/'Raw Data'!L204) -> 20.755152 | P13: ='Raw Data'!F204/'Raw Data'!M204 -> 14.241066
D14: ='Raw Data'!B205&" ("&'Raw Data'!C205&")" -> Kioxia Holdings (285A.T) | E14: JPY | F14: ='Raw Data'!$D$215 -> 155.11 | G14: ='Raw Data'!F205/F14 -> 182842.66 | H14: ='Raw Data'!G205/F14 -> 271.22687 | I14: ='Raw Data'!H205/F14 -> 183113.89 | J14: ='Raw Data'!J205/F14 -> 24240.861 | K14: ='Raw Data'!K205/F14 -> 15279.479 | L14: =K14/J14 -> 0.63031915 | M14: =I14/J14 -> 7.5539348 | N14: =I14/K14 -> 11.984302 | O14: =IF('Raw Data'!L205<=0,"n.m.",'Raw Data'!D205/'Raw Data'!L205) -> 20.727443 | P14: ='Raw Data'!F205/'Raw Data'!M205 -> 11.816969
D15: ='Raw Data'!B206&" ("&'Raw Data'!C206&")" -> Seagate Technology (STX) | E15: USD | F15: ='Raw Data'!$D$216 -> 1 | G15: ='Raw Data'!F206/F15 -> 175501.88 | H15: ='Raw Data'!G206/F15 -> 2190 | I15: ='Raw Data'!H206/F15 -> 177691.88 | J15: ='Raw Data'!J206/F15 -> 12200 | K15: ='Raw Data'!K206/F15 -> 4500 | L15: =K15/J15 -> 0.36885246 | M15: =I15/J15 -> 14.564908 | N15: =I15/K15 -> 39.487084 | O15: =IF('Raw Data'!L206<=0,"n.m.",'Raw Data'!D206/'Raw Data'!L206) -> 55.525899 | P15: ='Raw Data'!F206/'Raw Data'!M206 -> 80.876441
D16: Median | L16: =MEDIAN(L10:L15) -> 0.54561899 | M16: =MEDIAN(M10:M15) -> 9.1551002 | N16: =MEDIAN(N10:N15) -> 14.621881 | O16: =MEDIAN(O10:O15) -> 18.847247 | P16: =MEDIAN(P10:P15) -> 13.029017
D17: 25th percentile | L17: =_xlfn.QUARTILE.INC(L10:L15,1) -> 0.40725471 | M17: =_xlfn.QUARTILE.INC(M10:M15,1) -> 6.5070291 | N17: =_xlfn.QUARTILE.INC(N10:N15,1) -> 9.0802692 | O17: =_xlfn.QUARTILE.INC(O10:O15,1) -> 13.389967 | P17: =_xlfn.QUARTILE.INC(P10:P15,1) -> 6.4710975
D18: 75th percentile | L18: =_xlfn.QUARTILE.INC(L10:L15,3) -> 0.62854183 | M18: =_xlfn.QUARTILE.INC(M10:M15,3) -> 11.618064 | N18: =_xlfn.QUARTILE.INC(N10:N15,3) -> 27.387395 | O18: =_xlfn.QUARTILE.INC(O10:O15,3) -> 20.748225 | P18: =_xlfn.QUARTILE.INC(P10:P15,3) -> 16.613726
D19: DRAM makers only (Samsung, SK hynix): average | L19: =AVERAGE(L10:L11) -> 0.61356684 | M19: =AVERAGE(M10:M11) -> 4.5419048 | N19: =AVERAGE(N10:N11) -> 7.1817418 | O19: =AVERAGE(O10:O11) -> 9.8116477 | P19: =AVERAGE(P10:P11) -> 3.7146211
C21: Broader semiconductors (reference only, not in the median)
D22: ='Raw Data'!B207&" ("&'Raw Data'!C207&")" -> Intel (INTC) | E22: USD | F22: ='Raw Data'!$D$216 -> 1 | G22: ='Raw Data'!F207/F22 -> 509985 | H22: ='Raw Data'!G207/F22 -> 20560 | I22: ='Raw Data'!H207/F22 -> 530545 | J22: ='Raw Data'!J207/F22 -> 57030 | K22: ='Raw Data'!K207/F22 -> 16840 | L22: =K22/J22 -> 0.29528318 | M22: =I22/J22 -> 9.3029107 | N22: =I22/K22 -> 31.505048 | O22: =IF('Raw Data'!L207<=0,"n.m.",'Raw Data'!D207/'Raw Data'!L207) -> n.m. | P22: ='Raw Data'!F207/'Raw Data'!M207 -> 4.9445899
D23: ='Raw Data'!B208&" ("&'Raw Data'!C208&")" -> Texas Instruments (TXN) | E23: USD | F23: ='Raw Data'!$D$216 -> 1 | G23: ='Raw Data'!F208/F23 -> 240577.45 | H23: ='Raw Data'!G208/F23 -> 7050 | I23: ='Raw Data'!H208/F23 -> 247627.45 | J23: ='Raw Data'!J208/F23 -> 19450 | K23: ='Raw Data'!K208/F23 -> 9520 | L23: =K23/J23 -> 0.48946015 | M23: =I23/J23 -> 12.731488 | N23: =I23/K23 -> 26.011287 | O23: =IF('Raw Data'!L208<=0,"n.m.",'Raw Data'!D208/'Raw Data'!L208) -> 40.034954 | P23: ='Raw Data'!F208/'Raw Data'!M208 -> 13.357993
C25: Micron (same 15-Sep-2026 price; multiples from the Model tab)
D26: Micron (MU): trailing, FY2025 | E26: USD | F26: ='Raw Data'!$D$216 -> 1 | G26: =Model!$J$56 -> 1047625.1 | H26: =Model!$J$57 -> -45796.481 | I26: =Model!$J$58 -> 1001828.6 | J26: =Model!I10 -> 37378 | K26: =Model!I13 -> 18122 | L26: =K26/J26 -> 0.48483065 | M26: =Model!I67 -> 26.802627 | N26: =Model!I66 -> 55.282453 | O26: =Model!I63 -> 122.20986 | P26: =Model!I64 -> 19.341366
D27: Micron (MU): current, FY2026E | E27: USD | F27: ='Raw Data'!$D$216 -> 1 | G27: =Model!$J$56 -> 1047625.1 | H27: =Model!$J$57 -> -45796.481 | I27: =Model!$J$58 -> 1001828.6 | J27: =Model!J10 -> 128959 | K27: =Model!J13 -> 105878.33 | L27: =K27/J27 -> 0.82102322 | M27: =Model!J67 -> 7.7685823 | N27: =Model!J66 -> 9.4620738 | O27: =Model!J63 -> 12.871728 | P27: =Model!J64 -> 7.694178
D28: Micron (MU): forward, FY2027E (live case) | E28: USD | F28: ='Raw Data'!$D$216 -> 1 | G28: =Model!$J$56 -> 1047625.1 | H28: =Model!$J$57 -> -45796.481 | I28: =Model!$J$58 -> 1001828.6 | J28: =Model!K10 -> 145667.62 | K28: =Model!K13 -> 123447.35 | L28: =K28/J28 -> 0.84745914 | M28: =Model!K67 -> 6.8774969 | N28: =Model!K66 -> 8.1154319 | O28: =Model!K63 -> 10.998127 | P28: =Model!K64 -> 4.5066697
C30: What peer multiples imply for Micron (applied to FY2026E, the year closest to the peers' LTM)
D31: Method | F31: Multiple | G31: Micron FY2026E ($M) | H31: Implied EV ($M) | I31: Implied equity ($M) | J31: Value per share | K31: vs. price
D32: EV / EBITDA: peer median x FY2026E EBITDA | F32: =N16 -> 14.621881 | G32: =Model!J13 -> 105878.33 | H32: =F32*G32 -> 1548140.3 | I32: =H32+DCF!$F$60+DCF!$F$61 -> 1593936.8 | J32: =I32/DCF!$F$63 -> 1386.032 | K32: =J32/Model!$J$54-1 -> 0.49421305
D33: EV / EBITDA: DRAM makers' average x FY2026E EBITDA | F33: =N19 -> 7.1817418 | G33: =Model!J13 -> 105878.33 | H33: =F33*G33 -> 760390.86 | I33: =H33+DCF!$F$60+DCF!$F$61 -> 806187.34 | J33: =I33/DCF!$F$63 -> 701.03247 | K33: =J33/Model!$J$54-1 -> -0.24425133
D34: P / E: peer median x FY2026E net income | F34: =O16 -> 18.847247 | G34: =Schedules!J281 -> 82874.655 | H34: n.a. | I34: =F34*G34 -> 1561959.1 | J34: =I34/DCF!$F$63 -> 1358.2253 | K34: =J34/Model!$J$54-1 -> 0.46423599
D35: P / B: peer median x FY2026E book equity | F35: =P16 -> 13.029017 | G35: =Schedules!J357 -> 136158.15 | H35: n.a. | I35: =F35*G35 -> 1774007 | J35: =I35/DCF!$F$63 -> 1542.6148 | K35: =J35/Model!$J$54-1 -> 0.6630172
D36: DCF base case (perpetuity growth), for comparison | H36: =DCF!F59 -> 238365.89 | I36: =DCF!F62 -> 284162.37 | J36: =DCF!F64 -> 247.09772 | K36: =DCF!F66 -> -0.73361609
C38: Reading it
D39: ="Peers trade at a median "&TEXT(N16,"0.0x")&" LTM EBITDA, but on peak-cycle earnings: memory prices are near a record high. Applying that to Micron's FY2026E (also a peak year) gives a high value; it assumes today's margins last." -> Peers trade at a median 14.6x LTM EBITDA, but on peak-cycle earnings: memory prices are near a record high. Applying that to Micron's FY2026E (also a peak year) gives a high value; it assumes today's margins last.
D40: ="The DCF exit multiple stays at Micron's own mid-cycle median of "&TEXT(DCF!F38,"0.00x")&" (FY2021-FY2025). The DRAM makers closest to Micron (Samsung, SK hynix) trade at "&TEXT(N19,"0.0x")&" EV/EBITDA." -> The DCF exit multiple stays at Micron's own mid-cycle median of 7.77x (FY2021-FY2025). The DRAM makers closest to Micron (Samsung, SK hynix) trade at 7.2x EV/EBITDA.
D41: Peer financials are local-currency figures converted at one 15-Sep-2026 spot rate; multiples are currency-free (calculated in local currency), so the FX rate only affects the US$ columns.

Sheet Scenarios
B3: Scenarios and Sensitivities
B5: Bear, Base and Bull are recorded by setting the scenario switch (Assumptions D7) to each case and pasting the live column as values. Column J is live and follows the switch; column K shows it still matches the recorded case.
E7: Units | F7: Bear | G7: Base | H7: Bull | I7: Probability-weighted | J7: ="Live: "&INDEX(Assumptions!$C$27:$C$29,Assumptions!$D$7) -> Live: Base | K7: Live less recorded
C9: A. Valuation (DCF)
D10: Value per share: perpetuity growth (the answer) | E10: ($) | F10: 127.24045 | G10: 247.09772 | H10: 515.08876 | I10: =SUMPRODUCT($F$41:$H$41,F10:H10) -> 284.13116 | J10: =DCF!F64 -> 247.09772 | K10: =ROUND(J10-INDEX(F10:H10,Assumptions!$D$7),6) -> 0
D11: Value per share: exit multiple (cross-check) | E11: ($) | F11: 198.20869 | G11: 333.11753 | H11: 582.57188 | I11: =SUMPRODUCT($F$41:$H$41,F11:H11) -> 361.75391 | J11: =DCF!G64 -> 333.11753 | K11: =ROUND(J11-INDEX(F11:H11,Assumptions!$D$7),6) -> 0
D12: Upside / (downside) vs. share price, perpetuity growth | E12: (%) | F12: -0.86282832 | G12: -0.73361609 | H12: -0.44470811 | I12: =I10/I38-1 -> -0.69369215 | J12: =DCF!F66 -> -0.73361609 | K12: =ROUND(J12-INDEX(F12:H12,Assumptions!$D$7),6) -> 0
D13: PV of free cash flow, FY2027E-FY2032E | E13: ($M) | F13: 80248.854 | G13: 160098.22 | H13: 282252.44 | I13: =SUMPRODUCT($F$41:$H$41,F13:H13) -> 170674.43 | J13: =DCF!F57 -> 160098.22 | K13: =ROUND(J13-INDEX(F13:H13,Assumptions!$D$7),6) -> 0
D14: PV of terminal value | E14: ($M) | F14: 20281.188 | G14: 78267.672 | H14: 264303.15 | I14: =SUMPRODUCT($F$41:$H$41,F14:H14) -> 110279.92 | J14: =DCF!F58 -> 78267.672 | K14: =ROUND(J14-INDEX(F14:H14,Assumptions!$D$7),6) -> 0
D15: Enterprise value | E15: ($M) | F15: 100530.04 | G15: 238365.89 | H15: 546555.59 | I15: =SUMPRODUCT($F$41:$H$41,F15:H15) -> 280954.35 | J15: =DCF!F59 -> 238365.89 | K15: =ROUND(J15-INDEX(F15:H15,Assumptions!$D$7),6) -> 0
D16: Net cash, FY2026E (cash and investments less debt) | E16: ($M) | F16: 45796.481 | G16: 45796.481 | H16: 45796.481 | I16: =SUMPRODUCT($F$41:$H$41,F16:H16) -> 45796.481 | J16: =DCF!F60+DCF!F61 -> 45796.481 | K16: =ROUND(J16-INDEX(F16:H16,Assumptions!$D$7),6) -> 0
D17: Equity value | E17: ($M) | F17: 146326.52 | G17: 284162.37 | H17: 592352.08 | I17: =SUMPRODUCT($F$41:$H$41,F17:H17) -> 326750.84 | J17: =DCF!F62 -> 284162.37 | K17: =ROUND(J17-INDEX(F17:H17,Assumptions!$D$7),6) -> 0
D18: Diluted shares, FY2026E | E18: (M sh) | F18: 1150 | G18: 1150 | H18: 1150 | I18: =SUMPRODUCT($F$41:$H$41,F18:H18) -> 1150 | J18: =DCF!F63 -> 1150 | K18: =ROUND(J18-INDEX(F18:H18,Assumptions!$D$7),6) -> 0
D19: Terminal value as % of enterprise value | E19: (%) | F19: 0.20174256 | G19: 0.32835097 | H19: 0.48357963 | J19: =DCF!F69 -> 0.32835097 | K19: =ROUND(J19-INDEX(F19:H19,Assumptions!$D$7),6) -> 0
D20: Implied EV / EBITDA, FY2027E | E20: (x) | F20: 1.2782422 | G20: 1.9309113 | H20: 3.46259 | J20: =DCF!F59/DCF!K10 -> 1.9309113 | K20: =ROUND(J20-INDEX(F20:H20,Assumptions!$D$7),6) -> 0
D21: Implied P / B, FY2026E book equity | E21: (x) | F21: 1.0746806 | G21: 2.0870022 | H21: 4.3504708 | J21: =DCF!F62/Schedules!J357 -> 2.0870022 | K21: =ROUND(J21-INDEX(F21:H21,Assumptions!$D$7),6) -> 0
D22: Long-run growth g (computed) | E22: (%) | F22: -0.011055966 | G22: 0.0096558191 | H22: 0.034885871 | J22: =DCF!F45 -> 0.0096558191 | K22: =ROUND(J22-INDEX(F22:H22,Assumptions!$D$7),6) -> 0
C24: B. The Operating Story
D25: Revenue, FY2027E | E25: ($M) | F25: 99989.595 | G25: 145667.62 | H25: 180920.79 | J25: =Model!K10 -> 145667.62 | K25: =ROUND(J25-INDEX(F25:H25,Assumptions!$D$7),6) -> 0
D26: Revenue, FY2032E | E26: ($M) | F26: 48433.435 | G26: 69290.759 | H26: 112695.57 | J26: =Model!P10 -> 69290.759 | K26: =ROUND(J26-INDEX(F26:H26,Assumptions!$D$7),6) -> 0
D27: Revenue growth a year, FY2026E-FY2032E | E27: (%) | F27: -0.15059346 | G27: -0.098351474 | H27: -0.022216896 | J27: =(Model!P10/Model!J10)^(1/6)-1 -> -0.098351474 | K27: =ROUND(J27-INDEX(F27:H27,Assumptions!$D$7),6) -> 0
D28: Gross margin, FY2032E | E28: (%) | F28: 0.35785989 | G28: 0.48951564 | H28: 0.64408201 | J28: =Schedules!P262 -> 0.48951564 | K28: =ROUND(J28-INDEX(F28:H28,Assumptions!$D$7),6) -> 0
D29: EBITDA, FY2027E | E29: ($M) | F29: 78647.102 | G29: 123447.35 | H29: 157845.89 | J29: =Model!K13 -> 123447.35 | K29: =ROUND(J29-INDEX(F29:H29,Assumptions!$D$7),6) -> 0
D30: EBITDA margin, FY2032E | E30: (%) | F30: 0.54754629 | G30: 0.66554854 | H30: 0.78961992 | J30: =Model!P14 -> 0.66554854 | K30: =ROUND(J30-INDEX(F30:H30,Assumptions!$D$7),6) -> 0
D31: Capex % of revenue, FY2027E-FY2032E average | E31: (%) | F31: 0.4 | G31: 0.33833333 | H31: 0.28666667 | J31: =AVERAGE(Assumptions!K46:P46) -> 0.33833333 | K31: =ROUND(J31-INDEX(F31:H31,Assumptions!$D$7),6) -> 0
D32: Unlevered free cash flow, FY2027E-FY2032E total | E32: ($M) | F32: 97580.903 | G32: 203029.84 | H32: 372613.95 | J32: =SUM(DCF!K15:P15) -> 203029.84 | K32: =ROUND(J32-INDEX(F32:H32,Assumptions!$D$7),6) -> 0
D33: Diluted EPS, FY2032E | E33: ($) | F33: 8.0386276 | G33: 22.87435 | H33: 55.357861 | J33: =Schedules!P286 -> 22.87435 | K33: =ROUND(J33-INDEX(F33:H33,Assumptions!$D$7),6) -> 0
C35: C. Valuation Inputs (same in every case)
D36: WACC | E36: (%) | F36: 0.12453408 | G36: 0.12453408 | H36: 0.12453408 | J36: =DCF!F36 -> 0.12453408 | K36: =ROUND(J36-INDEX(F36:H36,Assumptions!$D$7),6) -> 0
D37: Exit EV / EBITDA multiple | E37: (x) | F37: 7.77 | G37: 7.77 | H37: 7.77 | J37: =DCF!F38 -> 7.77 | K37: =ROUND(J37-INDEX(F37:H37,Assumptions!$D$7),6) -> 0
D38: Share price (15-Sep-2026) | E38: ($) | F38: 927.6 | G38: 927.6 | H38: 927.6 | I38: =G38 -> 927.6 | J38: =Model!J54 -> 927.6 | K38: =ROUND(J38-INDEX(F38:H38,Assumptions!$D$7),6) -> 0
C40: D. Probability Weighting and Target Price
D41: Probability weight | E41: (%) | F41: 0.25 | G41: 0.5 | H41: 0.25 | I41: =SUM(F41:H41) -> 1
D42: Target price (probability-weighted value per share, perpetuity growth) | E42: ($) | I42: =I10 -> 284.13116
D43: Upside / (downside) to target | E43: (%) | I43: =I42/I38-1 -> -0.69369215
D44: Rating band: Buy above | E44: (%) | I44: 0.15
D45: Rating band: Sell below | E45: (%) | I45: -0.15
D46: Rating | I46: =IF(I43>I44,"BUY",IF(I43<I45,"SELL","HOLD")) -> SELL
C48: ="E. Sensitivity: Value per Share (live case: "&INDEX(Assumptions!$C$27:$C$29,Assumptions!$D$7)&")" -> E. Sensitivity: Value per Share (live case: Base)
D49: Perpetuity growth: WACC (rows) x long-run growth g (columns) | L49: Exit multiple: WACC (rows) x exit EV/EBITDA (columns)
E50: WACC \ g | F50: 0 | G50: 0.005 | H50: =DCF!$F$45 -> 0.0096558191 | I50: 0.02 | J50: 0.03 | K50: WACC \ x | L50: 5 | M50: 6.5 | N50: =DCF!$F$38 -> 7.77 | O50: 10 | P50: 13
E51: 0.105 | F51: =(SUMPRODUCT(DCF!$K$15:$P$15,(1+$E51)^-DCF!$K$24:$P$24)+DCF!$P$11*(1+F$50)*(1-F$50/DCF!$F$42)/($E51-F$50)*(1+$E51)^-DCF!$P$23+DCF!$F$60+DCF!$F$61)/DCF!$F$63 -> 270.28082 | G51: =(SUMPRODUCT(DCF!$K$15:$P$15,(1+$E51)^-DCF!$K$24:$P$24)+DCF!$P$11*(1+G$50)*(1-G$50/DCF!$F$42)/($E51-G$50)*(1+$E51)^-DCF!$P$23+DCF!$F$60+DCF!$F$61)/DCF!$F$63 -> 272.52969 | H51: =(SUMPRODUCT(DCF!$K$15:$P$15,(1+$E51)^-DCF!$K$24:$P$24)+DCF!$P$11*(1+H$50)*(1-H$50/DCF!$F$42)/($E51-H$50)*(1+$E51)^-DCF!$P$23+DCF!$F$60+DCF!$F$61)/DCF!$F$63 -> 274.81206 | I51: =(SUMPRODUCT(DCF!$K$15:$P$15,(1+$E51)^-DCF!$K$24:$P$24)+DCF!$P$11*(1+I$50)*(1-I$50/DCF!$F$42)/($E51-I$50)*(1+$E51)^-DCF!$P$23+DCF!$F$60+DCF!$F$61)/DCF!$F$63 -> 280.68579 | J51: =(SUMPRODUCT(DCF!$K$15:$P$15,(1+$E51)^-DCF!$K$24:$P$24)+DCF!$P$11*(1+J$50)*(1-J$50/DCF!$F$42)/($E51-J$50)*(1+$E51)^-DCF!$P$23+DCF!$F$60+DCF!$F$61)/DCF!$F$63 -> 287.76759 | K51: =E51 -> 0.105 | L51: =(SUMPRODUCT(DCF!$K$15:$P$15,(1+$K51)^-DCF!$K$24:$P$24)+DCF!$P$10*L$50*(1+$K51)^-DCF!$P$23+DCF!$F$60+DCF!$F$61)/DCF!$F$63 -> 293.8601 | M51: =(SUMPRODUCT(DCF!$K$15:$P$15,(1+$K51)^-DCF!$K$24:$P$24)+DCF!$P$10*M$50*(1+$K51)^-DCF!$P$23+DCF!$F$60+DCF!$F$61)/DCF!$F$63 -> 326.90274 | N51: =(SUMPRODUCT(DCF!$K$15:$P$15,(1+$K51)^-DCF!$K$24:$P$24)+DCF!$P$10*N$50*(1+$K51)^-DCF!$P$23+DCF!$F$60+DCF!$F$61)/DCF!$F$63 -> 354.87885 | O51: =(SUMPRODUCT(DCF!$K$15:$P$15,(1+$K51)^-DCF!$K$24:$P$24)+DCF!$P$10*O$50*(1+$K51)^-DCF!$P$23+DCF!$F$60+DCF!$F$61)/DCF!$F$63 -> 404.00225 | P51: =(SUMPRODUCT(DCF!$K$15:$P$15,(1+$K51)^-DCF!$K$24:$P$24)+DCF!$P$10*P$50*(1+$K51)^-DCF!$P$23+DCF!$F$60+DCF!$F$61)/DCF!$F$63 -> 470.08754
E52: 0.115 | F52: =(SUMPRODUCT(DCF!$K$15:$P$15,(1+$E52)^-DCF!$K$24:$P$24)+DCF!$P$11*(1+F$50)*(1-F$50/DCF!$F$42)/($E52-F$50)*(1+$E52)^-DCF!$P$23+DCF!$F$60+DCF!$F$61)/DCF!$F$63 -> 256.15571 | G52: =(SUMPRODUCT(DCF!$K$15:$P$15,(1+$E52)^-DCF!$K$24:$P$24)+DCF!$P$11*(1+G$50)*(1-G$50/DCF!$F$42)/($E52-G$50)*(1+$E52)^-DCF!$P$23+DCF!$F$60+DCF!$F$61)/DCF!$F$63 -> 257.76842 | H52: =(SUMPRODUCT(DCF!$K$15:$P$15,(1+$E52)^-DCF!$K$24:$P$24)+DCF!$P$11*(1+H$50)*(1-H$50/DCF!$F$42)/($E52-H$50)*(1+$E52)^-DCF!$P$23+DCF!$F$60+DCF!$F$61)/DCF!$F$63 -> 259.38738 | I52: =(SUMPRODUCT(DCF!$K$15:$P$15,(1+$E52)^-DCF!$K$24:$P$24)+DCF!$P$11*(1+I$50)*(1-I$50/DCF!$F$42)/($E52-I$50)*(1+$E52)^-DCF!$P$23+DCF!$F$60+DCF!$F$61)/DCF!$F$63 -> 263.47427 | J52: =(SUMPRODUCT(DCF!$K$15:$P$15,(1+$E52)^-DCF!$K$24:$P$24)+DCF!$P$11*(1+J$50)*(1-J$50/DCF!$F$42)/($E52-J$50)*(1+$E52)^-DCF!$P$23+DCF!$F$60+DCF!$F$61)/DCF!$F$63 -> 268.25645 | K52: =E52 -> 0.115 | L52: =(SUMPRODUCT(DCF!$K$15:$P$15,(1+$K52)^-DCF!$K$24:$P$24)+DCF!$P$10*L$50*(1+$K52)^-DCF!$P$23+DCF!$F$60+DCF!$F$61)/DCF!$F$63 -> 285.62539 | M52: =(SUMPRODUCT(DCF!$K$15:$P$15,(1+$K52)^-DCF!$K$24:$P$24)+DCF!$P$10*M$50*(1+$K52)^-DCF!$P$23+DCF!$F$60+DCF!$F$61)/DCF!$F$63 -> 316.92935 | N52: =(SUMPRODUCT(DCF!$K$15:$P$15,(1+$K52)^-DCF!$K$24:$P$24)+DCF!$P$10*N$50*(1+$K52)^-DCF!$P$23+DCF!$F$60+DCF!$F$61)/DCF!$F$63 -> 343.43337 | O52: =(SUMPRODUCT(DCF!$K$15:$P$15,(1+$K52)^-DCF!$K$24:$P$24)+DCF!$P$10*O$50*(1+$K52)^-DCF!$P$23+DCF!$F$60+DCF!$F$61)/DCF!$F$63 -> 389.97192 | P52: =(SUMPRODUCT(DCF!$K$15:$P$15,(1+$K52)^-DCF!$K$24:$P$24)+DCF!$P$10*P$50*(1+$K52)^-DCF!$P$23+DCF!$F$60+DCF!$F$61)/DCF!$F$63 -> 452.57984
E53: =DCF!$F$36 -> 0.12453408 | F53: =(SUMPRODUCT(DCF!$K$15:$P$15,(1+$E53)^-DCF!$K$24:$P$24)+DCF!$P$11*(1+F$50)*(1-F$50/DCF!$F$42)/($E53-F$50)*(1+$E53)^-DCF!$P$23+DCF!$F$60+DCF!$F$61)/DCF!$F$63 -> 244.73967 | G53: =(SUMPRODUCT(DCF!$K$15:$P$15,(1+$E53)^-DCF!$K$24:$P$24)+DCF!$P$11*(1+G$50)*(1-G$50/DCF!$F$42)/($E53-G$50)*(1+$E53)^-DCF!$P$23+DCF!$F$60+DCF!$F$61)/DCF!$F$63 -> 245.922 | H53: =(SUMPRODUCT(DCF!$K$15:$P$15,(1+$E53)^-DCF!$K$24:$P$24)+DCF!$P$11*(1+H$50)*(1-H$50/DCF!$F$42)/($E53-H$50)*(1+$E53)^-DCF!$P$23+DCF!$F$60+DCF!$F$61)/DCF!$F$63 -> 247.09772 | I53: =(SUMPRODUCT(DCF!$K$15:$P$15,(1+$E53)^-DCF!$K$24:$P$24)+DCF!$P$11*(1+I$50)*(1-I$50/DCF!$F$42)/($E53-I$50)*(1+$E53)^-DCF!$P$23+DCF!$F$60+DCF!$F$61)/DCF!$F$63 -> 250.01735 | J53: =(SUMPRODUCT(DCF!$K$15:$P$15,(1+$E53)^-DCF!$K$24:$P$24)+DCF!$P$11*(1+J$50)*(1-J$50/DCF!$F$42)/($E53-J$50)*(1+$E53)^-DCF!$P$23+DCF!$F$60+DCF!$F$61)/DCF!$F$63 -> 253.34957 | K53: =E53 -> 0.12453408 | L53: =(SUMPRODUCT(DCF!$K$15:$P$15,(1+$K53)^-DCF!$K$24:$P$24)+DCF!$P$10*L$50*(1+$K53)^-DCF!$P$23+DCF!$F$60+DCF!$F$61)/DCF!$F$63 -> 278.18859 | M53: =(SUMPRODUCT(DCF!$K$15:$P$15,(1+$K53)^-DCF!$K$24:$P$24)+DCF!$P$10*M$50*(1+$K53)^-DCF!$P$23+DCF!$F$60+DCF!$F$61)/DCF!$F$63 -> 307.9335 | N53: =(SUMPRODUCT(DCF!$K$15:$P$15,(1+$K53)^-DCF!$K$24:$P$24)+DCF!$P$10*N$50*(1+$K53)^-DCF!$P$23+DCF!$F$60+DCF!$F$61)/DCF!$F$63 -> 333.11753 | O53: =(SUMPRODUCT(DCF!$K$15:$P$15,(1+$K53)^-DCF!$K$24:$P$24)+DCF!$P$10*O$50*(1+$K53)^-DCF!$P$23+DCF!$F$60+DCF!$F$61)/DCF!$F$63 -> 377.3383 | P53: =(SUMPRODUCT(DCF!$K$15:$P$15,(1+$K53)^-DCF!$K$24:$P$24)+DCF!$P$10*P$50*(1+$K53)^-DCF!$P$23+DCF!$F$60+DCF!$F$61)/DCF!$F$63 -> 436.82814
E54: 0.135 | F54: =(SUMPRODUCT(DCF!$K$15:$P$15,(1+$E54)^-DCF!$K$24:$P$24)+DCF!$P$11*(1+F$50)*(1-F$50/DCF!$F$42)/($E54-F$50)*(1+$E54)^-DCF!$P$23+DCF!$F$60+DCF!$F$61)/DCF!$F$63 -> 234.00154 | G54: =(SUMPRODUCT(DCF!$K$15:$P$15,(1+$E54)^-DCF!$K$24:$P$24)+DCF!$P$11*(1+G$50)*(1-G$50/DCF!$F$42)/($E54-G$50)*(1+$E54)^-DCF!$P$23+DCF!$F$60+DCF!$F$61)/DCF!$F$63 -> 234.8446 | H54: =(SUMPRODUCT(DCF!$K$15:$P$15,(1+$E54)^-DCF!$K$24:$P$24)+DCF!$P$11*(1+H$50)*(1-H$50/DCF!$F$42)/($E54-H$50)*(1+$E54)^-DCF!$P$23+DCF!$F$60+DCF!$F$61)/DCF!$F$63 -> 235.67469 | I54: =(SUMPRODUCT(DCF!$K$15:$P$15,(1+$E54)^-DCF!$K$24:$P$24)+DCF!$P$11*(1+I$50)*(1-I$50/DCF!$F$42)/($E54-I$50)*(1+$E54)^-DCF!$P$23+DCF!$F$60+DCF!$F$61)/DCF!$F$63 -> 237.70161 | J54: =(SUMPRODUCT(DCF!$K$15:$P$15,(1+$E54)^-DCF!$K$24:$P$24)+DCF!$P$11*(1+J$50)*(1-J$50/DCF!$F$42)/($E54-J$50)*(1+$E54)^-DCF!$P$23+DCF!$F$60+DCF!$F$61)/DCF!$F$63 -> 239.95754 | K54: =E54 -> 0.135 | L54: =(SUMPRODUCT(DCF!$K$15:$P$15,(1+$K54)^-DCF!$K$24:$P$24)+DCF!$P$10*L$50*(1+$K54)^-DCF!$P$23+DCF!$F$60+DCF!$F$61)/DCF!$F$63 -> 270.46008 | M54: =(SUMPRODUCT(DCF!$K$15:$P$15,(1+$K54)^-DCF!$K$24:$P$24)+DCF!$P$10*M$50*(1+$K54)^-DCF!$P$23+DCF!$F$60+DCF!$F$61)/DCF!$F$63 -> 298.59679 | N54: =(SUMPRODUCT(DCF!$K$15:$P$15,(1+$K54)^-DCF!$K$24:$P$24)+DCF!$P$10*N$50*(1+$K54)^-DCF!$P$23+DCF!$F$60+DCF!$F$61)/DCF!$F$63 -> 322.4192 | O54: =(SUMPRODUCT(DCF!$K$15:$P$15,(1+$K54)^-DCF!$K$24:$P$24)+DCF!$P$10*O$50*(1+$K54)^-DCF!$P$23+DCF!$F$60+DCF!$F$61)/DCF!$F$63 -> 364.24911 | P54: =(SUMPRODUCT(DCF!$K$15:$P$15,(1+$K54)^-DCF!$K$24:$P$24)+DCF!$P$10*P$50*(1+$K54)^-DCF!$P$23+DCF!$F$60+DCF!$F$61)/DCF!$F$63 -> 420.52253
E55: 0.145 | F55: =(SUMPRODUCT(DCF!$K$15:$P$15,(1+$E55)^-DCF!$K$24:$P$24)+DCF!$P$11*(1+F$50)*(1-F$50/DCF!$F$42)/($E55-F$50)*(1+$E55)^-DCF!$P$23+DCF!$F$60+DCF!$F$61)/DCF!$F$63 -> 225.13317 | G55: =(SUMPRODUCT(DCF!$K$15:$P$15,(1+$E55)^-DCF!$K$24:$P$24)+DCF!$P$11*(1+G$50)*(1-G$50/DCF!$F$42)/($E55-G$50)*(1+$E55)^-DCF!$P$23+DCF!$F$60+DCF!$F$61)/DCF!$F$63 -> 225.7419 | H55: =(SUMPRODUCT(DCF!$K$15:$P$15,(1+$E55)^-DCF!$K$24:$P$24)+DCF!$P$11*(1+H$50)*(1-H$50/DCF!$F$42)/($E55-H$50)*(1+$E55)^-DCF!$P$23+DCF!$F$60+DCF!$F$61)/DCF!$F$63 -> 226.33564 | I55: =(SUMPRODUCT(DCF!$K$15:$P$15,(1+$E55)^-DCF!$K$24:$P$24)+DCF!$P$11*(1+I$50)*(1-I$50/DCF!$F$42)/($E55-I$50)*(1+$E55)^-DCF!$P$23+DCF!$F$60+DCF!$F$61)/DCF!$F$63 -> 227.76253 | J55: =(SUMPRODUCT(DCF!$K$15:$P$15,(1+$E55)^-DCF!$K$24:$P$24)+DCF!$P$11*(1+J$50)*(1-J$50/DCF!$F$42)/($E55-J$50)*(1+$E55)^-DCF!$P$23+DCF!$F$60+DCF!$F$61)/DCF!$F$63 -> 229.3139 | K55: =E55 -> 0.145 | L55: =(SUMPRODUCT(DCF!$K$15:$P$15,(1+$K55)^-DCF!$K$24:$P$24)+DCF!$P$10*L$50*(1+$K55)^-DCF!$P$23+DCF!$F$60+DCF!$F$61)/DCF!$F$63 -> 263.47356 | M55: =(SUMPRODUCT(DCF!$K$15:$P$15,(1+$K55)^-DCF!$K$24:$P$24)+DCF!$P$10*M$50*(1+$K55)^-DCF!$P$23+DCF!$F$60+DCF!$F$61)/DCF!$F$63 -> 290.16768 | N55: =(SUMPRODUCT(DCF!$K$15:$P$15,(1+$K55)^-DCF!$K$24:$P$24)+DCF!$P$10*N$50*(1+$K55)^-DCF!$P$23+DCF!$F$60+DCF!$F$61)/DCF!$F$63 -> 312.7687 | O55: =(SUMPRODUCT(DCF!$K$15:$P$15,(1+$K55)^-DCF!$K$24:$P$24)+DCF!$P$10*O$50*(1+$K55)^-DCF!$P$23+DCF!$F$60+DCF!$F$61)/DCF!$F$63 -> 352.45395 | P55: =(SUMPRODUCT(DCF!$K$15:$P$15,(1+$K55)^-DCF!$K$24:$P$24)+DCF!$P$10*P$50*(1+$K55)^-DCF!$P$23+DCF!$F$60+DCF!$F$61)/DCF!$F$63 -> 405.84218
D56: Same cash flows as the DCF tab; only the discount rate and the terminal assumption change. Shaded cell = the DCF tab's answer.
C58: F. Chart Data for the Executive Summary (links only)
D59: Exhibit 1: valuation range | F59: Low | G59: High | H59: Range | J59: Price line x | K59: Target line x | L59: Line y | M59: Bar label | N59: Legend text
D60: DCF, perpetuity growth (Bear to Bull) | F60: =F10 -> 127.24045 | G60: =H10 -> 515.08876 | H60: =G60-F60 -> 387.84831 | J60: =$F$66 -> 927.6 | K60: =$G$66 -> 284.13116 | L60: 0 | M60: =TEXT(F60,"$#,##0")&" – "&TEXT(G60,"$#,##0") -> $127 – $515 | N60: ="Share price ("&TEXT($F$66,"$#,##0.00")&")" -> Share price ($927.60)
D61: DCF, exit multiple (Bear to Bull) | F61: =F11 -> 198.20869 | G61: =H11 -> 582.57188 | H61: =G61-F61 -> 384.36319 | J61: =$F$66 -> 927.6 | K61: =$G$66 -> 284.13116 | L61: 1 | M61: =TEXT(F61,"$#,##0")&" – "&TEXT(G61,"$#,##0") -> $198 – $583 | N61: ="Target price ("&TEXT($G$66,"$#,##0.00")&")" -> Target price ($284.13)
D62: DCF sensitivity, Base (WACC 10.5-14.5%, g 0-3%) | F62: =MIN(F51:J55) -> 225.13317 | G62: =MAX(F51:J55) -> 287.76759 | H62: =G62-F62 -> 62.634414 | M62: =TEXT(F62,"$#,##0")&" – "&TEXT(G62,"$#,##0") -> $225 – $288
D63: Comps: DRAM makers' EV/EBITDA (Samsung to SK hynix) | F63: =(MIN(Comps!N10:N11)*Model!J13+DCF!F60+DCF!F61)/DCF!F63 -> 615.36157 | G63: =(MAX(Comps!N10:N11)*Model!J13+DCF!F60+DCF!F61)/DCF!F63 -> 786.70337 | H63: =G63-F63 -> 171.3418 | M63: =TEXT(F63,"$#,##0")&" – "&TEXT(G63,"$#,##0") -> $615 – $787
D64: Comps: peer EV/EBITDA, 25th-75th percentile | F64: =(Comps!N17*Model!J13+DCF!F60+DCF!F61)/DCF!F63 -> 875.8263 | G64: =(Comps!N18*Model!J13+DCF!F60+DCF!F61)/DCF!F63 -> 2561.3289 | H64: =G64-F64 -> 1685.5026 | M64: =TEXT(F64,"$#,##0")&" – "&TEXT(G64,"$#,##0") -> $876 – $2,561
D65: Comps: peer P/E, 25th-75th percentile | F65: =Comps!O17*Schedules!J281/DCF!F63 -> 964.94689 | G65: =Comps!O18*Schedules!J281/DCF!F63 -> 1495.2191 | H65: =G65-F65 -> 530.2722 | M65: =TEXT(F65,"$#,##0")&" – "&TEXT(G65,"$#,##0") -> $965 – $1,495
D66: Share price (15-Sep-2026) / target price | F66: =I38 -> 927.6 | G66: =I42 -> 284.13116
D68: Exhibit 3: enterprise value to equity value bridge (Base) | F68: Start | G68: Bar | H68: End
D69: PV of FCF FY27-32 | F69: 0 | G69: =G13 -> 160098.22 | H69: =F69+G69 -> 160098.22
D70: PV of terminal value | F70: =G13 -> 160098.22 | G70: =G14 -> 78267.672 | H70: =F70+G70 -> 238365.89
D71: Enterprise value | F71: 0 | G71: =G15 -> 238365.89 | H71: =F71+G71 -> 238365.89
D72: Plus: net cash | F72: =G15 -> 238365.89 | G72: =G16 -> 45796.481 | H72: =F72+G72 -> 284162.37
D73: Equity value | F73: 0 | G73: =G17 -> 284162.37 | H73: =F73+G73 -> 284162.37
D75: Exhibit 4: value per share by case vs. share price | F75: Value per share | G75: Share price
D76: Bear | F76: =F10 -> 127.24045 | G76: =$I$38 -> 927.6
D77: Base | F77: =G10 -> 247.09772 | G77: =$I$38 -> 927.6
D78: Bull | F78: =H10 -> 515.08876 | G78: =$I$38 -> 927.6
D79: Probability-weighted | F79: =I10 -> 284.13116 | G79: =$I$38 -> 927.6
D81: Exhibit 2: EBITDA margin labels (Base)
F82: =TEXT('Executive Summary'!D27,"0%") -> 55% | G82: =TEXT('Executive Summary'!E27,"0%") -> 13% | H82: =TEXT('Executive Summary'!F27,"0%") -> 36% | I82: =TEXT('Executive Summary'!G27,"0%") -> 48% | J82: =TEXT('Executive Summary'!H27,"0%") -> 82% | K82: =TEXT('Executive Summary'!I27,"0%") -> 85% | L82: =TEXT('Executive Summary'!J27,"0%") -> 77% | M82: =TEXT('Executive Summary'!K27,"0%") -> 69% | ... P82: =TEXT('Executive Summary'!N27,"0%") -> 67%

Sheet Checks
B3: Model Checks
B5: Every check should show OK. Values are the size of the error (0 = ties exactly) unless stated.
D7: Check | E7: Units | F7: Value | G7: Tolerance | H7: Status | I7: What it tests
C9: Raw Data (as reported, FY2021-FY2025)
D10: Balance sheet balances | E10: ($M) | F10: =SUMPRODUCT(ABS('Raw Data'!D67:H67-'Raw Data'!D80:H80-'Raw Data'!D89:H89)) -> 0 | G10: 0.5 | H10: =IF(F10<=G10,"OK","CHECK") -> OK | I10: Total assets - total liabilities - total equity, every year
D11: Net income: income statement = cash flow statement | E11: ($M) | F11: =SUMPRODUCT(ABS('Raw Data'!D34:H34-'Raw Data'!D96:H96)) -> 0 | G11: 0.5 | H11: =IF(F11<=G11,"OK","CHECK") -> OK | I11: The two statements report the same net income
D12: Revenue by product adds up | E12: ($M) | F12: =SUMPRODUCT(ABS('Raw Data'!D162:H162-'Raw Data'!D18:H18)) -> 0 | G12: 0.5 | H12: =IF(F12<=G12,"OK","CHECK") -> OK | I12: DRAM + NAND + Other = total revenue
C14: Forecast (Schedules, Model, DCF)
D15: Balance sheet balances, every year | E15: ($M) | F15: =MAX(INDEX(ABS(Schedules!F361:P361),0)) -> 0 | G15: 0.5 | H15: =IF(F15<=G15,"OK","CHECK") -> OK | I15: Schedules row 361: assets - liabilities - equity, FY2022A-FY2032E
D16: Free cash flow: two routes agree, FY2027E-FY2032E | E16: ($M) | F16: =MAX(INDEX(ABS(Model!K32:P32),0)) -> 0 | G16: 0.5 | H16: =IF(F16<=G16,"OK","CHECK") -> OK | I16: Model row 32: CFO route less NOPAT route
D17: DCF free cash flow = Model free cash flow | E17: ($M) | F17: =MAX(INDEX(ABS(DCF!F15:P15-Model!F25:P25),0)) -> 0 | G17: 0.5 | H17: =IF(F17<=G17,"OK","CHECK") -> OK | I17: DCF row 15 equals Model row 25 in every year
D18: Revolver never drawn | E18: ($M) | F18: =MAX(INDEX(ABS(Schedules!K196:P196),0)) -> 0 | G18: 0.5 | H18: =IF(F18<=G18,"OK","CHECK") -> OK | I18: Cash covers every outflow, so the $2.0bn revolver stays at 0
C20: Valuation
D21: WACC weights add to 100% | E21: (%) | F21: =ABS(WACC!F27+WACC!F28-1) -> 0 | G21: 0.0001 | H21: =IF(F21<=G21,"OK","CHECK") -> OK | I21: Equity weight + debt weight = 1
D22: Long-run growth below WACC | E22: (%) | F22: =MAX(0,DCF!F45-DCF!F36) -> 0 | G22: 0 | H22: =IF(F22<=G22,"OK","CHECK") -> OK | I22: Perpetuity formula only works if g < WACC
D23: Probability weights add to 100% | E23: (%) | F23: =ABS(SUM(Scenarios!F41:H41)-1) -> 0 | G23: 0.0001 | H23: =IF(F23<=G23,"OK","CHECK") -> OK | I23: Bear + Base + Bull = 100%
D24: Recorded case matches the live model | E24: ($) | F24: =MAX(INDEX(ABS(Scenarios!K10:K38),0)) -> 0 | G24: 0.01 | H24: =IF(F24<=G24,"OK","CHECK") -> OK | I24: Scenarios column K: re-record the cases if this fails
D25: Workbook saved on the Base case | E25: (case) | F25: =ABS(Assumptions!D7-2) -> 0 | G25: 0 | H25: =IF(F25<=G25,"OK","CHECK") -> OK | I25: The Executive Summary sensitivity and Comps forward row show the live case
D26: Peer data complete | E26: (cells) | F26: =72-COUNT('Raw Data'!D201:H208,'Raw Data'!J201:M208) -> 0 | G26: 0 | H26: =IF(F26<=G26,"OK","CHECK") -> OK | I26: 8 peers x 9 data cells in Raw Data
D28: Overall | H28: =IF(COUNTIF(H10:H26,"CHECK")=0,"ALL CHECKS PASS",COUNTIF(H10:H26,"CHECK")&" CHECK(S) FAIL") -> ALL CHECKS PASS

Sheet Sources
B2: Sources
B5: Item | C5: Value | D5: As of | E5: Source | F5: Link
B6: Share price (close) | C6: $927.60 | D6: 15-Sep-2026 | E6: stockanalysis.com | F6: https://stockanalysis.com/stocks/MU/
B7: Shares outstanding | C7: 1,129.4M | D7: 17-Jun-2026 | E7: Micron 10-Q Q3 FY26 cover page | F7: https://www.sec.gov/Archives/edgar/data/0000723125/000072312526000015/mu-20260528.htm
B8: Levered beta (5-yr monthly) | C8: 2.22 | D8: 15-Sep-2026 | E8: stockanalysis.com / Yahoo Finance | F8: https://stockanalysis.com/stocks/MU/
B9: 10-year Treasury yield | C9: 4.97% | D9: 14-Sep-2026 | E9: FRED series DGS10 | F9: https://fred.stlouisfed.org/series/DGS10
B10: Equity risk premium (implied) | C10: 4.14% | D10: 01-Sep-2026 | E10: Damodaran, NYU Stern | F10: https://pages.stern.nyu.edu/~adamodar/New_Home_Page/home.htm
B11: Pre-tax cost of debt (BBB index) | C11: 5.90% | D11: 14-Sep-2026 | E11: FRED series BAMLC0A4CBBBEY | F11: https://fred.stlouisfed.org/series/BAMLC0A4CBBBEY
B12: Credit rating - S&P | C12: BBB, outlook positive | D12: 26-May-2026 | E12: S&P Global Ratings | F12: https://cbonds.com/news/3941503/
B13: Credit rating - Moody's | C13: Baa2, outlook stable | D13: 08-Jan-2026 | E13: Moody's Investors Service | F13: https://www.moodys.com/credit-ratings/Micron-Technology-Inc-credit-rating-491900
B14: Financial statements FY2021-FY2025 | C14: 10-K filings | D14: FY2025 | E14: Micron 10-K | F14: https://www.sec.gov/cgi-bin/browse-edgar?action=getcompany&CIK=0000723125&type=10-K
B15: Q1-Q3 FY2026 and 9M data | C15: 10-Q filings | D15: 28-May-2026 | E15: Micron 10-Q Q3 FY26 | F15: https://www.sec.gov/Archives/edgar/data/0000723125/000072312526000015/mu-20260528.htm
B16: Industry beta, D/E, tax rate (US semiconductors) | C16: 1.52 · 2.59% · 5.11% | D16: Jan-2026 | E16: Damodaran, Betas by Sector (US) | F16: https://pages.stern.nyu.edu/~adamodar/New_Home_Page/datafile/Betas.html
B17: EV / EBITDA history, FY2021-FY2025 | C17: 6.25 · 3.52 · 19.33 · 12.30 · 7.77x | D17: Fiscal year ends | E17: stockanalysis.com, financial ratios (annual) | F17: https://stockanalysis.com/stocks/mu/financials/ratios/
B18: Peer market data and LTM financials (8 companies) | C18: see Raw Data 201-208 | D18: 46280 | E18: stockanalysis.com statistics and price history | F18: https://stockanalysis.com/stocks/wdc/statistics/
B19: FX rates KRW and JPY per US$ | C19: 1,361.84 · 155.11 | D19: 46280 | E19: FRED H.10 (DEXKOUS, DEXJPUS) | F19: https://fred.stlouisfed.org/series/DEXKOUS
